Workbook

Sheet NEW POOL
A1: 2025 PRICING MASTER - September
A3: CUSTOMER NAME: | B3: Bishop
A4: CITY: | B4: Indian Land
A5: Silt Fence: | B5: 1 | C5: "1" if Silt Fence is required
A7: Perimeter: | B7: 104 | C7: LNFT | D7: Max Width: | E7: 16 | F7: FT | J7: =IF(B$21+B$22+B$23>0,1,0) -> 0
A8: Surface Area: | B8: 576 | C8: SQFT | D8: Max Length: | E8: 36 | F8: FT | G8: `
A9: Shallow Depth: | B9: 3.5 | C9: FT | D9: Decking: | E9: 834 | F9: SQFT | G9: 817 | H9: 713
A10: End Depth: | B10: 7 | C10: FT | D10: Travel: | E10: 0 | F10: MILES
A11: Total Step & Bench: | B11: 70 | C11: LNFT | D11: Pool to Street: | E11: 0 | F11: ( 1 if 251 to 300, 2 if 300 to 350)
A12: Tanning Shelf: | B12: 0 | C12: 1 for Yes, 0 for No
D13: Approx. Gallons: | E13: =_xlfn.CEILING.MATH(((B8*((B9+B10)/2))*7.6),10)-(B12*850) -> 22990 | F13: DO NOT ADJUST GALLONS HERE!
A14: Spa Length: | B14: 0
A15: Spa Width: | B15: 0
A16: Spa Shape: | B16: 0 | C16: ( 1 for Round, 2 for Square )
A17: Spa Perimeter: | B17: =ROUNDUP(IF(B16=1,(B14*3.14),(B14*2+B15*2)),0) -> 0 | C17: DO NOT CHANGE HERE!
A18: Raised Spa?: | B18: 0 | C18: ( 1 for Yes, 0 for No) | E18: (Raised Spa = +18")
A19: Raised Spa Facing: | B19: 0 | C19: ( 1=Tile / 2=Ledgstone / 3=Stacked Stone)
A21: Fiberglass - Small | B21: =IF(A21="Fiberglass - Small",0,1) -> 0
A22: Fiberglass - Medium | B22: 0
A23: Fiberglass - Large | B23: =IF(A23="Fiberglass - Large",0,1) -> 0
A24: Standard Finish | B24: 0
A25: No Spa | B25: =IF(A25="No Spa",0,1) -> 0
A26: Add Spillover | B26: 0
A27: No Tanning | B27: =IF(A27="No Tanning",0,1) -> 0
A28: No Crane | B28: =IF(A28="No Crane",0,1) -> 0
A30: EXCAVATION
B31: LNFT | C31: FACING
A32: 6" RBB: | B32: 0 | C32: 0 | D32: ( 1=Tile / 2=Panel Ledge / 3=Stacked Stone)
A33: 12" RBB: | B33: 0 | C33: 0
A34: 18" RBB: | B34: 0 | C34: 0
A35: 24" RBB: | B35: 0 | C35: 0
A36: 30" RBB: | B36: 0 | C36: 0
A37: 36" RBB: | B37: 0 | C37: 0
A38: Total SQFT of RBB: | B38: =SHOT!L10 -> 0 | C38: DO NOT CHANGE HERE!
C39: FACING
A40: # of Columns | B40: 0 | C40: 0 | D40: =D32 -> ( 1=Tile / 2=Panel Ledge / 3=Stacked Stone)
A41: Coumn Width: | B41: 0 | C41: FT
A42: Column Depth: | B42: 0 | C42: FT
A43: Column Height: | B43: 0 | C43: FT
A45: Add'l Site Prep: | B45: 0 | C45: Hours
A46: Gravel Install: | B46: 1 | C46: Enter "1" to Select
A47: Dirt Haul: | B47: 1 | C47: Enter "1" to Select
A48: Add'l Bench: | B48: =IF(B11>20,B11-20,0) -> 50 | C48: DO NOT CHANGE HERE!
A49: Automatic Cover: | B49: 0 | C49: Enter "1" to Select
A51: Double Curtain: | B51: 0 | C51: LNFT
A53: Soil Sample / Engineer | B53: 1 | C53: Enter "1" to Select
A55: PLUMBING
A57: Add'l Skimmer: | B57: 0 | C57: (1) is Included
A58: Skimmer Run: | B58: 60 | C58: Total - All Skimmers
A59: Main Drain Run: | B59: 70 | C59: Main Drain to EQ
A60: Cleaner Run: | B60: 0 | C60: Pool Center to EQ
A61: Auto-Fill Run: | B61: 0 | C61: Hose Bibb to AWL
A62: Water Feature (1) Run: | B62: 0 | C62: Water Feature to EQ
A63: Water Feature (2) Run: | B63: 0 | C63: Water Feature to EQ
A64: Water Feature (3) Run: | B64: 0 | C64: Water Feature to EQ
A65: Water Feature (4) Run: | B65: 0 | C65: Water Feature to EQ
A66: I/F Valve to EQ: | B66: 0 | C66: Valve to EQ
A67: I/F Valve to Pool: | B67: 0 | C67: Valve to Pool
A68: Gas Run: | B68: 0 | C68: Meter to Heater
A69: Spa Run: | B69: 0 | C69: Spa to EQ
A71: Electrical Run: | B71: 60 | C71: House Panel to EQ | E71: 60+90
A72: Light Run: | B72: 135 | C72: All Lights to EQ
A73: Heatpump Electical: | B73: 0 | C73: Total Run
A75: TILE / COPING / DECKING
A77: Add'l Tile: | B77: 0 | C77: LNFT for spillway or infinity edge
A79: Add Trim Tile to Steps & Bench | B79: 0 | C79: Gunite Pools Only
A81: Level 1 Tile | B81: =IF((B82+B83)=0,"INCLUDED",0) -> INCLUDED
A82: Upgrade Tile - Level 2 | B82: 0
A83: Upgrade Tile - Level 3 | B83: 0
A85: Flagstone Coping: | B85: 0 | C85: Enter "1" to Select
A87: Paver Coping: | B87: 0 | C87: Enter "1" to Select
A88: Paver Decking: | B88: 1 | C88: Enter "1" to Select
A90: Travertine Coping - Level 1: | B90: 0 | C90: Enter "1" to Select | E90: ='TILE COPING'!F30 -> Ivory, Hazelnut, Noce, Country Classic, Light Noce, Harvest Blend
A91: Travertine Decking - Level 1: | B91: 0 | C91: Enter "1" to Select | E91: ='TILE COPING'!F31 -> Ivory, Hazelnut, Noce, Country Classic, Light Noce, Harvest Blend
A93: Travertine Coping - Level 2: | B93: 1 | C93: Enter "1" to Select | E93: ='TILE COPING'!F32 -> Silver, Silver Vogue, River Silver, Bianco Dolomite, Dianna Royal, Skyline, Alaska Silver, Turkish Carrea
A94: Travertine Decking - Level 2: | B94: 0 | C94: Enter "1" to Select | E94: ='TILE COPING'!F33 -> Silver, Silver Vogue, River Silver, Bianco Dolomite, Dianna Royal, Skyline, Alaska Silver, Turkish Carrea
A96: Concrete Coping: | B96: 0 | C96: Enter "1" to Select
A97: Concrete Decking: | B97: 0 | C97: Enter "1" to Select
A98: Concrete Steps: | B98: 0 | C98: LNFT
A100: Rough Grading | B100: 1 | C100: Keep unless Deck Is Off Contract!
A102: DRAINAGE
A104: Downspout Total LF from all | B104: 0 | C104: Enter LNFT
A105: Deck Drain Total LF | B105: 0 | C105: Enter LNFT
A106: French Drain Total LF | B106: 0 | C106: Enter LNFT
A107: Box Drain Total LF | B107: 0 | C107: Enter LNFT
A109: EQUIPMENT
A111: PUMPS / FILTER / CLEANER / HEATER
A113: Jandy 1.85HP Variable Pump | B113: 1 | C113: =VLOOKUP(A113,EQUIP!M15:T17,8,FALSE) -> INCLUDED
A114: No Auxiliary Pump | B114: =IF(C114>0,1,0) -> 0 | C114: =VLOOKUP(A114,EQUIP!M14:S19,7,FALSE) -> 0
A115: No Auxiliary Pump | B115: =IF(C115>0,1,0) -> 0 | C115: =VLOOKUP(A115,EQUIP!M14:S19,7,FALSE) -> 0
A117: 580 SQFT Cartridge Filter | B117: 1 | C117: =VLOOKUP(A117,EQUIP!M23:O28,3,FALSE) -> 620
A119: Polaris Alpha IQ | B119: 0 | C119: =VLOOKUP(A119,EQUIP!M31:S33,7,FALSE) -> 2000
A121: No Heater | B121: 0 | C121: =VLOOKUP(A121,EQUIP!M36:S39,7,FALSE) -> 0 | E121: =IF(A121="Jandy 260K BTU - JXI Heater", "CANNOT BE USED TO HEAT A SPA","")
A122: Upgrade Heater to VersaFlo | B122: 0 | C122: =B122*EQUIP!S39 -> 0 | E122: =IF(B14>0,"PROJECT HAS A SPA - SELECT YOUR HEATER","")
A124: 24 Watt - Jandy Nicheless LED | B124: 2 | C124: =IF(B124=2,"INCLUDED",IF(B124=1,-EQUIP!S121,((B124-2)*EQUIP!S45))) -> INCLUDED
A125: No Additional Lights | B125: =EXC!C27 -> 0 | C125: =B125*EQUIP!S43 -> 0 | E125: =IF(B14>0,"PROJECT HAS A SPA - ADD SPA LIGHT","")
A127: Salt System - Jandy Tru-Clear | B127: =IF(C127>0,1,0) -> 1 | C127: =VLOOKUP(A127,EQUIP!M49:S57,7,FALSE)+(H127*EQUIP!S58) -> 1645 | E127: =IF(C127=1280,1,0) -> 0 | F127: =IF(A127=EQUIP!M57,1,0) -> 0 | G127: =B131 -> 1 | H127: =F127*G127 -> 0
A128: No Sanitation | B128: =IF(C128>0,1,0) -> 0 | C128: =VLOOKUP(A128,EQUIP!M49:S57,7,FALSE)+(H128*EQUIP!S58) -> 0 | E128: =IF(C128=1280,1,0) -> 0 | F128: =IF(A128=EQUIP!M57,1,0) -> 0 | G128: =B131 -> 1 | H128: =F128*G128 -> 0
A129: No Sanitation | B129: =IF(C129>0,1,0) -> 0 | C129: =VLOOKUP(A129,EQUIP!M49:S57,7,FALSE)+(H129*EQUIP!S58) -> 0 | E129: =IF(C129=1280,1,0) -> 0 | F129: =IF(A129=EQUIP!M57,1,0) -> 0 | G129: =B131 -> 1 | H129: =F129*G129 -> 0
A131: Jandy TCX Controler (1 JVA, Lights and Heater Control) | B131: 1 | C131: =VLOOKUP(A131,EQUIP!M63:S72,7,FALSE) -> 1217.7778 | E131: =IF(B14>0,"PROJECT HAS A SPA - SELECT AUTOMATION","")
...

Sheet CUSTOM
C1: Material | D1: Labor | E1: Total
C2: Cost | D2: Cost | E2: Cost | G2: Retail
A3: Parged Concrete | C3: 0 | D3: 0 | E3: =C3+D3 -> 0 | F3: 0.7 | G3: =E3/F3 -> 0
A5: Oversized coping | C5: 824 | D5: 0 | E5: =C5+D5 -> 824 | F5: 0.7 | G5: =E5/F5 -> 1177.1429
A7: handrail | C7: 1028 | D7: 0 | E7: =C7+D7 -> 1028 | F7: 0.7 | G7: =E7/F7 -> 1468.5714 | H7: 763+80+185
A9: No Custom Feature | C9: 0 | D9: 0 | E9: =C9+D9 -> 0 | F9: 0.7 | G9: =E9/F9 -> 0
A11: No Custom Feature | C11: 0 | D11: 0 | E11: =C11+D11 -> 0 | F11: 0.7 | G11: =E11/F11 -> 0
A13: No Custom Feature | C13: 0 | D13: 0 | E13: =C13+D13 -> 0 | F13: 0.7 | G13: =E13/F13 -> 0
A15: No Custom Feature | C15: 0 | D15: 0 | E15: =C15+D15 -> 0 | F15: 0.7 | G15: =E15/F15 -> 0
A17: No Custom Feature | C17: 0 | D17: 0 | E17: =C17+D17 -> 0 | F17: 0.7 | G17: =E17/F17 -> 0

Sheet PROPOSAL
B1: 2025 | F1: Proposal & Specifications
F2: Prepared by:
F4: John Piotrowski
F5: 980-392-7944
B6: a passion for splashin' | F6: jpiotrowski@ppas.com
A7: PREPARED FOR: | B7: ='NEW POOL'!B3 -> Bishop | F7: =TODAY() -> 45959
B8: ='NEW POOL'!B4 -> Indian Land
A10: Dimensions | B10: Width | C10: Length | D10: Shallow | E10: Deep | F10: Premier Advantage
A11: Pool Dimensions (Feet) | B11: ='NEW POOL'!E7 -> 16 | C11: ='NEW POOL'!E8 -> 36 | D11: ='NEW POOL'!B9 -> 3.5 | E11: ='NEW POOL'!B10 -> 7
A12: Spa Dimensions (Feet) | B12: ='NEW POOL'!B15 -> 0 | C12: ='NEW POOL'!B14 -> 0 | D12: =IF(B12>0,3,0) -> 0 | E12: 0 | F12: =IF(C12=0,"No Spa","Split Bench for Customized Therapy") -> No Spa
A13: =IF(I43=1,"Shell:","Notes:") -> Notes: | B13: =IF('NEW POOL'!A21="Fiberglass - Small","",'NEW POOL'!A21)
B14: =IF('NEW POOL'!A22="Fiberglass - Medium","",'NEW POOL'!A22)
B15: =IF('NEW POOL'!A23="Fiberglass - Large","",'NEW POOL'!A23)
A17: Steps & Benches | F17: Premier Advantage
A18: One set of shallow-end access steps
A19: Deep-end loveseat bench | F19: For safety and relaxing
A20: Notes:
A23: Plans, Permits & Insurance | F23: Premier Advantage
A24: Detailed construction plans in advance for approval prior to excavation | F24: Ensures clear understanding of project details
A25: Engineered structural plans | F25: Certificates available upon request
A26: All required building permits
A27: Underground services alert called prior to excavation
A28: All work and vehicles are covered by commercial liability and auto insurance
A29: All employees are covered by Workers Compensation Insurance
A30: Taxes on all materials and equipment included in contract price
A31: Lien releases are available throughout construction
A32: Premier is licensed and bonded in accordance with State Contractors Board Regulations
A33: Notes:
A36: Excavation | F36: Premier Advantage
A37: Pool layout prior to excavation | F37: Pool is painted on ground for visual approval by homeowner
A38: Pool hand contoured | F38: Hand trimming assures uniform wall and floor thickness with proper cove radius
A40: Notes:
A43: Steel | F43: Premier Advantage | I43: =I76 -> 0
A44: =IF(I43=1,"Fiberglass Shell - No Steel","4 bar bond beam with ½ inch steel; 3/8 inch rebar on 10 inch centers through pool") -> 4 bar bond beam with ½ inch steel; 3/8 inch rebar on 10 inch centers through pool | F44: =IF(I43=1,"","Our bond beam and wall steel schedules are beyond code for protection against expansive soils") -> Our bond beam and wall steel schedules are beyond code for protection against expansive soils
A45: =IF(I43=1,"","10 inch on center in transition slope by 20 feet length") -> 10 inch on center in transition slope by 20 feet length | F45: =IF(I43=1,"","Strongest steel schedule in the industry!") -> Strongest steel schedule in the industry!
A46: 8" on center in the deep end and coves
A48: Notes:
A51: Plumbing | F51: Premier Advantage
A52: 2 ½ inch suction line | F52: Premier Stealth Series pump
A53: 2 ½ inch suction line for all pump motors larger than 1.0 HP | F53: Premier High-Performance circulation pump
A54: 2 inch return line (to 1st tee) | F54: Premier booster pump
A55: When possible 45-degree elbows used rather than 90-degree to improve efficiency and performance
A56: Separate skimmer and main drain suction - allows for maximimum performance
A57: Heavy duty surface skimmer
A58: Jandy Ball Valves
A60: Hose bib at pad for draining pool
A61: All circulation lines are under pressure test throughout construction to ensure no leaks in the system
A63: Notes:
A66: Electric | F66: Premier Advantage
A67: Breakers at pad included | F67: Protected outlet for homeowner convenience
A68: 110 volt GFI protected light circuit with outlet
A69: 220 volt pump circuit
A70: Jandy IQ20 pump controler | F70: Control your pump from your phone
A71: Bonding as per N.E.C. Code
A72: (2) Low-voltage Premier Colored LED Lights
A73: Notes:
A76: Shotcrete | F76: Premier Advantage | I76: =J142 -> 0
A77: =IF(J142=1,"No Shotcrete - Fiberglass Shell","4,000 PSI pneumatically applied shotcrete") -> 4,000 PSI pneumatically applied shotcrete | F77: =IF(I76=1,"","Lifetime structural warranty") -> Lifetime structural warranty
A79: =IF(I76=1,"","All shotcrete is measured by a certified weighmaster") -> All shotcrete is measured by a certified weighmaster
A80: =IF(I76=1,"","All nozzlemen are certified for State and Municipal work") -> All nozzlemen are certified for State and Municipal work
A81: =IF(I76=1,"","Lifetime structural warranty") -> Lifetime structural warranty
A82: Notes:
A85: Tile & Masonary | F85: Premier Advantage | I85: =I76 -> 0
A86: =IF(I85=1,"Fiberglass Shell - No Tile","All pool & spa waterline tile including - skimmer throat") -> All pool & spa waterline tile including - skimmer throat | F86: =IF(I85=1,"","Frost-proof tiles in a variety of patterns and colors") -> Frost-proof tiles in a variety of patterns and colors
A87: =IF(I85=1,"","Trim tile available on steps and benches") -> Trim tile available on steps and benches | F87: By request at extra cost for safety and beauty
A88: Notes:
A91: Coping / Decking | F91: Premier Advantage
A94: Notes:
A97: Equipment | F97: Premier Advantage
A98: ='NEW POOL'!A113 -> Jandy 1.85HP Variable Pump | F98: 3-Year NO-FAULT Warranty on all Jandy Equipment
A99: ='NEW POOL'!A114 -> No Auxiliary Pump
A100: ='NEW POOL'!A117 -> 580 SQFT Cartridge Filter
A101: ='NEW POOL'!A127 -> Salt System - Jandy Tru-Clear
A102: ='NEW POOL'!A128 -> No Sanitation
A103: ='NEW POOL'!A129 -> No Sanitation
A104: ='NEW POOL'!A121 -> No Heater
A106: ='NEW POOL'!A131 -> Jandy TCX Controler (1 JVA, Lights and Heater Control)
A107: Notes: | B107: Maintenance Kit includes: Telescoping pole, Brush, Leaf Skimmer, Test Kit and Net
A110: Clean Up & Interior | F110: Premier Advantage
A111: All Trenches filled and yard rough graded
A112: All construction debris hauled away
A114: =IF(J142=1,"",'NEW POOL'!A175) -> Pebble Tec - Level 1 | F114: =IF(A114="","","Combines durablity and functionality") -> Combines durablity and functionality
A115: VGB compliant Main Drain Covers
A116: =IF('NEW POOL'!B47=1, "Dirt haul off included", "Dirt to remain at property") -> Dirt haul off included
A117: Pool filled with water | F117: Water Trucks included
A118: Notes:
A121: Start Up & Orientation | F121: Premier Advantage
A122: Equipment turned on and started-up | F122: Pool Maintenance & Equipment fully explained
A123: Intial chemical balance | F123: Program cycles set for ideal run times
A124: "Pool School" / Orientation | F124: Report Card allows you to provide feeback
A125: Notes:
B127: 2025 | F127: Proposal & Specifications
F128: =F2 -> Prepared by:
F130: =F4 -> John Piotrowski
F131: =F5 -> 980-392-7944
B132: a passion for splashin' | F132: =F6 -> jpiotrowski@ppas.com
A133: Total Price & Options
A135: Summary | B135: Retail Price | D135: Savings | E135: Sale Price | F135: Notes
A136: Base Pool Price: | B136: 123591.37 | E136: =B136+D136 -> 123591.37
E137: =B137+D137 -> 0
...

Sheet COST - NEW
A2: PLANS & ENGINEERING
A3: =PLANS!A4 -> Pool Only: | B3: =PLANS!B4 -> 410 | C3: =PLANS!C4 -> 1 | D3: =PLANS!D4 -> 410
A4: =PLANS!A5 -> Spa: | B4: =PLANS!B5 -> 80 | C4: =PLANS!C5 -> 0 | D4: =PLANS!D5 -> 0
A5: =PLANS!A6 -> Waterfall: | B5: =PLANS!B6 -> 15 | C5: =PLANS!C6 -> 0 | D5: =PLANS!D6 -> 0
A6: =PLANS!A7 -> Waterfeature: | B6: =PLANS!B7 -> 10 | C6: =PLANS!C7 -> 0 | D6: =PLANS!D7 -> 0
A7: =PLANS!A8 -> Soil Sample / Engineer: | B7: =PLANS!B8 -> 750 | C7: =PLANS!C8 -> 1 | D7: =PLANS!D8 -> 750
A9: PLANS & ENGINEERING TOTAL | D9: =SUM(D3:D8) -> 1160
A11: LAYOUT
A12: Pool Only | B12: 50 | C12: 1 | D12: =B12*C12 -> 50
A13: Spa | B13: 15 | C13: =EXC!C27 -> 0 | D13: =B13*C13 -> 0
A14: Silt Fencing, Etc. | B14: 500 | C14: ='NEW POOL'!B5 -> 1 | D14: =B14*C14 -> 500
A16: LAYOUT TOTAL | D16: =SUM(D12:D15) -> 550
A18: PERMIT
A19: Pool Only: | B19: 850 | C19: 1 | D19: =B19*C19 -> 850
A20: Spa: | B20: 150 | C20: =EXC!C27 -> 0 | D20: =B20*C20 -> 0
A21: Permit Runner: | B21: 75 | C21: 1 | D21: =B21*C21 -> 75
A23: PERMIT TOTAL | D23: =SUM(D19:D22) -> 925
A25: EXCAVATION
A26: Base Excavation: | B26: =EXC!G5 -> 576 | D26: =EXC!D18 -> 2700
A27: Over 1,000 SQFT: | B27: =EXC!B17 -> 4 | C27: =EXC!C17 -> 0 | D27: =EXC!D17 -> 0
A28: =EXC!A20 -> Add'l 6" Depth: | B28: =EXC!B20 -> 90 | C28: =EXC!C20 -> 0 | D28: =EXC!D20 -> 0
A29: =EXC!A21 -> 6" RBB: | B29: =EXC!B21 -> 5 | C29: =EXC!C21 -> 0 | D29: =EXC!D21 -> 0
A30: =EXC!A22 -> 12" RBB: | B30: =EXC!B22 -> 6.5 | C30: =EXC!C22 -> 0 | D30: =EXC!D22 -> 0
A31: =EXC!A23 -> 18" RBB: | B31: =EXC!B23 -> 7.5 | C31: =EXC!C23 -> 0 | D31: =EXC!D23 -> 0
A32: =EXC!A24 -> 24" RBB: | B32: =EXC!B24 -> 8.5 | C32: =EXC!C24 -> 0 | D32: =EXC!D24 -> 0
A33: =EXC!A25 -> 30" RBB" | B33: =EXC!B25 -> 9 | C33: =EXC!C25 -> 0 | D33: =EXC!D25 -> 0
A34: =EXC!A26 -> 36" RBB: | B34: =EXC!B26 -> 10 | C34: =EXC!C26 -> 0 | D34: =EXC!D26 -> 0
A35: =EXC!A27 -> Base Spa: | B35: =EXC!B27 -> 200 | C35: =EXC!C27 -> 0 | D35: =EXC!D27 -> 0
A36: =EXC!A28 -> Raise Spa: | B36: =EXC!B28 -> 350 | C36: =EXC!C28 -> 0 | D36: =EXC!D28 -> 0
A37: =EXC!A29 -> Site Prep: | B37: =EXC!B29 -> 200 | C37: =EXC!C29 -> 0 | D37: =EXC!D29 -> 0
A38: =EXC!A30 -> Backfill: | B38: =EXC!B30 -> 600 | C38: =EXC!C30 -> 1 | D38: =EXC!D30 -> 600
A39: =EXC!A31 -> Gravel: | B39: =EXC!B31 -> 1 | C39: =EXC!C31 -> 2.75 | D39: =EXC!D31 -> 1584
A40: =EXC!A32 -> Dirt Haul: | B40: =EXC!B32 -> 18 | C40: =ROUNDUP(EXC!C32,0) -> 180 | D40: =ROUNDUP(EXC!D32,0) -> 3230
A41: =EXC!A33 -> Cover Box: | B41: =EXC!B33 -> 450 | C41: =EXC!C33 -> 0 | D41: =EXC!D33 -> 0
A42: =EXC!A34 -> Travel: | B42: =EXC!B34 -> 7 | C42: =EXC!C34 -> 0 | D42: =EXC!D34 -> 0
A43: =EXC!A35 -> Misc: | B43: =EXC!B35 -> 75 | C43: =EXC!C35 -> 1 | D43: =EXC!D35 -> 75 | E43: Discount
A44: PAP Discount: | D44: =F44*-E44 -> -818.9 | E44: 0.1 | F44: =SUM(D26:D43) -> 8189
A45: EXCAVATION TOTAL: | D45: =IF('NEW POOL'!B21+'NEW POOL'!B22+'NEW POOL'!B23>0,D40+('NEW POOL'!B47*D43),SUM(D26:D44)) -> 7370.1
A47: PLUMBING
A48: =PLUM!A4 -> Short Stub | B48: =PLUM!B4 -> 550 | C48: =PLUM!C4 -> 1 | D48: =PLUM!D4 -> 550
A49: =PLUM!A5 -> Spa Base: | B49: =PLUM!B5 -> 750 | C49: =PLUM!C5 -> 0 | D49: =PLUM!D5 -> 0
A50: Pool Overun: | B50: =PLUM!B8 -> 25 | C50: =PLUM!C8 -> 27 | D50: =PLUM!D8 -> 675
A51: Spa Overun: | B51: =PLUM!B9 -> 22 | C51: =PLUM!C9 -> 0 | D51: =PLUM!D9 -> 0
A52: =PLUM!A10 -> 1/2" | B52: =PLUM!B10 -> 3.25 | C52: =PLUM!C10 -> 0 | D52: =PLUM!D10 -> 0
A53: =PLUM!A11 -> 3/4" | B53: =PLUM!B11 -> 3 | C53: =PLUM!C11 -> 0 | D53: =PLUM!D11 -> 0
A54: =PLUM!A12 -> 1" | B54: =PLUM!B12 -> 3.5 | C54: =PLUM!C12 -> 0 | D54: =PLUM!D12 -> 0
A55: =PLUM!A13 -> 1.5" | B55: =PLUM!B13 -> 4.5 | C55: =PLUM!C13 -> 0 | D55: =PLUM!D13 -> 0
A56: =PLUM!A14 -> 2.0" | B56: =PLUM!B14 -> 5.5 | C56: =PLUM!C14 -> 205 | D56: =PLUM!D14 -> 1127.5
A57: =PLUM!A15 -> 2.5" | B57: =PLUM!B15 -> 7 | C57: =PLUM!C15 -> 70 | D57: =PLUM!D15 -> 490
A58: =PLUM!A16 -> 3.0" | B58: =PLUM!B16 -> 8.75 | C58: =PLUM!C16 -> 0 | D58: =PLUM!D16 -> 0
A59: =PLUM!A17 -> W/F (1) | D59: =PLUM!D17 -> 0
A60: =PLUM!A18 -> W/F (2) | D60: =PLUM!D18 -> 0
A61: =PLUM!A19 -> W/F (3) | D61: =PLUM!D19 -> 0
A62: =PLUM!A20 -> W/F (4) | D62: =PLUM!D20 -> 0
A63: =PLUM!A22 -> Add'l Main Drain: | B63: =PLUM!B22 -> 275 | C63: =PLUM!C22 -> 0 | D63: =PLUM!D22 -> 0
A64: =PLUM!A23 -> Manifold: | B64: =PLUM!B23 -> 175 | C64: =PLUM!C23 -> 1 | D64: =PLUM!D23 -> 175
A65: =PLUM!A24 -> Heater Set: | B65: =PLUM!B24 -> 300 | C65: =PLUM!C24 -> 0 | D65: =PLUM!D24 -> 0
A66: =PLUM!A25 -> Infloor: | B66: =PLUM!B25 -> 10 | C66: =PLUM!C25 -> 0 | D66: =PLUM!D25 -> 0
A67: =PLUM!A26 -> Conduit: | B67: =PLUM!B26 -> 2.75 | C67: =PLUM!C26 -> 229 | D67: =PLUM!D26 -> 629.75
A68: =PLUM!A27 -> Strip Forms | B68: =PLUM!B27 -> 700 | C68: =PLUM!C27 -> 1 | D68: =PLUM!D27 -> 700
A69: =PLUM!A28 -> Travel: | B69: =PLUM!B28 -> 5 | C69: =PLUM!C28 -> 0 | D69: =PLUM!D28 -> 0
A70: PAP Discount: | D70: =F70*-E70 -> 0 | E70: 0 | F70: =SUM(D48:D69) -> 4347.25
A71: PLUMBING TOTAL: | D71: =IF('NEW POOL'!B21+'NEW POOL'!B22+'NEW POOL'!B23>0,(SUM(D48:D70)*0.4),SUM(D48:D70)) -> 4347.25
A73: GAS
A74: =PLUM!A33 -> Base Set: | B74: =PLUM!B33 -> 1500 | C74: =IF('NEW POOL'!B68>0,1,0) -> 0 | D74: =B74*C74 -> 0
A75: =PLUM!A34 -> Add'l Run | B75: =PLUM!B34 -> 11 | C75: =PLUM!C34 -> 0 | D75: =PLUM!D34 -> 0
A77: GAS TOTAL: | D77: =SUM(D74:D76) -> 0
A79: STEEL
A80: =STEEL!A4 -> Base: | B80: =STEEL!B4 -> 25 | C80: =STEEL!C4 -> 104 | D80: =STEEL!D4 -> 2600
A81: =STEEL!A5 -> 4-Bar Beam: | B81: =STEEL!B5 -> 100 | C81: =STEEL!C5 -> 1 | D81: =STEEL!D5 -> 100
A82: =STEEL!A6 -> 10" OC: | B82: =STEEL!B6 -> 0 | C82: =STEEL!C6 -> 104 | D82: =STEEL!D6 -> 0
A83: =STEEL!A7 -> Add'l 6" Depth: | B83: =STEEL!B7 -> 100 | C83: =STEEL!C7 -> 0 | D83: =STEEL!D7 -> 0
A84: =STEEL!A8 -> Spa: | B84: =STEEL!B8 -> 450 | C84: =STEEL!C8 -> 0 | D84: =STEEL!D8 -> 0
A85: Raise Spa: | B85: =STEEL!B9 -> 150 | C85: =STEEL!C9 -> 0 | D85: =STEEL!D9 -> 0
A86: =STEEL!A10 -> Bench: | B86: =STEEL!B10 -> 8 | C86: =STEEL!C10 -> 70 | D86: =STEEL!D10 -> 560
A87: =STEEL!A11 -> 6" RBB: | B87: =STEEL!B11 -> 3 | C87: =STEEL!C11 -> 0 | D87: =STEEL!D11 -> 0
A88: =STEEL!A12 -> 12" RBB: | B88: =STEEL!B12 -> 4 | C88: =STEEL!C12 -> 0 | D88: =STEEL!D12 -> 0
A89: =STEEL!A13 -> 18" RBB: | B89: =STEEL!B13 -> 5 | C89: =STEEL!C13 -> 0 | D89: =STEEL!D13 -> 0
A90: =STEEL!A14 -> 24" RBB: | B90: =STEEL!B14 -> 6 | C90: =STEEL!C14 -> 0 | D90: =STEEL!D14 -> 0
A91: =STEEL!A15 -> 30" RBB: | B91: =STEEL!B15 -> 7 | C91: =STEEL!C15 -> 0 | D91: =STEEL!D15 -> 0
A92: =STEEL!A16 -> 36" RBB: | B92: =STEEL!B16 -> 7 | C92: =STEEL!C16 -> 0 | D92: =STEEL!D16 -> 0
A93: =STEEL!A17 -> Pool Bonding: | B93: =STEEL!B17 -> 500 | C93: =STEEL!C17 -> 1 | D93: =STEEL!D17 -> 500
A94: =STEEL!A18 -> Bonding Lights: | B94: =STEEL!B18 -> 0 | C94: =STEEL!C18 -> 2 | D94: =STEEL!D18 -> 0
A95: =STEEL!A19 -> #4 in Floor: | B95: =STEEL!B19 -> 0 | C95: =STEEL!C19 -> 1 | D95: =STEEL!D19 -> 0
A96: =STEEL!A20 -> Depth over 8': | B96: =STEEL!B20 -> 80 | C96: =STEEL!C20 -> 0 | D96: =STEEL!D20 -> 0
A97: =STEEL!A21 -> Negative Edge: | B97: =STEEL!B21 -> 750 | C97: =STEEL!C21 -> 0 | D97: =STEEL!D21 -> 0
A98: =STEEL!A22 -> Tanning Shelf: | B98: =STEEL!B22 -> 275 | C98: =STEEL!C22 -> 0 | D98: =STEEL!D22 -> 0
A99: =STEEL!A24 -> Spa Double Curtain: | B99: =STEEL!B24 -> 75 | C99: =STEEL!C24 -> 0 | D99: =STEEL!D24 -> 0
A100: =STEEL!A25 -> Double Curtain: | B100: =STEEL!B25 -> 35 | C100: =STEEL!C25 -> 0 | D100: =STEEL!D25 -> 0
A101: =STEEL!A23 -> Muck Out: | B101: =STEEL!B23 -> 100 | C101: =STEEL!C23 -> 2 | D101: =STEEL!D23 -> 200
A102: =STEEL!A26 -> Travel: | B102: =STEEL!B26 -> 7 | C102: =STEEL!C26 -> 0 | D102: =STEEL!D26 -> 0
A103: PAP Discount: | D103: =F103*-E103 -> -396 | E103: 0.1 | F103: =SUM(D80:D102) -> 3960
A104: STEEL TOTAL: | D104: =IF('NEW POOL'!$B$21+'NEW POOL'!$B$22+'NEW POOL'!$B$23>0,0,SUM(D80:D103)) -> 3564
A106: ELECTRICAL
A107: =ELEC!A4 -> Base: | B107: =ELEC!B4 -> 1650 | C107: =ELEC!C4 -> 1 | D107: =ELEC!D4 -> 1650
A108: =ELEC!A5 -> Homerun: | B108: =ELEC!B5 -> 18 | C108: =ELEC!C5 -> 0 | D108: =ELEC!D5 -> 0
A109: =ELEC!A6 -> Lights: | B109: =ELEC!B6 -> 100 | C109: =ELEC!C6 -> 1 | D109: =ELEC!D6 -> 100
A110: =ELEC!A7 -> Heater: | B110: =ELEC!B7 -> 255 | C110: =ELEC!C7 -> 0 | D110: =ELEC!D7 -> 0
A111: =ELEC!A8 -> Heatpump: | B111: =ELEC!B8 -> 450 | C111: =ELEC!C8 -> 0 | D111: =ELEC!D8 -> 0
A112: =ELEC!A9 -> Add'l Heatpump: | B112: =ELEC!B9 -> 6 | C112: =ELEC!C9 -> 0 | D112: =ELEC!D9 -> 0
...

Sheet SUMMARY - NEW
A1: JOB COST SUMMARY
A3: CUSTOMER NAME: | B3: ='NEW POOL'!B3 -> Bishop
A5: PLANS & ENGINEERING TOTAL | D5: ='COST - NEW'!D9 -> 1160
A7: LAYOUT TOTAL | D7: ='COST - NEW'!D16 -> 550
A9: PERMIT TOTAL | D9: ='COST - NEW'!D23 -> 925
A11: EXCAVATION TOTAL: | D11: ='COST - NEW'!D45 -> 7370.1
A13: PLUMBING TOTAL: | D13: ='COST - NEW'!D71 -> 4347.25
A15: GAS TOTAL: | D15: ='COST - NEW'!D77 -> 0
A17: STEEL TOTAL: | D17: =OTHER!D17 -> 3564
A19: ELECTRICAL TOTAL: | D19: ='COST - NEW'!D121 -> 2385
A21: SHOTCRETE LABOR TOTAL: | D21: =OTHER!D21 -> 3690
A23: SHOTCRETE MATERIAL TOTAL: | D23: =OTHER!D23 -> 11393.168
A25: TILE LABOR TOTAL: | D25: =OTHER!D25 -> 1040
A27: TILE MATERIAL TOTAL: | D27: =OTHER!D27 -> 782.6
A29: COPING / DECKING LABOR TOTAL: | D29: ='COST - NEW'!D204 -> 7685.04
A31: COPING / DECKING MATERIAL TOTAL: | D31: ='COST - NEW'!D206 -> 4532.4118
A33: STONE / ROCKWORK LABOR TOTAL: | D33: ='COST - NEW'!D225 -> 0
A35: STONE / ROCKWORK MATERIAL TOTAL: | D35: ='COST - NEW'!D227 -> 0
A37: DRAINAGE: | D37: =MISC!D18 -> 0
A39: EQUIPMENT ORDERED TOTAL: | D39: ='COST - NEW'!D261 -> 8132.267
A41: EQUIPMENT SET TOTAL: | D41: ='COST - NEW'!D272 -> 875
A43: CLEAN-UP TOTAL: | D43: ='COST - NEW'!D282 -> 1438
A45: INTERIOR FINISH TOTAL: | D45: =OTHER!D43 -> 8577.55
A47: WATER TRUCK TOTAL: | D47: =INT!D28 -> 1715
A49: FIBERGLASS SHELL TOTAL: | D49: =OTHER!D45 -> 0
A51: FIBERGLASS INSTALL TOTAL: | D51: =OTHER!D47 -> 150
A53: START-UP / ORIENTATION TOTAL: | D53: ='COST - NEW'!D330 -> 1000
A55: =CUSTOM!A3 -> Parged Concrete | D55: ='COST - NEW'!D333 -> 0
A57: =CUSTOM!A5 -> Oversized coping | D57: ='COST - NEW'!D334 -> 824
A59: =CUSTOM!A7 -> handrail | D59: ='COST - NEW'!D335 -> 1028
A61: =CUSTOM!A9 -> No Custom Feature | D61: ='COST - NEW'!D336 -> 0
A63: =CUSTOM!A11 -> No Custom Feature | D63: ='COST - NEW'!D337 -> 0
A65: =CUSTOM!A13 -> No Custom Feature | D65: ='COST - NEW'!D338 -> 0
A67: =CUSTOM!A15 -> No Custom Feature | D67: ='COST - NEW'!D339 -> 0
A69: =CUSTOM!A17 -> No Custom Feature | D69: ='COST - NEW'!D340 -> 0
A71: TOTAL COST: | D71: =SUM(D5:D70) -> 73164.386

Sheet OTHER
A1: JOB COST SUMMARY
A3: CUSTOMER NAME: | B3: ='NEW POOL'!B3 -> Bishop | F3: Pool Only | G3: Pool / Spa | M3: 0.7
F4: Base | G4: Base | I4: As-Designed | K4: Difference | M4: Retail Difference
A5: PLANS & ENGINEERING TOTAL | D5: ='COST - NEW'!D9 -> 1160 | F5: 275 | G5: 315 | I5: =D5 -> 1160 | K5: =IF(EXC!$C$27=0,OTHER!I5-OTHER!F5,OTHER!I5-OTHER!G5) -> 885 | M5: =K5/$M$3 -> 1264.2857
A7: LAYOUT TOTAL | D7: ='COST - NEW'!D16 -> 550 | F7: 65 | G7: 65 | I7: =D7 -> 550 | K7: =IF(EXC!$C$27=0,OTHER!I7-OTHER!F7,OTHER!I7-OTHER!G7) -> 485 | M7: =K7/$M$3 -> 692.85714
A9: PERMIT TOTAL | D9: ='COST - NEW'!D23 -> 925 | F9: 925 | G9: 1075 | I9: =D9 -> 925 | K9: =IF(EXC!$C$27=0,OTHER!I9-OTHER!F9,OTHER!I9-OTHER!G9) -> 0 | M9: =K9/$M$3 -> 0
A11: EXCAVATION TOTAL: | D11: ='COST - NEW'!D45 -> 7370.1 | F11: 3650 | G11: 4000 | I11: =D11 -> 7370.1 | K11: =IF(EXC!$C$27=0,OTHER!I11-OTHER!F11,OTHER!I11-OTHER!G11) -> 3720.1 | M11: =K11/$M$3 -> 5314.4286
A13: PLUMBING TOTAL: | D13: ='COST - NEW'!D71 -> 4347.25 | F13: 1833.5 | G13: 3058 | I13: =D13 -> 4347.25 | K13: =IF(EXC!$C$27=0,OTHER!I13-OTHER!F13,OTHER!I13-OTHER!G13) -> 2513.75 | M13: =CEILING(K13/$M$3,10) -> 3600
A15: GAS TOTAL: | D15: ='COST - NEW'!D77 -> 0 | F15: 0 | G15: 0 | I15: =D15 -> 0 | K15: =IF(EXC!$C$27=0,OTHER!I15-OTHER!F15,OTHER!I15-OTHER!G15) -> 0 | M15: =CEILING(K15/$M$3,10) -> 0
A17: STEEL TOTAL: | D17: =IF('NEW POOL'!$B$21+'NEW POOL'!$B$22+'NEW POOL'!$B$23>0,0,'COST - NEW'!D104) -> 3564 | F17: 2950 | G17: 3450 | I17: =D17 -> 3564 | K17: =IF(EXC!$C$27=0,OTHER!I17-OTHER!F17,OTHER!I17-OTHER!G17) -> 614 | M17: =K17/$M$3 -> 877.14286
A19: ELECTRICAL TOTAL: | D19: ='COST - NEW'!D121 -> 2385 | F19: 2010 | G19: 2135 | I19: =D19 -> 2385 | K19: =IF(EXC!$C$27=0,OTHER!I19-OTHER!F19,OTHER!I19-OTHER!G19) -> 375 | M19: =K19/$M$3 -> 535.71429
A21: SHOTCRETE LABOR TOTAL: | D21: =IF('NEW POOL'!$B$21+'NEW POOL'!$B$22+'NEW POOL'!$B$23>0,0,'COST - NEW'!D145) -> 3690 | F21: 2880 | G21: 3400 | I21: =D21 -> 3690 | K21: =IF(EXC!$C$27=0,OTHER!I21-OTHER!F21,OTHER!I21-OTHER!G21) -> 810 | M21: =K21/$M$3 -> 1157.1429
A23: SHOTCRETE MATERIAL TOTAL: | D23: =IF('NEW POOL'!$B$21+'NEW POOL'!$B$22+'NEW POOL'!$B$23>0,0,'COST - NEW'!D147) -> 11393.168 | F23: 6992.7 | G23: 8113.46 | I23: =D23 -> 11393.168 | K23: =IF(EXC!$C$27=0,OTHER!I23-OTHER!F23,OTHER!I23-OTHER!G23) -> 4400.4675 | M23: =K23/$M$3 -> 6286.3821
A25: TILE LABOR TOTAL: | D25: =IF('NEW POOL'!$B$21+'NEW POOL'!$B$22+'NEW POOL'!$B$23>0,0,'COST - NEW'!D173) -> 1040 | F25: 830 | G25: 1180 | I25: =D25 -> 1040 | K25: =IF(EXC!$C$27=0,OTHER!I25-OTHER!F25,OTHER!I25-OTHER!G25) -> 210 | M25: =K25/$M$3 -> 300
A27: TILE MATERIAL TOTAL: | D27: =IF('NEW POOL'!$B$21+'NEW POOL'!$B$22+'NEW POOL'!$B$23>0,0,'COST - NEW'!D175) -> 782.6 | F27: 540 | G27: 752.8 | I27: =D27 -> 782.6 | K27: =IF(EXC!$C$27=0,OTHER!I27-OTHER!F27,OTHER!I27-OTHER!G27) -> 242.6 | M27: =K27/$M$3 -> 346.57143
A29: COPING / DECKING LABOR TOTAL: | D29: ='COST - NEW'!D204 -> 7685.04 | F29: 0 | G29: 0 | I29: =D29 -> 7685.04 | K29: =IF(EXC!$C$27=0,OTHER!I29-OTHER!F29,OTHER!I29-OTHER!G29) -> 7685.04 | L29: 0.745 | M29: =CEILING(K29/L29,10) -> 10320
A31: COPING / DECKING MATERIAL TOTAL: | D31: ='COST - NEW'!D206 -> 4532.4118 | F31: 0 | G31: 0 | I31: =D31 -> 4532.4118 | K31: =IF(EXC!$C$27=0,OTHER!I31-OTHER!F31,OTHER!I31-OTHER!G31) -> 4532.4118 | L31: 0.745 | M31: =CEILING(K31/L31,10) -> 6090
A33: STONE / ROCKWORK LABOR TOTAL: | D33: ='COST - NEW'!D225 -> 0 | F33: 0 | G33: 0 | I33: =D33 -> 0 | K33: =IF(EXC!$C$27=0,OTHER!I33-OTHER!F33,OTHER!I33-OTHER!G33) -> 0 | M33: =CEILING(K33/$M$3,40) -> 0
A35: STONE / ROCKWORK MATERIAL TOTAL: | D35: ='COST - NEW'!D227 -> 0 | F35: 0 | G35: 0 | I35: =D35 -> 0 | K35: =IF(EXC!$C$27=0,OTHER!I35-OTHER!F35,OTHER!I35-OTHER!G35) -> 0 | M35: =CEILING(K35/$M$3,40) -> 0
A37: EQUIPMENT ORDERED TOTAL: | D37: ='COST - NEW'!D261 -> 8132.267 | F37: 3504.25 | G37: 3504.25 | I37: =D37 -> 8132.267 | K37: =IF(EXC!$C$27=0,OTHER!I37-OTHER!F37,OTHER!I37-OTHER!G37) -> 4628.017 | M37: =K37/$M$3 -> 6611.4529
A39: EQUIPMENT SET TOTAL: | D39: ='COST - NEW'!D272 -> 875 | F39: 550 | G39: 550 | I39: =D39 -> 875 | K39: =IF(EXC!$C$27=0,OTHER!I39-OTHER!F39,OTHER!I39-OTHER!G39) -> 325 | M39: =K39/$M$3 -> 464.28571
A41: CLEAN-UP TOTAL: | D41: ='COST - NEW'!D282 -> 1438 | F41: 700 | G41: 800 | I41: =D41 -> 1438 | K41: =IF(EXC!$C$27=0,OTHER!I41-OTHER!F41,OTHER!I41-OTHER!G41) -> 738 | M41: =K41/$M$3 -> 1054.2857
A43: INTERIOR FINISH TOTAL: | D43: =IF('NEW POOL'!$B$21+'NEW POOL'!$B$22+'NEW POOL'!$B$23>0,0,'COST - NEW'!D295) -> 8577.55 | F43: 4278 | G43: 5340.96 | I43: =D43 -> 8577.55 | K43: =IF(EXC!$C$27=0,OTHER!I43-OTHER!F43,OTHER!I43-OTHER!G43) -> 4299.55 | M43: =IF(D43=0,0,CEILING(K43/$M$3,320)) -> 6400
A45: FIBERGLASS SHELL TOTAL: | D45: ='COST - NEW'!D315 -> 0
A47: FIBERGLASS INSTALL TOTAL: | D47: =SUM(FIBER!G66:G78) -> 150
A49: START-UP / ORIENTATION TOTAL: | D49: ='COST - NEW'!D330 -> 1000 | F49: 500 | G49: 500 | I49: =D49 -> 1000 | K49: =IF(EXC!$C$27=0,OTHER!I49-OTHER!F49,OTHER!I49-OTHER!G49) -> 500 | M49: =K49/$M$3 -> 714.28571
A51: ='SUMMARY - NEW'!A55 -> Parged Concrete | D51: ='SUMMARY - NEW'!D55 -> 0
A53: ='SUMMARY - NEW'!A57 -> Oversized coping | D53: ='SUMMARY - NEW'!D57 -> 824
A55: ='SUMMARY - NEW'!A59 -> handrail | D55: ='SUMMARY - NEW'!D59 -> 1028
A57: ='SUMMARY - NEW'!A61 -> No Custom Feature | D57: ='SUMMARY - NEW'!D61 -> 0
A59: TOTAL COST: | D59: =SUM(D5:D58) -> 71449.386 | F59: =SUM(F5:F50) -> 32483.45 | G59: =SUM(G5:G50) -> 38239.47 | I59: =SUM(I5:I50) -> 69447.386 | K59: =I59-F59 -> 36963.936 | M59: =K59/$M$3 -> 52805.623
G60: =G59-F59 -> 5756.02 | H60: 0.71
G61: =G60/H60 -> 8107.0704
F63: Spa Base: | G63: 14950
A66: Additional Size: | F66: Add'l Depth | G66: Retail
A67: Perimeter: | B67: 125 | C67: =IF('NEW POOL'!B7>80,'NEW POOL'!B7-80,0) -> 24 | D67: =B67*C67 -> 3000 | F67: 6 | G67: 1050 | H67: =IF('NEW POOL'!$B$10=6,1,0) -> 0 | I67: =G67*H67 -> 0
A68: Surface Area: | B68: 12 | C68: =IF('NEW POOL'!B8>400,'NEW POOL'!B8-400,0) -> 176 | D68: =B68*C68 -> 2112 | F68: 7 | G68: 1390 | H68: =IF('NEW POOL'!$B$10=7,1,0) -> 1 | I68: =G68*H68 -> 1390
A69: Additional Depth: | C69: =SUM(H67:H70) -> 1 | D69: =I72 -> 1390 | F69: 8 | G69: 2750 | H69: =IF('NEW POOL'!$B$10=8,1,0) -> 0 | I69: =G69*H69 -> 0
F70: 9 | G70: 3880 | H70: =IF('NEW POOL'!$B$10=9,1,0) -> 0 | I70: =G70*H70 -> 0
I72: =SUM(I67:I70) -> 1390

Sheet BILLING
F3: CUSTOMER: | G3: ='NEW POOL'!B3 -> Bishop
F5: CITY: | G5: ='NEW POOL'!B4 -> Indian Land
A9: IN-HOUSE BILLING
A12: Permit Runner | G12: ='COST - NEW'!D21 -> 75
A15: Layout | G15: 65
A18: Waterproofing | G18: =CEILING('COST - NEW'!D293,1) -> 0

Sheet PLANS
A1: MAY 2020
A3: PLANS & ENGINEERING
A4: Pool Only: | B4: 410 | C4: 1 | D4: =B4*C4 -> 410
A5: Spa: | B5: 80 | C5: =EXC!C27 -> 0 | D5: =B5*C5 -> 0
A6: Waterfall: | B6: 15 | C6: =IF('NEW POOL'!B167>0,1,0) -> 0 | D6: =B6*C6 -> 0
A7: Waterfeature: | B7: 10 | C7: ='NEW POOL'!B138+'NEW POOL'!B139+'NEW POOL'!B141+'NEW POOL'!B143 -> 0 | D7: =B7*C7 -> 0
A8: Soil Sample / Engineer: | B8: 750 | C8: ='NEW POOL'!B53 -> 1 | D8: =B8*C8 -> 750
A10: Plans Total: | D10: =SUM(D4:D9) -> 1160

Sheet EXC
A1: MARCH 2022
J2: Size over 1000
A3: Base | H3: Dig | J3: =IF(G5>1000,G5-1000,0) -> 0
A4: 0-400 | B4: 2700 | C4: =IF(G5<401,1,0) -> 0 | D4: =B4*C4 -> 0 | F4: Perimeter | G4: ='NEW POOL'!B7 -> 104 | H4: =G4*1.12 -> 116.48
A5: 401-450 | B5: =B4 -> 2700 | C5: =IF(C4>0,0,IF($G$5>400,IF($G$5<451,1,0))) -> 0 | D5: =B5*C5 -> 0 | F5: Surface | G5: ='NEW POOL'!B8 -> 576 | H5: =G5*1.15 -> 662.4
A6: 451-500 | B6: 2700 | C6: =IF(C4+C5>0,0,IF($G$5>450,IF($G$5<501,1,0))) -> 0 | D6: =B6*C6 -> 0 | F6: Min Depth | G6: ='NEW POOL'!B9 -> 3.5 | H6: =G6+1.25 -> 4.75
A7: 501-550 | B7: =B6 -> 2700 | C7: =IF(C4+C5+C6>0,0,IF($G$5>500,IF($G$5<551,1,0))) -> 0 | D7: =B7*C7 -> 0 | F7: Max Depth | G7: ='NEW POOL'!B10 -> 7 | H7: =G7+1.25 -> 8.25
A8: 551-600 | B8: =B7 -> 2700 | C8: =IF(C4+C5+C6+C7>0,0,IF($G$5>550,IF($G$5<601,1,0))) -> 1 | D8: =B8*C8 -> 2700 | F8: Avg Depth | G8: =(G6+G7)/2 -> 5.25 | H8: =(H6+H7)/2 -> 6.5
A9: 601-650 | B9: 2700 | C9: =IF(C4+C5+C6+C7+C8>0,0,IF($G$5>600,IF($G$5<651,1,0))) -> 0 | D9: =B9*C9 -> 0 | F9: Spa | G9: =IF(C27>0,50,0) -> 0 | H9: =IF(G9>0,75,0) -> 0
A10: 651-700 | B10: =B9 -> 2700 | C10: =IF(C4+C5+C6+C7+C8+C9>0,0,IF($G$5>650,IF($G$5<701,1,0))) -> 0 | D10: =B10*C10 -> 0
A11: 701-750 | B11: =B10 -> 2700 | C11: =IF(C4+C5+C6+C7+C8+C9+C10>0,0,IF($G$5>700,IF($G$5<751,1,0))) -> 0 | D11: =B11*C11 -> 0 | F11: Yardage Removed: | H11: =((H5*H8)/24)+((H9*2.5)/24) -> 179.4
A12: 751-800 | B12: 2750 | C12: =IF(C4+C5+C6+C7+C8+C9+C10+C11>0,0,IF($G$5>750,IF($G$5<801,1,0))) -> 0 | D12: =B12*C12 -> 0
A13: 801-850 | B13: 3000 | C13: =IF(C4+C5+C6+C7+C8+C9+C10+C11+C12>0,0,IF($G$5>800,IF($G$5<851,1,0))) -> 0 | D13: =B13*C13 -> 0
A14: 851-900 | B14: 3100 | C14: =IF(C4+C5+C6+C7+C8+C9+C10+C11+C12+C13>0,0,IF($G$5>850,IF($G$5<901,1,0))) -> 0 | D14: =B14*C14 -> 0
A15: 901-950 | B15: 3150 | C15: =IF(C4+C5+C6+C7+C8+C9+C10+C11+C12+C13+C14>0,0,IF($G$5>900,IF($G$5<951,1,0))) -> 0 | D15: =B15*C15 -> 0
A16: 951-1000 | B16: =B15 -> 3150 | C16: =IF(C4+C5+C6+C7+C8+C9+C10+C11+C12+C13+C14+C15>0,0,IF($G$5>950,IF($G$5<1001,1,0)))+IF('NEW POOL'!B8>1000,1,0) -> 0 | D16: =B16*C16 -> 0
A17: 1000+ | B17: 4 | C17: =J3 -> 0 | D17: =B17*C17 -> 0
D18: =SUM(D4:D17) -> 2700
A20: Add'l 6" Depth: | B20: 90 | C20: =IF('NEW POOL'!B10<8.05,0,('NEW POOL'!B10-8)*2) -> 0 | D20: =B20*C20 -> 0
A21: 6" RBB: | B21: 5 | C21: ='NEW POOL'!B32 -> 0 | D21: =B21*C21 -> 0
A22: 12" RBB: | B22: 6.5 | C22: ='NEW POOL'!B33 -> 0 | D22: =B22*C22 -> 0
A23: 18" RBB: | B23: 7.5 | C23: ='NEW POOL'!B34 -> 0 | D23: =B23*C23 -> 0
A24: 24" RBB: | B24: 8.5 | C24: ='NEW POOL'!B35 -> 0 | D24: =B24*C24 -> 0
A25: 30" RBB" | B25: 9 | C25: ='NEW POOL'!B36 -> 0 | D25: =B25*C25 -> 0
A26: 36" RBB: | B26: 10 | C26: ='NEW POOL'!B37 -> 0 | D26: =B26*C26 -> 0
A27: Base Spa: | B27: 200 | C27: =IF('NEW POOL'!B17>0,1,0) -> 0 | D27: =B27*C27 -> 0
A28: Raise Spa: | B28: 350 | C28: ='NEW POOL'!B18 -> 0 | D28: =B28*C28 -> 0
A29: Site Prep: | B29: 200 | C29: ='NEW POOL'!B45 -> 0 | D29: =B29*C29 -> 0
A30: Backfill: | B30: 600 | C30: 1 | D30: =B30*C30 -> 600
A31: Gravel: | B31: 1 | C31: ='NEW POOL'!B46*2.75 -> 2.75 | D31: =B31*C31*G5 -> 1584 | E31: Per 3" | G31: Dirt Haul Actual
A32: Dirt Haul: | B32: 18 | C32: ='NEW POOL'!B47*H11 -> 179.4 | D32: =B32*C32 -> 3229.2 | E32: Per Yard | G32: 600 | H32: Skid Steer | L32: =G32 -> 600
A33: Cover Box: | B33: 450 | C33: ='NEW POOL'!B49 -> 0 | D33: =B33*C33*'NEW POOL'!E7 -> 0 | E33: Per Ft | G33: 90 | H33: Hourly Driver | J33: 8 | L33: =G33*J33 -> 720
A34: Travel: | B34: 7 | C34: ='NEW POOL'!E10 -> 0 | D34: =B34*C34 -> 0 | G34: 85 | H34: Per Load | J34: 20 | L34: =G34*J34 -> 1700
A35: Misc: | B35: 75 | C35: 1 | D35: =B35*C35 -> 75
D36: =SUM(D20:D35) -> 5488.2 | L36: =SUM(L32:L35) -> 3020
D38: =D18+D36 -> 8188.2

Sheet PLUM
A1: MARCH 2022
A3: PLUMBING
A4: Short Stub | B4: 550 | C4: 1 | D4: =B4*C4 -> 550
A5: Spa Base: | B5: 750 | C5: =EXC!C27 -> 0 | D5: =B5*C5 -> 0
D6: =SUM(D4:D5) -> 550
A8: Pool Overun: | B8: 25 | C8: =IF('NEW POOL'!B58>33,'NEW POOL'!B58-33,0) -> 27 | D8: =B8*C8 -> 675 | E8: Over 33'
A9: Spa Overun: | B9: 22 | C9: =IF('NEW POOL'!B69>30,('NEW POOL'!B69-30),0) -> 0 | D9: =B9*C9 -> 0 | E9: Over33'
A10: 1/2" | B10: 3.25 | C10: =ROUNDUP(K10,0) -> 0 | D10: =B10*C10 -> 0 | K10: =SUM(E10:J10) -> 0
A11: 3/4" | B11: 3 | C11: =ROUNDUP(K11,0) -> 0 | D11: =B11*C11 -> 0 | K11: =SUM(E11:J11) -> 0
A12: 1" | B12: 3.5 | C12: =ROUNDUP(K12,0) -> 0 | D12: =B12*C12 -> 0 | E12: ='NEW POOL'!B61 -> 0 | K12: =SUM(E12:J12) -> 0
A13: 1.5" | B13: 4.5 | C13: =ROUNDUP(K13,0) -> 0 | D13: =B13*C13 -> 0 | E13: ='NEW POOL'!B62 -> 0 | K13: =SUM(E13:J13) -> 0
A14: 2.0" | B14: 5.5 | C14: =ROUNDUP(K14,0) -> 205 | D14: =B14*C14 -> 1127.5 | E14: ='NEW POOL'!B7 -> 104 | F14: ='NEW POOL'!B58 -> 60 | G14: ='NEW POOL'!B60 -> 0 | H14: ='NEW POOL'!B66+('NEW POOL'!B67*6*1.15) -> 0 | K14: =(SUM(E14:J14)*1.25) -> 205
A15: 2.5" | B15: 7 | C15: =ROUNDUP(K15,0) -> 70 | D15: =B15*C15 -> 490 | E15: ='NEW POOL'!B59 -> 70 | F15: 0 | G15: ='NEW POOL'!B17 -> 0 | K15: =SUM(E15:J15) -> 70
A16: 3.0" | B16: 8.75 | C16: =ROUNDUP(K16,0) -> 0 | D16: =B16*C16 -> 0 | K16: =SUM(E16:J16) -> 0
A17: W/F (1) | B17: =B14 -> 5.5 | C17: ='NEW POOL'!B62 -> 0 | D17: =K17 -> 0 | E17: 30 | F17: LNFT Inlcuded | H17: =IF('NEW POOL'!B62>0,1,0) -> 0 | I17: =IF('NEW POOL'!B62<($E$17+1),$E$17,'NEW POOL'!B62) -> 30 | J17: =H17*I17 -> 0 | K17: =((($E$18*H17)+((J17-$E$17)*B17)))*H17 -> 0
A18: W/F (2) | B18: =B17 -> 5.5 | C18: ='NEW POOL'!B63 -> 0 | D18: =K18 -> 0 | E18: 200 | F18: Base | H18: =IF('NEW POOL'!B63>0,1,0) -> 0 | I18: =IF('NEW POOL'!B63<($E$17+1),$E$17,'NEW POOL'!B63) -> 30 | J18: =H18*I18 -> 0 | K18: =((($E$18*H18)+((J18-$E$17)*B18)))*H18 -> 0
A19: W/F (3) | B19: =B18 -> 5.5 | C19: ='NEW POOL'!B64 -> 0 | D19: =K19 -> 0 | H19: =IF('NEW POOL'!B64>0,1,0) -> 0 | I19: =IF('NEW POOL'!B64<($E$17+1),$E$17,'NEW POOL'!B64) -> 30 | J19: =H19*I19 -> 0 | K19: =((($E$18*H19)+((J19-$E$17)*B19)))*H19 -> 0
A20: W/F (4) | B20: =B19 -> 5.5 | C20: ='NEW POOL'!B65 -> 0 | D20: =K20 -> 0 | H20: =IF('NEW POOL'!B65>0,1,0) -> 0 | I20: =IF('NEW POOL'!B65<($E$17+1),$E$17,'NEW POOL'!B65) -> 30 | J20: =H20*I20 -> 0 | K20: =((($E$18*H20)+((J20-$E$17)*B20)))*H20 -> 0
A21: Add'l W/F Run: | B21: =B13 -> 4.5 | C21: =E17+E18+E19+E20 -> 230 | D21: =B21*C21 -> 1035
A22: Add'l Main Drain: | B22: 275 | C22: ='NEW POOL'!B114+'NEW POOL'!B115 -> 0 | D22: =B22*C22 -> 0
A23: Manifold: | B23: 175 | C23: 1 | D23: =B23*C23 -> 175
A24: Heater Set: | B24: 300 | C24: =IF((E24+F24)=1,1,0) -> 0 | E24: =C5 -> 0 | F24: ='NEW POOL'!B121 -> 0
A25: Infloor: | B25: 10 | C25: =ROUNDUP(IF('NEW POOL'!B66+'NEW POOL'!B66>0,'NEW POOL'!B8*0.5,0),0) -> 0 | D25: =B25*C25 -> 0
A26: Conduit: | B26: 2.75 | C26: =ROUNDUP(('NEW POOL'!B71+'NEW POOL'!B72*1.25),0) -> 229 | D26: =B26*C26 -> 629.75
A27: Strip Forms | B27: 700 | C27: 1 | D27: =B27*C27 -> 700
A28: Travel: | B28: 5 | C28: 0 | D28: =B28*C28 -> 0
D30: =SUM(D10:D29)+D6 -> 4707.25
A32: GAS
A33: Base Set: | B33: 1500 | C33: =IF('NEW POOL'!B68>0,1,0) -> 0 | D33: =B33*C33 -> 0
A34: Add'l Run | B34: 11 | C34: =IF('NEW POOL'!B68>25,'NEW POOL'!B68-25,0) -> 0 | D34: =B34*C34 -> 0
D36: =SUM(D33:D35) -> 0
A38: EQ SET | E38: Remodel
A39: Base Set: | B39: 750 | C39: 1 | D39: =B39*C39 -> 750
A40: Add'l Pump(s): | B40: 150 | C40: =C22 -> 0 | D40: =B40*C40 -> 0 | E40: 100
A41: Ozone: | B41: 200 | C41: =IF(J41>0,1,0) -> 0 | D41: =B41*C41 -> 0 | E41: 75 | G41: =IF('NEW POOL'!$A$127=EQUIP!$M$54,1,0) -> 0 | H41: =IF('NEW POOL'!A128=EQUIP!M54,1,0) -> 0 | I41: =IF('NEW POOL'!A129=EQUIP!M54,1,0) -> 0 | J41: =SUM(G41:I41) -> 0
A42: =EQUIP!M55 -> Del Ozone with UV AOP unit with Degas | B42: 210 | C42: =IF(J42>0,1,0) -> 0 | D42: =B42*C42 -> 0 | E42: 100 | G42: =IF('NEW POOL'!A127=EQUIP!M55,1,0) -> 0 | H42: =IF('NEW POOL'!A128=EQUIP!M55,1,0) -> 0 | I42: =IF('NEW POOL'!A129=EQUIP!M55,1,0) -> 0 | J42: =SUM(G42:I42) -> 0
A43: Heater: | B43: 200 | C43: ='NEW POOL'!B121 -> 0 | D43: =B43*C43 -> 0 | E43: 200
A44: Pool Bonding: | B44: 125 | C44: 1 | D44: =B44*C44 -> 125
A45: Travel: | B45: 7 | C45: =C28 -> 0 | D45: =B45*C45 -> 0
D47: =SUM(D39:D46) -> 875
A49: Filter: | E49: 100

Sheet STEEL
A1: MARCH 2022
A3: STEEL
A4: Base: | B4: 25 | C4: ='NEW POOL'!B7 -> 104 | D4: =B4*C4 -> 2600
A5: 4-Bar Beam: | B5: 100 | C5: 1 | D5: =B5*C5 -> 100
A6: 10" OC: | B6: 0 | C6: =C4 -> 104 | D6: =B6*C6 -> 0
A7: Add'l 6" Depth: | B7: 100 | C7: =EXC!C20 -> 0 | D7: =B7*C7 -> 0 | E7: Per 6"
A8: Spa: | B8: 450 | C8: =EXC!C27 -> 0 | D8: =B8*C8 -> 0
A9: Raise Spa: | B9: 150 | C9: ='NEW POOL'!B18 -> 0 | D9: =B9*C9 -> 0
A10: Bench: | B10: 8 | C10: ='NEW POOL'!B11 -> 70 | D10: =B10*C10 -> 560
A11: 6" RBB: | B11: 3 | C11: ='NEW POOL'!B32 -> 0 | D11: =B11*C11 -> 0
A12: 12" RBB: | B12: 4 | C12: ='NEW POOL'!B33 -> 0 | D12: =B12*C12 -> 0
A13: 18" RBB: | B13: 5 | C13: ='NEW POOL'!B34 -> 0 | D13: =B13*C13 -> 0
A14: 24" RBB: | B14: 6 | C14: ='NEW POOL'!B35 -> 0 | D14: =B14*C14 -> 0
A15: 30" RBB: | B15: 7 | C15: ='NEW POOL'!B36 -> 0 | D15: =B15*C15 -> 0
A16: 36" RBB: | B16: 7 | C16: ='NEW POOL'!B37 -> 0 | D16: =B16*C16 -> 0
A17: Pool Bonding: | B17: 500 | C17: 1 | D17: =B17*C17 -> 500
A18: Bonding Lights: | B18: 0 | C18: ='NEW POOL'!B124+'NEW POOL'!B125 -> 2 | D18: =B18*C18 -> 0
A19: #4 in Floor: | B19: 0 | C19: =IF('NEW POOL'!B10>6,1,0) -> 1 | D19: =B19*C19 -> 0
A20: Depth over 8': | B20: 80 | C20: =IF('NEW POOL'!B10>8.1,1,0) -> 0 | D20: =B20*C20 -> 0
A21: Negative Edge: | B21: 750 | C21: 0 | D21: =B21*C21 -> 0
A22: Tanning Shelf: | B22: 275 | C22: ='NEW POOL'!B12 -> 0 | D22: =B22*C22 -> 0
A23: Muck Out: | B23: 100 | C23: 2 | D23: =B23*C23 -> 200
A24: Spa Double Curtain: | B24: 75 | C24: =IF('NEW POOL'!B14>0,1,0) -> 0 | D24: =B24*C24 -> 0
A25: Double Curtain: | B25: 35 | C25: ='NEW POOL'!B51 -> 0 | D25: =B25*C25 -> 0
A26: Travel: | B26: 7 | C26: ='NEW POOL'!E10 -> 0 | D26: =B26*C26 -> 0
D28: =SUM(D4:D27) -> 3960

Sheet ELEC
A1: MARCH 2022
A3: ELECTRICAL
A4: Base: | B4: 1650 | C4: 1 | D4: =B4*C4 -> 1650
A5: Homerun: | B5: 18 | C5: =IF('NEW POOL'!B71>E5,'NEW POOL'!B71-E5,0) -> 0 | D5: =B5*C5 -> 0 | E5: 65 | F5: Included
A6: Lights: | B6: 100 | C6: =IF(STEEL!C18>E6,STEEL!C18-E6) -> 1 | D6: =B6*C6 -> 100 | E6: 1 | F6: Included
A7: Heater: | B7: 255 | C7: ='NEW POOL'!B121 -> 0 | D7: =B7*C7 -> 0
A8: Heatpump: | B8: =450 -> 450 | C8: =IF('NEW POOL'!E121="",0,1) -> 0 | D8: =B8*C8 -> 0
A9: Add'l Heatpump: | B9: 6 | C9: =IF('NEW POOL'!B73>40,'NEW POOL'!B73-40,0) -> 0 | D9: =B9*C9 -> 0 | E9: 40 | F9: Included
A10: Salt System: | B10: 200 | C10: ='NEW POOL'!E127+'NEW POOL'!E128+'NEW POOL'!E129 -> 0 | D10: =B10*C10 -> 0
A11: Automation: | B11: 250 | C11: ='NEW POOL'!B131 -> 1 | D11: =B11*C11 -> 250
A12: Bonding: | B12: 300 | C12: 1 | D12: =B12*C12 -> 300
A13: Outlet: | B13: 85 | C13: 1 | D13: =B13*C13 -> 85
A14: Travel: | B14: 7 | C14: ='NEW POOL'!E10 -> 0 | D14: =B14*C14 -> 0
A15: Auto Fill Run: | B15: 3 | C15: ='NEW POOL'!B134 -> 0 | D15: =B15*C15 -> 0 | E15: =D15/0.7 -> 0
D17: =SUM(D4:D16) -> 2385

Sheet SHOT
A1: AUGUST 2022
C2: Interior Area: | D2: =((('NEW POOL'!B9+'NEW POOL'!B10)/2)*'NEW POOL'!B7)+'NEW POOL'!B8 -> 1122 | E2: Yardage: | F2: =ROUNDUP(((((('NEW POOL'!B7*1)+(D2*0.67))+('NEW POOL'!B38))/24)+((('NEW POOL'!B17*1)+('NEW POOL'!B17*3)+(40))/25)+('NEW POOL'!B167/10))*1.1,0)+('NEW POOL'!B51/20)+('NEW POOL'!B18*2) -> 41
A3: SHOTCRETE - LABOR | J3: ='NEW POOL'!A32 -> 6" RBB: | K3: ='NEW POOL'!B32 -> 0 | L3: =K3*0.5 -> 0
A4: Minimum Labor: | B4: 90 | C4: =E4 -> 32 | D4: =B4*C4 -> 2880 | E4: 32 | F4: Minimum Labor Yardage | J4: ='NEW POOL'!A33 -> 12" RBB: | K4: ='NEW POOL'!B33 -> 0 | L4: =K4*1 -> 0
A5: Add'l Labor: | B5: =B4 -> 90 | C5: =IF(F2>32,F2-32,0) -> 9 | D5: =B5*C5 -> 810 | E5: 75 | F5: Included | J5: ='NEW POOL'!A34 -> 18" RBB: | K5: ='NEW POOL'!B34 -> 0 | L5: =K5*1.5 -> 0
A6: Spa: | B6: 250 | C6: =EXC!C27 -> 0 | D6: =B6*C6 -> 0 | E6: 1 | F6: Included | J6: ='NEW POOL'!A35 -> 24" RBB: | K6: ='NEW POOL'!B35 -> 0 | L6: =K6*2 -> 0
A7: Auto Cover: | B7: 250 | C7: =K13*'NEW POOL'!B49 -> 0 | D7: =B7*C7 -> 0 | E7: Per 6" | J7: ='NEW POOL'!A36 -> 30" RBB: | K7: ='NEW POOL'!B36 -> 0 | L7: =K7*2.5 -> 0
A8: Distance 251 to 300 | B8: 500 | C8: =IF('NEW POOL'!E11=1,1,0) -> 0 | D8: =B8*C8 -> 0 | J8: ='NEW POOL'!A37 -> 36" RBB: | K8: ='NEW POOL'!B37 -> 0 | L8: =K8*3 -> 0
A9: Distance 301 to 350 | B9: 1000 | C9: =IF('NEW POOL'!E11=2,1,0) -> 0 | D9: =B9*C9 -> 0
A10: Travel: | B10: 7 | C10: ='NEW POOL'!E10 -> 0 | D10: =B10*C10 -> 0 | F10: =B5+B15 -> 318 | K10: SQFT: | L10: =SUM(L3:L9) -> 0
A12: Labor Total: | D12: =SUM(D4:D11) -> 3690 | J12: Auto Cover
J13: ='NEW POOL'!E7+2 -> 18 | K13: =ROUNDUP((J13*7/22),0) -> 6 | L13: =D7+D17 -> 0
A14: SHOTCRETE -MATERIAL
A15: Per Yard: | B15: 228 | C15: =F2 -> 41 | D15: =B15*C15 -> 9348
A16: Clean-Out: | B16: 125 | C16: 1 | D16: =B16*C16 -> 125
A17: Auto Cover: | B17: =B15 -> 228 | C17: =C7 -> 0 | D17: =B17*C17 -> 0
A18: Environ / Fuel: | B18: 25 | C18: =C15 -> 41 | D18: =B18*C18 -> 1025
A19: Miscelaneous: | B19: 150 | C19: 1 | D19: 125
A20: Travel: | B20: 7 | C20: ='NEW POOL'!E10 -> 0 | D20: =B20*C20 -> 0
C21: Sub Total: | D21: =SUM(D15:D20) -> 10623
A22: MECK: | B22: 0.025 | D22: =D21*B22 -> 265.575
A23: NC: | B23: 0.0475 | D23: =D21*B23 -> 504.5925
A25: Material Total: | D25: =D21+D22+D23 -> 11393.168
A27: Total Shotcrete: | D27: =D12+D25 -> 15083.168

Sheet TILE COPING
A1: MAY 2022
A3: TILE | G3: TILE - RBB & COLUMNS
A4: Labor - Pool: | B4: 10 | C4: ='NEW POOL'!B7 -> 104 | D4: =B4*C4 -> 1040 | G4: ='NEW POOL'!A32 -> 6" RBB: | H4: ='NEW POOL'!B32 -> 0 | I4: =IF('NEW POOL'!C32=1,1,0) -> 0 | J4: =H4*0.5*I4 -> 0
A5: Material - Level 1 - Pool: | B5: 7 | C5: =$C$4*E5 -> 104 | D5: =B5*C5 -> 728 | E5: =IF('NEW POOL'!B81="INCLUDED",1,0) -> 1 | F5: Included | G5: ='NEW POOL'!A33 -> 12" RBB: | H5: ='NEW POOL'!B33 -> 0 | I5: =IF('NEW POOL'!C33=1,1,0) -> 0 | J5: =H5*2*I5 -> 0
A6: Material - Level 2 - Pool: | B6: 20 | C6: =$C$4*'NEW POOL'!B82 -> 0 | D6: =B6*C6 -> 0 | F6: Included | G6: ='NEW POOL'!A34 -> 18" RBB: | H6: ='NEW POOL'!B34 -> 0 | I6: =IF('NEW POOL'!C34=1,1,0) -> 0 | J6: =H6*3*I6 -> 0
A7: Material - Level 3 - Pool: | B7: 50 | C7: =$C$4*'NEW POOL'!B83 -> 0 | D7: =B7*C7 -> 0 | G7: ='NEW POOL'!A35 -> 24" RBB: | H7: ='NEW POOL'!B35 -> 0 | I7: =IF('NEW POOL'!C35=1,1,0) -> 0 | J7: =H7*4*I7 -> 0
A8: Labor - Spa: | B8: =B4 -> 10 | C8: ='NEW POOL'!B17 -> 0 | D8: =B8*C8 -> 0 | G8: ='NEW POOL'!A36 -> 30" RBB: | H8: ='NEW POOL'!B36 -> 0 | I8: =IF('NEW POOL'!C36=1,1,0) -> 0 | J8: =H92*I8 -> 0
A9: Material - Level 1 - Spa: | B9: =B5 -> 7 | C9: =$C$8*E9 -> 0 | D9: =B9*C9 -> 0 | E9: =E5 -> 1 | G9: ='NEW POOL'!A37 -> 36" RBB: | H9: ='NEW POOL'!B37 -> 0 | I9: =IF('NEW POOL'!C37=1,1,0) -> 0 | J9: =H9*6*I9 -> 0
A10: Material - Level 2 - Spa: | B10: =B6 -> 20 | C10: =$C$8*'NEW POOL'!B82 -> 0 | D10: =B10*C10 -> 0 | G10: Columns: | H10: =H48 -> 0 | I10: =IF('NEW POOL'!C40=1,1,0) -> 0 | J10: =H10*I10*((('NEW POOL'!$B$41*'NEW POOL'!$B$43*2)+('NEW POOL'!$B$42*'NEW POOL'!$B$43*2))*2) -> 0
A11: Material - Level 3 - Spa: | B11: =B7 -> 50 | C11: =$C$8*'NEW POOL'!B83 -> 0 | D11: =B11*C11 -> 0 | I11: LNFT | J11: =SUM(J4:J10) -> 0
A12: Labor - Other: | B12: =B8 -> 10 | C12: =J14+J11+'NEW POOL'!B77 -> 0 | D12: =B12*C12 -> 0 | M12: ='NEW POOL'!B82+'NEW POOL'!B83 -> 0
A13: Material - Level 1 - Other: | B13: =B9 -> 7 | C13: =IF(M12=1,0,'TILE COPING'!C12) -> 0 | D13: =B13*C13 -> 0 | E13: =E5 -> 1 | G13: SPA FACING
A14: Material - Level 2 - Other: | B14: =B10 -> 20 | C14: =C12*'NEW POOL'!B82 -> 0 | D14: =B14*C14 -> 0 | G14: Tile: | H14: ='NEW POOL'!$B$18 -> 0 | I14: =IF('NEW POOL'!B19=1,1,0) -> 0 | J14: =ROUNDUP(((H14*I14*'NEW POOL'!$B$17*3)*1.1),0) -> 0 | K14: LNFT
A15: Material - Level 3 - Other: | B15: =B11 -> 50 | C15: =C12*'NEW POOL'!B83 -> 0 | D15: =B15*C15 -> 0 | G15: Panel: | H15: ='NEW POOL'!$B$18 -> 0 | I15: =IF('NEW POOL'!B19=2,1,0) -> 0 | J15: =ROUNDUP(((H15*I15*'NEW POOL'!$B$17*1.5)*1.1),0) -> 0 | K15: SQFT
A16: Trim Tile - Labor: | B16: 10 | C16: =('NEW POOL'!B11+('NEW POOL'!B17*0.8))*'NEW POOL'!B79 -> 0 | D16: =B16*C16 -> 0 | G16: Stacked: | H16: ='NEW POOL'!$B$18 -> 0 | I16: =IF('NEW POOL'!B19=3,1,0) -> 0 | J16: =ROUNDUP(((H16*I16*'NEW POOL'!$B$17*1.5)*1.1),0) -> 0 | K16: SQFT
A17: Trim Tile - Material: | B17: 4 | C17: =C16 -> 0 | D17: =B17*C17 -> 0
A18: Travel: | B18: 7 | C18: ='NEW POOL'!E10 -> 0 | D18: =B18*C18 -> 0 | F18: REMODEL | J18: Pool | K18: =REMODEL!B7 -> 80
F19: Labor - Remove & Replace Tile | I19: 19.5 | J19: Spa | K19: =REMODEL!B17 -> 0
A20: Tile Total: | D20: =SUM(D4:D19) -> 1768 | F20: Skimmers | I20: 50 | J20: Skimmers | K20: =REMODEL!B37 -> 1
F21: =A5 -> Material - Level 1 - Pool: | I21: =B5 -> 7 | J21: =IF(REMODEL!B39="INCLUDED",1,0) -> 1
A22: COPING / DECKING - LABOR | F22: =A6 -> Material - Level 2 - Pool: | I22: =B6 -> 20 | J22: =REMODEL!B40 -> 0
A23: Paver Coping - Labor: | B23: 12 | C23: =ROUNDUP((('NEW POOL'!$B$7*1.1)+('NEW POOL'!$B$17*2.15)),0)*'NEW POOL'!B87 -> 0 | D23: =B23*C23 -> 0 | E23: LNFT | F23: =A7 -> Material - Level 3 - Pool: | I23: =B7 -> 50 | J23: =REMODEL!B41 -> 0
A24: Paver Decking - Labor: | B24: 8 | C24: ='NEW POOL'!E9*1.05*'NEW POOL'!B88 -> 875.7 | D24: =B24*C24 -> 7005.6 | E24: SQFT | F24: Remove Joint / Install Caulk | I24: 7.5
A25: Travertine Coping - Labor: | B25: =B23 -> 12 | C25: =ROUNDUP((('NEW POOL'!$B$7*1.1)+('NEW POOL'!$B$17*2.15)),0)*('NEW POOL'!B90+'NEW POOL'!B93) -> 115 | D25: =B25*C25 -> 1380 | E25: LNFT | F25: Crack Repair | I25: 22
A26: Travertine Decking - Labor: | B26: =B24 -> 8 | C26: ='NEW POOL'!E9*1.05*('NEW POOL'!B91+'NEW POOL'!B94) -> 0 | D26: =B26*C26 -> 0 | E26: SQFT | F26: Coping: | G26: =DEMO!D6 -> 0
A27: Flagstone Coping - Labor: | B27: 15 | C27: =ROUNDUP((('NEW POOL'!$B$7*1.1)+('NEW POOL'!$B$17*2.15)),0)*'NEW POOL'!B85 -> 0 | D27: =B27*C27 -> 0 | F27: Decking: | G27: =REMODEL!E9 -> 0
A28: Concrete Decking - Cantilever: | B28: 16.5 | C28: =('NEW POOL'!B7*'NEW POOL'!B96)*'NEW POOL'!B96 -> 0 | D28: =B28*C28 -> 0 | E28: SQFT
A29: Concrete Pump | B29: 600 | C29: =IF(('NEW POOL'!B96+'NEW POOL'!B97)>0,1,0) -> 0 | D29: =B29*C29 -> 0
A30: Concrete Steps: | B30: 27 | C30: ='NEW POOL'!B98 -> 0 | D30: =B30*C30 -> 0 | F30: Ivory, Hazelnut, Noce, Country Classic, Light Noce, Harvest Blend
A31: Total Labor: | D31: =SUM(D23:D30) -> 8385.6 | F31: Ivory, Hazelnut, Noce, Country Classic, Light Noce, Harvest Blend
F32: Silver, Silver Vogue, River Silver, Bianco Dolomite, Dianna Royal, Skyline, Alaska Silver, Turkish Carrea
A33: COPING / DECKING - MATERIAL | F33: Silver, Silver Vogue, River Silver, Bianco Dolomite, Dianna Royal, Skyline, Alaska Silver, Turkish Carrea
A34: Paver Coping - Material: | B34: 9 | C34: =C23 -> 0 | D34: =B34*C34 -> 0 | E34: LNFT | F34: =1000+120 -> 1120 | G34: 90 | I34: Base | J34: Add'l
A35: Paver Decking - Material: | B35: 3.25 | C35: =C24 -> 875.7 | D35: =B35*C35 -> 2846.025 | E35: SQFT | G35: 4' Band on Pool: | H35: ='NEW POOL'!B97 -> 0 | I35: =(H35*'NEW POOL'!B7*4)*1.1 -> 0 | J35: ='NEW POOL'!E9-'TILE COPING'!I35 -> 834
A36: Travertine Coping - Level 1: | B36: 11 | C36: =IF('NEW POOL'!B90=1,C25,0) -> 0 | D36: =B36*C36 -> 0 | E36: LNFT
A37: Travertine Decking - Level 1: | B37: 7.5 | C37: =IF('NEW POOL'!B91=1,C26,0) -> 0 | D37: =B37*C37 -> 0 | E37: SQFT
A38: Travertine Coping - Level 2: | B38: 12 | C38: =IF('NEW POOL'!B93=1,C25,0) -> 115 | D38: =B38*C38 -> 1380 | E38: LNFT
A39: Travertine Decking - Level 2: | B39: 9.75 | C39: =IF('NEW POOL'!B94=1,C26,0) -> 0 | D39: =B39*C39 -> 0 | E39: SQFT
A40: Flagstone - Material | B40: 25 | C40: ='NEW POOL'!B85*'NEW POOL'!B7 -> 0 | D40: =B40*C40 -> 0 | E40: LNFT
A41: Concrete Decking - Base: | B41: 7 | C41: =CEILING(I35,10) -> 0 | D41: =B41*C41 -> 0 | E41: SQFT | G41: PANEL LEDGE - RBB & COLUMNS | L41: STACKED STONE - RBB & COLUMNS
A42: Concrete Decking - Add'l: | B42: 7 | C42: =IF('NEW POOL'!B97>0,CEILING(J35,10),0) -> 0 | D42: =B42*C42 -> 0 | E42: SQFT | G42: ='NEW POOL'!A32 -> 6" RBB: | H42: ='NEW POOL'!B32 -> 0 | I42: =IF('NEW POOL'!C32=2,1,0) -> 0 | J42: =H42*0.5*I42 -> 0 | L42: =G42 -> 6" RBB: | M42: =H42 -> 0 | N42: =IF('NEW POOL'!C32=3,1,0) -> 0 | O42: =M42*0.5*N42 -> 0
A43: Concrete Band for Fiberglass: | B43: 7 | C43: =(('NEW POOL'!B21+'NEW POOL'!B22+'NEW POOL'!B23)*'NEW POOL'!B7*1.25) -> 0 | D43: =B43*C43 -> 0 | E43: SQFT | G43: ='NEW POOL'!A33 -> 12" RBB: | H43: ='NEW POOL'!B33 -> 0 | I43: =IF('NEW POOL'!C33=2,1,0) -> 0 | J43: =H43*1*I43 -> 0 | L43: =G43 -> 12" RBB: | M43: =H43 -> 0 | N43: =IF('NEW POOL'!C33=3,1,0) -> 0 | O43: =M43*1*N43 -> 0
G44: ='NEW POOL'!A34 -> 18" RBB: | H44: ='NEW POOL'!B34 -> 0 | I44: =IF('NEW POOL'!C34=2,1,0) -> 0 | J44: =H44*1.5*I44 -> 0 | L44: =G44 -> 18" RBB: | M44: =H44 -> 0 | N44: =IF('NEW POOL'!C34=3,1,0) -> 0 | O44: =M44*1.5*N44 -> 0
A45: Total Material: | D45: =SUM(D34:D44) -> 4226.025 | G45: ='NEW POOL'!A35 -> 24" RBB: | H45: ='NEW POOL'!B35 -> 0 | I45: =IF('NEW POOL'!C35=2,1,0) -> 0 | J45: =H45*2*I45 -> 0 | L45: =G45 -> 24" RBB: | M45: =H45 -> 0 | N45: =IF('NEW POOL'!C35=3,1,0) -> 0 | O45: =M45*2*N45 -> 0
G46: ='NEW POOL'!A36 -> 30" RBB: | H46: ='NEW POOL'!B36 -> 0 | I46: =IF('NEW POOL'!C36=2,1,0) -> 0 | J46: =H46*2.5*I46 -> 0 | L46: =G46 -> 30" RBB: | M46: =H46 -> 0 | N46: =IF('NEW POOL'!C36=3,1,0) -> 0 | O46: =M46*2.5*N46 -> 0
A47: STONE / ROCKWORK | G47: ='NEW POOL'!A37 -> 36" RBB: | H47: ='NEW POOL'!B37 -> 0 | I47: =IF('NEW POOL'!C37=2,1,0) -> 0 | J47: =H47*3*I47 -> 0 | L47: =G47 -> 36" RBB: | M47: =H47 -> 0 | N47: =IF('NEW POOL'!C37=3,1,0) -> 0 | O47: =M47*3*N47 -> 0
A48: Panel Ledge - Labor: | B48: 12.5 | C48: =ROUNDUP((J49+J15),0) -> 0 | D48: =B48*C48 -> 0 | E48: SQFT | G48: Columns: | H48: ='NEW POOL'!B40 -> 0 | I48: =IF('NEW POOL'!C40=2,1,0) -> 0 | J48: =H48*I48*(('NEW POOL'!$B$41*'NEW POOL'!$B$43*2)+('NEW POOL'!$B$42*'NEW POOL'!$B$43*2)) -> 0 | L48: Columns: | M48: =H48 -> 0 | N48: =IF('NEW POOL'!C40=3,1,) -> 0 | O48: =M48*N48*(('NEW POOL'!$B$41*'NEW POOL'!$B$43*2)+('NEW POOL'!$B$42*'NEW POOL'!$B$43*2)) -> 0
A49: Stacked Stone - Labor: | B49: 16 | C49: =ROUNDUP((J16+O49),0) -> 0 | D49: =B49*C49 -> 0 | E49: SQFT | I49: SQFT | J49: =SUM(J42:J48) -> 0 | N49: SQFT | O49: =SUM(O42:O48) -> 0
A50: Bullnose Labor: | B50: 8 | C50: ='NEW POOL'!B167 -> 0 | D50: =B50*C50 -> 0 | E50: lnft
A51: Spillway - Labor: | B51: 150 | C51: ='NEW POOL'!B18 -> 0 | D51: =B51*C51 -> 0
A52: Total Labor: | D52: =SUM(D46:D51) -> 0
A54: Panel Ledge - Material: | B54: 13 | C54: =C48*1.15 -> 0 | D54: =B54*C54 -> 0 | E54: SQFT
A55: Stacked Stone - Material: | B55: 27 | C55: =C49*1.15 -> 0 | D55: =B55*C55 -> 0 | E55: SQFT
A56: Rockwork - Material: | B56: 0 | C56: =C50*1.05 -> 0 | D56: =B56*C56 -> 0 | E56: lnft
A57: Spillway - Material: | B57: 150 | C57: =C51 -> 0 | D57: =B57*C57 -> 0
A58: Total Material: | D58: =SUM(D54:D57) -> 0

Sheet MASONRY
A1: AUGUST 2023
A3: Retaining Walls
B4: Total Height | C4: $/SQFT | D4: $/LNFT | E4: LNFT | F4: COST
A5: No Retaining Wall | B5: 0 | C5: 0 | D5: 0 | E5: 0 | F5: 0
A6: 12" High - Standard | B6: 2 | C6: 50 | D6: =B6*C6 -> 100 | E6: ='NEW POOL'!B171 -> 0 | F6: =D6*E6 -> 0
A7: 24" High - Standard | B7: 3 | C7: =C6 -> 50 | D7: =B7*C7 -> 150 | E7: =E6 -> 0 | F7: =D7*E7 -> 0
A8: 36" High - Standard | B8: 4 | C8: =C7 -> 50 | D8: =B8*C8 -> 200 | E8: =E7 -> 0 | F8: =D8*E8 -> 0
A9: 48" High - Standard | B9: 5 | C9: =C8 -> 50 | D9: =B9*C9 -> 250 | E9: =E8 -> 0 | F9: =D9*E9 -> 0
A10: 12" High - CMU - Veneer Facing - 1-Side | B10: =B6 -> 2 | C10: 65 | D10: =B10*C10 -> 130 | E10: =E9 -> 0 | F10: =D10*E10 -> 0
A11: 24" High - CMU - Veneer Facing - 1-Side | B11: =B7 -> 3 | C11: =C10 -> 65 | D11: =B11*C11 -> 195 | E11: =E10 -> 0 | F11: =D11*E11 -> 0
A12: 36" High - CMU - Veneer Facing - 1-Side | B12: =B8 -> 4 | C12: =C11 -> 65 | D12: =B12*C12 -> 260 | E12: =E11 -> 0 | F12: =D12*E12 -> 0
A13: 48" High - CMU - Veneer Facing - 1-Side | B13: =B9 -> 5 | C13: =C12 -> 65 | D13: =B13*C13 -> 325 | E13: =E12 -> 0 | F13: =D13*E13 -> 0
A14: 12" High - CMU - Veneer Facing - 2-Sides | B14: =B10 -> 2 | C14: 75 | D14: =B14*C14 -> 150 | E14: =E13 -> 0 | F14: =D14*E14 -> 0
A15: 24" High - CMU - Veneer Facing - 2-Sides | B15: =B11 -> 3 | C15: =C14 -> 75 | D15: =B15*C15 -> 225 | E15: =E14 -> 0 | F15: =D15*E15 -> 0
A16: 36" High - CMU - Veneer Facing - 2-Sides | B16: =B12 -> 4 | C16: =C15 -> 75 | D16: =B16*C16 -> 300 | E16: =E15 -> 0 | F16: =D16*E16 -> 0
A17: 48" High - CMU - Veneer Facing - 2-Sides | B17: =B13 -> 5 | C17: =C16 -> 75 | D17: =B17*C17 -> 375 | E17: =E16 -> 0 | F17: =D17*E17 -> 0
A18: Includes 12" Footer

Sheet DEMO
A1: March 2023
A3: DEMO
A4: Cut | B4: 2.8 | C4: =IF(C5=1,0,1) -> 0 | D4: =INT!E23 -> 1122 | E4: =B4*D4*C4 -> 0
A5: Full Chip Out | B5: 3.5 | C5: =REMODEL!B24 -> 1 | D5: =D4 -> 1122 | E5: =B5*D5*C5 -> 3927
A6: Remove Coping | B6: 20 | C6: =REMODEL!B25 -> 0 | D6: =(REMODEL!B7+REMODEL!B17)*REMODEL!B25 -> 0 | E6: =B6*C6*D6 -> 0
A7: Remove Decking | B7: 4 | C7: =REMODEL!B26 -> 0 | E7: =B7*C7 -> 0
E11: =SUM(E4:E10) -> 3927

Sheet INT
A1: FEBRUARY 2023
A3: INTERIOR | E3: =SHOT!D2 -> 1122 | O3: Retail | P3: Upgrade | Q3: Rounded
A4: 1 | B4: 2 | C4: 3 | D4: 4 | E4: 5 | F4: 6 | G4: 7 | H4: 8 | I4: 9 | J4: 10 | K4: 11 | L4: 12 | M4: 13 | N4: 14 | O4: 15 | P4: 16 | Q4: 17 | R4: 18
E5: Spa | H5: Pool Prep | I5: Spa Prep | J5: Drains | K5: Vac | L5: Returns | M5: Hydro | N5: Total | O5: 0.7
A6: Ivory Quartz | B6: 5.5 | C6: =IF(E3<851,850,E3) -> 1122 | D6: =B6*C6 -> 6171 | E6: 850 | F6: =EXC!C27 -> 0 | G6: =E6*F6 -> 0 | H6: 850 | I6: =D25 -> 0 | J6: =('NEW POOL'!B113+'NEW POOL'!B114+'NEW POOL'!B115)*2*15 -> 30 | K6: ='NEW POOL'!B119*20 -> 0 | L6: 20 | M6: 60 | N6: =SUM(G6:M6)+D6 -> 7131 | O6: =N6/$O$5 -> 10187.143 | R6: Ivory / Blue / French Grey / Super Blue / Mariner Blue / Tropical Blue / Sky Blue
A7: Pebble Tec - Level 1 | B7: 6.3 | C7: =IF(E3<851,850,E3) -> 1122 | D7: =B7*C7 -> 7068.6 | E7: 1150 | F7: =F6 -> 0 | G7: =E7*F7 -> 0 | H7: =H6 -> 850 | I7: =I6 -> 0 | J7: =J6 -> 30 | K7: =K6 -> 0 | L7: 20 | M7: 60 | N7: =SUM(G7:M7)+D7 -> 8028.6 | O7: =N7/$O$5 -> 11469.429 | P7: =O7-O6 -> 1282.2857 | Q7: =CEILING(P7,10) -> 1290 | R7: Caribbean Blue / Sandy Beach / Tahoe Blue / White Pearl
A8: Pebble Tec - Level 2 | B8: 7.9 | C8: =IF(E3<851,850,E3) -> 1122 | D8: =B8*C8 -> 8863.8 | E8: =E7 -> 1150 | F8: =F6 -> 0 | G8: =E8*F8 -> 0 | H8: =H7 -> 850 | I8: =I7 -> 0 | J8: =J6 -> 30 | K8: =K7 -> 0 | L8: 20 | M8: 60 | N8: =SUM(G8:M8)+D8 -> 9823.8 | O8: =N8/$O$5 -> 14034 | P8: =O8-$O$6 -> 3846.8571 | Q8: =CEILING(P8,10) -> 3850 | R8: Black Marble / Black Pearl / Blue Lagood / Blue Wave
A9: Pebble Tec - Level 3 | B9: 8.85 | C9: =IF(E3<851,850,E3) -> 1122 | D9: =B9*C9 -> 9929.7 | E9: =E8 -> 1150 | F9: =F8 -> 0 | G9: =E9*F9 -> 0 | H9: =H8 -> 850 | I9: =I8 -> 0 | J9: =J8 -> 30 | K9: =K8 -> 0 | L9: 20 | M9: 60 | N9: =SUM(G9:M9)+D9 -> 10889.7 | O9: =N9/$O$5 -> 15556.714 | P9: =O9-$O$6 -> 5369.5714 | Q9: =CEILING(P9,10) -> 5370 | R9: Crème de Menthe / Emerald Bay / Midnight Blue / Moonlight Grey / Sky Blue / Soft White / Tropical Breeze
A10: Pebble Sheen - Level 1 | B10: 6.75 | C10: =IF(E3<851,850,E3) -> 1122 | D10: =B10*C10 -> 7573.5 | E10: 1250 | F10: =F9 -> 0 | G10: =E10*F10 -> 0 | H10: =H9 -> 850 | I10: =I9 -> 0 | J10: =J9 -> 30 | K10: =K9 -> 0 | L10: 20 | M10: 60 | N10: =SUM(G10:M10)+D10 -> 8533.5 | O10: =N10/$O$5 -> 12190.714 | P10: =O10-$O$6 -> 2003.5714 | Q10: =CEILING(P10,10) -> 2010 | R10: Bordeaux / Desert Gold / French Grey / Irish Mist / White Diamonds / HighTech Caribbean Blue / High Tech Tahoe Blue
A11: Pebble Sheen - Level 2 | B11: 7.85 | C11: =IF(E3<851,850,E3) -> 1122 | D11: =B11*C11 -> 8807.7 | E11: =E10 -> 1250 | F11: =F10 -> 0 | G11: =E11*F11 -> 0 | H11: =H10 -> 850 | I11: =I10 -> 0 | J11: =J10 -> 30 | K11: =K10 -> 0 | L11: 20 | M11: 60 | N11: =SUM(G11:M11)+D11 -> 9767.7 | O11: =N11/$O$5 -> 13953.857 | P11: =O11-$O$6 -> 3766.7143 | Q11: =CEILING(P11,10) -> 3770 | R11: Aqua Blue / Blue Granite / Black Onyx / Blue Surf / Black Eclipse
A12: Pebble Sheen - Level 3 | B12: 9.25 | C12: =IF(E3<851,850,E3) -> 1122 | D12: =B12*C12 -> 10378.5 | E12: =E11 -> 1250 | F12: =F11 -> 0 | G12: =E12*F12 -> 0 | H12: =H11 -> 850 | I12: =I11 -> 0 | J12: =J11 -> 30 | K12: =K11 -> 0 | L12: 20 | M12: 60 | N12: =SUM(G12:M12)+D12 -> 11338.5 | O12: =N12/$O$5 -> 16197.857 | P12: =O12-$O$6 -> 6010.7143 | Q12: =CEILING(P12,10) -> 6020 | R12: Artic White / Cool Blue / Ocean Blue / Prism Blue / Slate Blue / Turtle Bay
A13: Pebble Fina - Level 1 | B13: 7.75 | C13: =IF(E3<851,850,E3) -> 1122 | D13: =B13*C13 -> 8695.5 | E13: 1050 | F13: =F12 -> 0 | G13: =E13*F13 -> 0 | H13: =H9 -> 850 | I13: =I9 -> 0 | J13: =J9 -> 30 | K13: =K12 -> 0 | L13: 20 | M13: 60 | N13: =SUM(G13:M13)+D13 -> 9655.5 | O13: =N13/$O$5 -> 13793.571 | P13: =O13-$O$6 -> 3606.4286 | Q13: =CEILING(P13,10) -> 3610 | R13: Acquos / Bella Blue / Classico / Grigio / Steel Grey
A14: Pebble Fina - Level 2 | B14: 10 | C14: =IF(E3<851,850,E3) -> 1122 | D14: =B14*C14 -> 11220 | E14: 1675 | F14: =F13 -> 0 | G14: =E14*F14 -> 0 | H14: =H13 -> 850 | I14: =I13 -> 0 | J14: =J13 -> 30 | K14: =K13 -> 0 | L14: 20 | M14: 60 | N14: =SUM(G14:M14)+D14 -> 12180 | O14: =N14/$O$5 -> 17400 | P14: =O14-$O$6 -> 7212.8571 | Q14: =CEILING(P14,10) -> 7220 | R14: Cielo Blue / Egyptian Sand / Fresca Verde
A15: Pebble Brilliance | B15: 17 | C15: =IF(E3<851,850,E3) -> 1122 | D15: =B15*C15 -> 19074 | E15: 1050 | F15: =F14 -> 0 | G15: =E15*F15 -> 0 | H15: =H14 -> 850 | I15: =I14 -> 0 | J15: =J14 -> 30 | K15: =K14 -> 0 | L15: 20 | M15: 60 | N15: =SUM(G15:M15)+D15 -> 20034 | O15: =N15/$O$5 -> 28620 | P15: =O15-$O$6 -> 18432.857 | Q15: =CEILING(P15,10) -> 18440 | R15: All Colors
A16: Pebble Breeze | B16: 23 | C16: =IF(E3<851,850,E3) -> 1122 | D16: =B16*C16 -> 25806 | E16: 1150 | F16: =F12 -> 0 | G16: =E16*F16 -> 0 | H16: =H12 -> 850 | I16: =I12 -> 0 | J16: =J12 -> 30 | K16: =K15 -> 0 | L16: 20 | M16: 60 | N16: =SUM(G16:M16)+D16 -> 26766 | O16: =N16/$O$5 -> 38237.143 | P16: =O16-$O$6 -> 28050 | Q16: =CEILING(P16,10) -> 28050 | R16: All Colors
A17: Pebble Essence | B17: 17.5 | C17: =IF(E3<851,850,E3) -> 1122 | D17: =B17*C17 -> 19635 | E17: 1150 | F17: =F16 -> 0 | G17: =E17*F17 -> 0 | H17: =H16 -> 850 | I17: =I16 -> 0 | J17: =J16 -> 30 | K17: =K16 -> 0 | L17: 20 | M17: 60 | N17: =SUM(G17:M17)+D17 -> 20595 | O17: =N17/$O$5 -> 29421.429 | P17: =O17-$O$6 -> 19234.286 | Q17: =CEILING(P17,10) -> 19240 | R17: All Colors
B18: 0 | C18: =C17 -> 1122 | D18: =B18*C18 -> 0 | E18: 1150 | F18: =F17 -> 0 | G18: =E18*F18 -> 0 | H18: =H17 -> 850 | I18: =I17 -> 0 | J18: =J17 -> 30 | K18: =K17 -> 0 | L18: 20 | M18: 60 | N18: =SUM(G18:M18)+D18 -> 960 | O18: =N18/$O$5 -> 1371.4286 | P18: =O18-$O$6 -> -8815.7143 | Q18: =CEILING(P18,10) -> -8810
A20: Misc: | B20: 100 | C20: 1 | D20: =B20*C20 -> 100
A21: Travel: | B21: 10 | C21: ='NEW POOL'!E10 -> 0 | D21: =B21*C21 -> 0
A22: Step & Bench Detail: | B22: 20 | C22: =IF('NEW POOL'!B11>20,'NEW POOL'!B11-20,0) -> 50 | D22: =B22*C22 -> 1000
A23: Pool Prep up to 1,200: | B23: 750 | C23: 1 | D23: =B23*C23 -> 750 | E23: =(('NEW POOL'!B7*(('NEW POOL'!B9+'NEW POOL'!B10)/2))+'NEW POOL'!B8) -> 1122
A24: Prep over 1,200: | B24: 1 | C24: =IF(E23>1200,E23-1200,0) -> 0 | D24: =B24*C24 -> 0
A25: Spa Prep: | B25: 250 | C25: =IF('NEW POOL'!B17>0,1,0) -> 0 | D25: =B25*C25 -> 0
A27: Water Truck - Shotcrete | C27: =_xlfn.CEILING.MATH(E27/7000,0.5) -> 3.5 | E27: ='NEW POOL'!E13 -> 22990 | F27: Gallons
A28: Full Truck: | B28: 490 | C28: =C27 -> 3.5 | D28: =B28*C28 -> 1715 | E28: 7,000 Gallons
A30: Microglass - Shotcrete
A31: Pool - SQFT: | B31: 0 | C31: =E31 -> 1122 | D31: =B31*C31 -> 0 | E31: =(('NEW POOL'!B7*(('NEW POOL'!B9+'NEW POOL'!B10)/2)))+'NEW POOL'!B8 -> 1122 | F31: IA
A32: Spa - SQFT: | B32: =B31 -> 0 | C32: =E32 -> 0 | D32: =B32*C32 -> 0 | E32: =(('NEW POOL'!B14*'NEW POOL'!B15)+((('NEW POOL'!B14*2)+('NEW POOL'!B15*2))*1.7)) -> 0 | F32: IA
A33: Raised Spa: | B33: 300 | C33: ='NEW POOL'!B18 -> 0 | D33: =B33*C33 -> 0
D34: =SUM(D31:D33) -> 0
A36: Premium Start-Up

Sheet REMODEL
A1: 2023 REMODEL PRICING MASTER - MARCH
A3: CUSTOMER NAME:
A4: CITY:
A5: Additional Layout: | B5: 0
A7: Perimeter: | B7: 80 | C7: LNFT | D7: Max Width: | E7: 17 | F7: FT | K7: =IF(#REF!+#REF!+#REF!>0,1,0) -> #REF!
A8: Surface Area: | B8: 400 | C8: SQFT | D8: Max Length: | E8: 30 | F8: FT
A9: Shallow Depth: | B9: 3.5 | C9: FT | D9: New Decking: | E9: 0 | F9: SQFT
A10: End Depth: | B10: 6 | C10: FT | D10: Travel: | E10: 0 | F10: MILES
A11: Total Step & Bench: | B11: 20 | C11: LNFT | D11: Pool to Street: | E11: 0 | F11: ( 1 if 251 to 300, 2 if 300 to 350)
A12: Tanning Shelf: | B12: 1 | C12: 1 for Yes, 0 for No
D13: Approx. Gallons: | E13: =_xlfn.CEILING.MATH(((B8*((B9+B10)/2))*7.6),10)-(B12*850) -> 13590
A14: Spa Length: | B14: 0
A15: Spa Width: | B15: 0
A16: Spa Shape: | B16: 0 | C16: ( 1 for Round, 2 for Square )
A17: Spa Perimeter: | B17: =ROUNDUP(IF(B16=1,(B14*3.14),(B14*2+B15*2)),0) -> 0
A18: Raised Spa?: | B18: 0 | C18: ( 1 for Yes, 0 for No) | E18: (Raised Spa = +18")
A19: Raised Spa Facing: | B19: 0 | C19: ( 1=Tile / 2=Ledgstone / 3=Stacked Stone)
A22: DEMOLITION
A24: Chip Out - Existing Interior: | B24: 1
A25: Remove Coping: | B25: 0
A26: Remove Exsiting Decking: | B26: 0 | C26: SQFT
A28: TILE / COPING / DECKING
A30: Remove & Replace Tile: | B30: 1
A31: Additional Tile Remove & Replace: | B31: 0 | C31: SQFT
A32: Remove Expansion Between Tile & Coping: | B32: 0
A33: Crack Repair | B33: 0 | C33: LNFT
A35: Add Trim Tile to Steps & Bench | B35: 0
A37: Number of Skimmers: | B37: 1
A39: Level 1 Tile | B39: =IF(B30>0,"INCLUDED",0) -> INCLUDED
A40: Upgrade Tile - Level 2 | B40: 0
A41: Upgrade Tile - Level 3 | B41: 0
A43: Flagstone Coping: | B43: 0 | C43: Enter "1" to Select
A45: Paver Coping: | B45: 0 | C45: Enter "1" to Select
A46: Paver Decking: | B46: 0 | C46: Enter "1" to Select
A48: Travertine Coping - Level 1: | B48: 0 | C48: Enter "1" to Select | E48: ='TILE COPING'!F30 -> Ivory, Hazelnut, Noce, Country Classic, Light Noce, Harvest Blend
A49: Travertine Decking - Level 1: | B49: 0 | C49: Enter "1" to Select | E49: ='TILE COPING'!F31 -> Ivory, Hazelnut, Noce, Country Classic, Light Noce, Harvest Blend
A51: Travertine Coping - Level 2: | B51: 0 | C51: Enter "1" to Select | E51: ='TILE COPING'!F32 -> Silver, Silver Vogue, River Silver, Bianco Dolomite, Dianna Royal, Skyline, Alaska Silver, Turkish Carrea
A52: Travertine Decking - Level 2: | B52: 0 | C52: Enter "1" to Select | E52: ='TILE COPING'!F33 -> Silver, Silver Vogue, River Silver, Bianco Dolomite, Dianna Royal, Skyline, Alaska Silver, Turkish Carrea
A54: Concrete Coping: | B54: 0 | C54: Enter "1" to Select
A55: Concrete Decking: | B55: 0 | C55: Enter "1" to Select
A57: Rough Grading | B57: 0
A59: DRAINAGE
A61: Downspout #1 | B61: 0 | C61: Enter LNFT
A62: Downspout #2 | B62: 0 | C62: Enter LNFT
A63: Downspout #3 | B63: 0 | C63: Enter LNFT
A64: Downspout #4 | B64: 0 | C64: Enter LNFT
A66: EQUIPMENT
A68: PUMPS / FILTER / CLEANER / HEATER
A70: No Auxiliary Pump | B70: =IF(A70="No Auxiliary Pump",0,1) -> 0 | C70: =(VLOOKUP(A70,EQUIP!$M$14:$S$20,6,FALSE)) -> 0
A71: No Auxiliary Pump | B71: =IF(C71>0,1,0) -> 0 | C71: =(VLOOKUP(A71,EQUIP!$M$14:$S$20,6,FALSE)) -> 0
A72: No Auxiliary Pump | B72: =IF(C72>0,1,0) -> 0 | C72: =(VLOOKUP(A72,EQUIP!$M$14:$S$20,6,FALSE)) -> 0
A74: No Filter | B74: =IF(A74="No Filter",0,1) -> 0 | C74: =(VLOOKUP(A74,EQUIP!M22:S28,6,FALSE)) -> 0
A76: No Cleaner | B76: =IF(C76>0,1,0) -> 0 | C76: =VLOOKUP(A76,EQUIP!M31:S33,7,FALSE) -> 0
A78: No Heater | B78: =IF(A78="No Heater",0,1) -> 0 | C78: =VLOOKUP(A78,EQUIP!M36:S39,6,FALSE) -> 0 | E78: =IF(A78="Jandy 260K BTU - JXI Heater", "CANNOT BE USED TO HEAT A SPA","")
A79: Upgrade Heater to VersaFlo | B79: 0 | C79: =B79*EQUIP!R39 -> 0
A81: No Lights | B81: 0 | C81: =(VLOOKUP(A81,EQUIP!M42:R46,6,FALSE))*B81 -> #N/A
A83: No Sanitation | B83: =IF(C83>0,1,0) -> 0 | C83: =VLOOKUP(A83,EQUIP!M49:S57,6,FALSE) -> 0 | E83: =IF(C83=1280,1,0) -> 0 | F83: =IF(A83=EQUIP!M57,1,0) -> 0 | G83: =B87 -> 0 | H83: =F83*G83 -> 0
A84: No Sanitation | B84: =IF(C84>0,1,0) -> 0 | C84: =VLOOKUP(A84,EQUIP!M49:S57,6,FALSE) -> 0 | E84: =IF(C84=1280,1,0) -> 0 | F84: =IF(A84=EQUIP!M57,1,0) -> 0 | G84: =B87 -> 0 | H84: =F84*G84 -> 0
A85: No Sanitation | B85: =IF(C85>0,1,0) -> 0 | C85: =VLOOKUP(A85,EQUIP!M49:S57,6,FALSE) -> 0 | E85: =IF(C85=1280,1,0) -> 0 | F85: =IF(A85=EQUIP!M57,1,0) -> 0 | G85: =B87 -> 0 | H85: =F85*G85 -> 0
A87: No Automation | B87: =IF(C87>0,1,0) -> 0 | C87: =VLOOKUP(A87,EQUIP!M63:S72,7,FALSE)*1.2 -> 0
A89: No Auto-Fill | B89: =IF(A89=EQUIP!M105,0,1) -> 0 | C89: =VLOOKUP(A89,EQUIP!M105:S107,7,FALSE)+(ELEC!E15) -> 0
A90: Electric Autofill Run | B90: 0 | C90: LNFT
A92: CUSTOM FEATURES
A94: =CUSTOM!A3 -> Parged Concrete | B94: =IF(C94>0,1,0) -> 0 | C94: =CUSTOM!G3 -> 0 | E94: Enter Cost on Custom Tab
A96: =CUSTOM!A5 -> Oversized coping | B96: =IF(C96>0,1,0) -> 1 | C96: =CUSTOM!G5 -> 1177.1429 | E96: Enter Cost on Custom Tab
A98: =CUSTOM!A7 -> handrail | B98: =IF(C98>0,1,0) -> 1 | C98: =CUSTOM!G7 -> 1468.5714 | E98: Enter Cost on Custom Tab
A100: =CUSTOM!A9 -> No Custom Feature | B100: =IF(C100>0,1,0) -> 0 | C100: =CUSTOM!G9 -> 0 | E100: Enter Cost on Custom Tab
A102: =CUSTOM!A11 -> No Custom Feature | B102: =IF(C102>0,1,0) -> 0 | C102: =CUSTOM!G11 -> 0 | E102: Enter Cost on Custom Tab
A104: =CUSTOM!A13 -> No Custom Feature | B104: =IF(C104>0,1,0) -> 0 | C104: =CUSTOM!G13 -> 0 | E104: Enter Cost on Custom Tab
A106: =CUSTOM!A15 -> No Custom Feature | B106: =IF(C106>0,1,0) -> 0 | C106: =CUSTOM!G15 -> 0 | E106: Enter Cost on Custom Tab
A108: =CUSTOM!A17 -> No Custom Feature | B108: =IF(C108>0,1,0) -> 0 | C108: =CUSTOM!G17 -> 0 | E108: Enter Cost on Custom Tab
A110: ROCKWORK
A112: Rockwork | B112: 0 | C112: Tons
A114: INTERIOR FINISH
A116: Ivory Quartz | B116: 1 | E116: =VLOOKUP(A116,INT!A6:R18,18,FALSE) -> Ivory / Blue / French Grey / Super Blue / Mariner Blue / Tropical Blue / Sky Blue
A118: Add'l Water Truck | B118: 0 | C118: ='COST - NEW'!E299 -> 580 | E118: 7,000 gallons INCLUDED in BASE. Enter (1) for 7,000 add'l gallons and (2) for 14,000 add'l gallons
A120: Premium Start-Up | B120: 0
A122: RETAIL PRICE: | C122: ='COST - REMODEL'!D337 -> 26694.061
C124: 0
C126: 0
C128: 0
A130: SALE PRICE: | B130: ='COST - REMODEL'!E344*10 -> 2.175 | C130: =SUM(C122:D129) -> 26694.061

Sheet COST - REMODEL
A2: PLANS & ENGINEERING
A3: =PLANS!A4 -> Pool Only: | B3: =PLANS!B4 -> 410 | C3: =PLANS!C4 -> 1 | D3: =PLANS!D4 -> 410
A4: =PLANS!A5 -> Spa: | B4: =PLANS!B5 -> 80 | C4: =PLANS!C5 -> 0 | D4: =PLANS!D5 -> 0
A5: =PLANS!A6 -> Waterfall: | B5: =PLANS!B6 -> 15 | C5: =PLANS!C6 -> 0 | D5: =PLANS!D6 -> 0
A6: =PLANS!A7 -> Waterfeature: | B6: =PLANS!B7 -> 10 | C6: =PLANS!C7 -> 0 | D6: =PLANS!D7 -> 0
A7: =PLANS!A8 -> Soil Sample / Engineer: | B7: =PLANS!B8 -> 750 | C7: =PLANS!C8 -> 1 | D7: =PLANS!D8 -> 750
A9: PLANS & ENGINEERING TOTAL | D9: 0
A11: LAYOUT
A12: Pool Only | B12: 50 | C12: 1 | D12: =B12*C12 -> 50
A13: Spa | B13: 15 | C13: =EXC!C27 -> 0 | D13: =B13*C13 -> 0
A14: Silt Fencing, Etc. | B14: 500 | C14: ='NEW POOL'!B5 -> 1 | D14: =B14*C14 -> 500
A16: LAYOUT TOTAL | D16: =SUM(D12:D15) -> 550
A18: PERMIT
A19: Pool Only: | B19: 850 | C19: 0 | D19: =B19*C19 -> 0
A20: Spa: | B20: 150 | C20: =EXC!C27 -> 0 | D20: =B20*C20 -> 0
A21: Permit Runner: | B21: 75 | C21: 0 | D21: =B21*C21 -> 0
A23: PERMIT TOTAL | D23: =SUM(D19:D22) -> 0
A25: DEMO
A26: =DEMO!A4 -> Cut | B26: =DEMO!B4 -> 2.8 | C26: =DEMO!C4*DEMO!D4 -> 0 | D26: =DEMO!E4 -> 0
A27: =DEMO!A5 -> Full Chip Out | B27: =DEMO!B5 -> 3.5 | C27: =DEMO!C5*DEMO!D5 -> 1122 | D27: =DEMO!E5 -> 3927
A28: =DEMO!A6 -> Remove Coping | B28: =DEMO!B6 -> 20 | C28: =DEMO!D6 -> 0 | D28: =DEMO!E6 -> 0
A29: =DEMO!A7 -> Remove Decking | B29: =DEMO!B7 -> 4 | C29: =DEMO!C7 -> 0 | D29: =DEMO!E7 -> 0
A30: Remove Joint / Install Caulking | B30: ='TILE COPING'!I24 -> 7.5 | C30: =(REMODEL!B7+REMODEL!B17)*REMODEL!B32 -> 0 | D30: =B30*C30 -> 0
A32: DEMO TOTAL | D32: =SUM(D26:D31) -> 3927
A34: EXCAVATION
A35: Base Excavation: | B35: =EXC!G5 -> 576 | D35: =EXC!D18 -> 2700
A36: Over 1,000 SQFT: | B36: =EXC!B17 -> 4 | C36: =EXC!C17 -> 0 | D36: =EXC!D17 -> 0
A37: =EXC!A20 -> Add'l 6" Depth: | B37: =EXC!B20 -> 90 | C37: =EXC!C20 -> 0 | D37: =EXC!D20 -> 0
A38: =EXC!A21 -> 6" RBB: | B38: =EXC!B21 -> 5 | C38: =EXC!C21 -> 0 | D38: =EXC!D21 -> 0
A39: =EXC!A22 -> 12" RBB: | B39: =EXC!B22 -> 6.5 | C39: =EXC!C22 -> 0 | D39: =EXC!D22 -> 0
A40: =EXC!A23 -> 18" RBB: | B40: =EXC!B23 -> 7.5 | C40: =EXC!C23 -> 0 | D40: =EXC!D23 -> 0
A41: =EXC!A24 -> 24" RBB: | B41: =EXC!B24 -> 8.5 | C41: =EXC!C24 -> 0 | D41: =EXC!D24 -> 0
A42: =EXC!A25 -> 30" RBB" | B42: =EXC!B25 -> 9 | C42: =EXC!C25 -> 0 | D42: =EXC!D25 -> 0
A43: =EXC!A26 -> 36" RBB: | B43: =EXC!B26 -> 10 | C43: =EXC!C26 -> 0 | D43: =EXC!D26 -> 0
A44: =EXC!A27 -> Base Spa: | B44: =EXC!B27 -> 200 | C44: =EXC!C27 -> 0 | D44: =EXC!D27 -> 0
A45: =EXC!A28 -> Raise Spa: | B45: =EXC!B28 -> 350 | C45: =EXC!C28 -> 0 | D45: =EXC!D28 -> 0
A46: =EXC!A29 -> Site Prep: | B46: =EXC!B29 -> 200 | C46: =EXC!C29 -> 0 | D46: =EXC!D29 -> 0
A47: =EXC!A30 -> Backfill: | B47: =EXC!B30 -> 600 | C47: =EXC!C30 -> 1 | D47: =EXC!D30 -> 600
A48: =EXC!A31 -> Gravel: | B48: =EXC!B31 -> 1 | C48: =EXC!C31 -> 2.75 | D48: =EXC!D31 -> 1584
A49: =EXC!A32 -> Dirt Haul: | B49: =EXC!B32 -> 18 | C49: =ROUNDUP(EXC!C32,0) -> 180 | D49: =ROUNDUP(EXC!D32,0) -> 3230
A50: =EXC!A33 -> Cover Box: | B50: =EXC!B33 -> 450 | C50: =EXC!C33 -> 0 | D50: =EXC!D33 -> 0
A51: =EXC!A34 -> Travel: | B51: =EXC!B34 -> 7 | C51: =EXC!C34 -> 0 | D51: =EXC!D34 -> 0
A52: =EXC!A35 -> Misc: | B52: =EXC!B35 -> 75 | C52: =EXC!C35 -> 1 | D52: =EXC!D35 -> 75 | E52: Discount
A53: Discount: | D53: 0 | E53: 0
A54: EXCAVATION TOTAL: | D54: 0
A56: PLUMBING
A57: =PLUM!A4 -> Short Stub | B57: =PLUM!B4 -> 550 | C57: =PLUM!C4 -> 1 | D57: =PLUM!D4 -> 550
A58: =PLUM!A5 -> Spa Base: | B58: =PLUM!B5 -> 750 | C58: =PLUM!C5 -> 0 | D58: =PLUM!D5 -> 0
A59: Pool Overun: | B59: =PLUM!B8 -> 25 | C59: =PLUM!C8 -> 27 | D59: =PLUM!D8 -> 675
A60: Spa Overun: | B60: =PLUM!B9 -> 22 | C60: =PLUM!C9 -> 0 | D60: =PLUM!D9 -> 0
A61: =PLUM!A10 -> 1/2" | B61: =PLUM!B10 -> 3.25 | C61: =PLUM!C10 -> 0 | D61: =PLUM!D10 -> 0
A62: =PLUM!A11 -> 3/4" | B62: =PLUM!B11 -> 3 | C62: =PLUM!C11 -> 0 | D62: =PLUM!D11 -> 0
A63: =PLUM!A12 -> 1" | B63: =PLUM!B12 -> 3.5 | C63: =PLUM!C12 -> 0 | D63: =PLUM!D12 -> 0
A64: =PLUM!A13 -> 1.5" | B64: =PLUM!B13 -> 4.5 | C64: =PLUM!C13 -> 0 | D64: =PLUM!D13 -> 0
A65: =PLUM!A14 -> 2.0" | B65: =PLUM!B14 -> 5.5 | C65: =PLUM!C14 -> 205 | D65: =PLUM!D14 -> 1127.5
A66: =PLUM!A15 -> 2.5" | B66: =PLUM!B15 -> 7 | C66: =PLUM!C15 -> 70 | D66: =PLUM!D15 -> 490
A67: =PLUM!A16 -> 3.0" | B67: =PLUM!B16 -> 8.75 | C67: =PLUM!C16 -> 0 | D67: =PLUM!D16 -> 0
A68: =PLUM!A22 -> Add'l Main Drain: | B68: =PLUM!B22 -> 275 | C68: =PLUM!C22 -> 0 | D68: =PLUM!D22 -> 0
A69: =PLUM!A23 -> Manifold: | B69: =PLUM!B23 -> 175 | C69: =PLUM!C23 -> 1 | D69: =PLUM!D23 -> 175
A70: =PLUM!A24 -> Heater Set: | B70: =PLUM!B24 -> 300 | C70: =PLUM!C24 -> 0 | D70: =PLUM!D24 -> 0
A71: =PLUM!A25 -> Infloor: | B71: =PLUM!B25 -> 10 | C71: =PLUM!C25 -> 0 | D71: =PLUM!D25 -> 0
A72: =PLUM!A26 -> Conduit: | B72: =PLUM!B26 -> 2.75 | C72: =PLUM!C26 -> 229 | D72: =PLUM!D26 -> 629.75
A73: =PLUM!A28 -> Travel: | B73: =PLUM!B28 -> 5 | C73: =PLUM!C28 -> 0 | D73: =PLUM!D28 -> 0
A75: PLUMBING TOTAL: | D75: 0
A77: GAS
A78: =PLUM!A33 -> Base Set: | B78: =PLUM!B33 -> 1500 | C78: =IF('NEW POOL'!B68>0,1,0) -> 0 | D78: =B78*C78 -> 0
A79: =PLUM!A34 -> Add'l Run | B79: =PLUM!B34 -> 11 | C79: =PLUM!C34 -> 0 | D79: =PLUM!D34 -> 0
A81: GAS TOTAL: | D81: =SUM(D78:D80) -> 0
A83: STEEL
A84: =STEEL!A4 -> Base: | B84: =STEEL!B4 -> 25 | C84: =STEEL!C4 -> 104 | D84: =STEEL!D4 -> 2600
A85: =STEEL!A5 -> 4-Bar Beam: | B85: =STEEL!B5 -> 100 | C85: =STEEL!C5 -> 1 | D85: =STEEL!D5 -> 100
A86: =STEEL!A6 -> 10" OC: | B86: =STEEL!B6 -> 0 | C86: =STEEL!C6 -> 104 | D86: =STEEL!D6 -> 0
A87: =STEEL!A7 -> Add'l 6" Depth: | B87: =STEEL!B7 -> 100 | C87: =STEEL!C7 -> 0 | D87: =STEEL!D7 -> 0
A88: =STEEL!A8 -> Spa: | B88: =STEEL!B8 -> 450 | C88: =STEEL!C8 -> 0 | D88: =STEEL!D8 -> 0
A89: Raise Spa: | B89: =STEEL!B9 -> 150 | C89: =STEEL!C9 -> 0 | D89: =STEEL!D9 -> 0
A90: =STEEL!A10 -> Bench: | B90: =STEEL!B10 -> 8 | C90: =STEEL!C10 -> 70 | D90: =STEEL!D10 -> 560
A91: =STEEL!A11 -> 6" RBB: | B91: =STEEL!B11 -> 3 | C91: =STEEL!C11 -> 0 | D91: =STEEL!D11 -> 0
A92: =STEEL!A12 -> 12" RBB: | B92: =STEEL!B12 -> 4 | C92: =STEEL!C12 -> 0 | D92: =STEEL!D12 -> 0
A93: =STEEL!A13 -> 18" RBB: | B93: =STEEL!B13 -> 5 | C93: =STEEL!C13 -> 0 | D93: =STEEL!D13 -> 0
A94: =STEEL!A14 -> 24" RBB: | B94: =STEEL!B14 -> 6 | C94: =STEEL!C14 -> 0 | D94: =STEEL!D14 -> 0
A95: =STEEL!A15 -> 30" RBB: | B95: =STEEL!B15 -> 7 | C95: =STEEL!C15 -> 0 | D95: =STEEL!D15 -> 0
A96: =STEEL!A16 -> 36" RBB: | B96: =STEEL!B16 -> 7 | C96: =STEEL!C16 -> 0 | D96: =STEEL!D16 -> 0
A97: =STEEL!A17 -> Pool Bonding: | B97: =STEEL!B17 -> 500 | C97: =STEEL!C17 -> 1 | D97: =STEEL!D17 -> 500
A98: =STEEL!A18 -> Bonding Lights: | B98: =STEEL!B18 -> 0 | C98: =STEEL!C18 -> 2 | D98: =STEEL!D18 -> 0
A99: =STEEL!A19 -> #4 in Floor: | B99: =STEEL!B19 -> 0 | C99: =STEEL!C19 -> 1 | D99: =STEEL!D19 -> 0
A100: =STEEL!A20 -> Depth over 8': | B100: =STEEL!B20 -> 80 | C100: =STEEL!C20 -> 0 | D100: =STEEL!D20 -> 0
A101: =STEEL!A21 -> Negative Edge: | B101: =STEEL!B21 -> 750 | C101: =STEEL!C21 -> 0 | D101: =STEEL!D21 -> 0
A102: =STEEL!A22 -> Tanning Shelf: | B102: =STEEL!B22 -> 275 | C102: =STEEL!C22 -> 0 | D102: =STEEL!D22 -> 0
A103: =STEEL!A24 -> Spa Double Curtain: | B103: =STEEL!B24 -> 75 | C103: =STEEL!C24 -> 0 | D103: =STEEL!D24 -> 0
A104: =STEEL!A25 -> Double Curtain: | B104: =STEEL!B25 -> 35 | C104: =STEEL!C25 -> 0 | D104: =STEEL!D25 -> 0
A105: =STEEL!A23 -> Muck Out: | B105: =STEEL!B23 -> 100 | C105: =STEEL!C23 -> 2 | D105: =STEEL!D23 -> 200
A106: =STEEL!A26 -> Travel: | B106: =STEEL!B26 -> 7 | C106: =STEEL!C26 -> 0 | D106: =STEEL!D26 -> 0
A108: STEEL TOTAL: | D108: 0
A110: ELECTRICAL
A111: =ELEC!A4 -> Base: | B111: =ELEC!B4 -> 1650 | C111: =ELEC!C4 -> 1 | D111: =ELEC!D4 -> 1650
A112: =ELEC!A5 -> Homerun: | B112: =ELEC!B5 -> 18 | C112: =ELEC!C5 -> 0 | D112: =ELEC!D5 -> 0
A113: =ELEC!A6 -> Lights: | B113: =ELEC!B6 -> 100 | C113: =ELEC!C6 -> 1 | D113: =ELEC!D6 -> 100
A114: =ELEC!A7 -> Heater: | B114: =ELEC!B7 -> 255 | C114: =ELEC!C7 -> 0 | D114: =ELEC!D7 -> 0
A115: =ELEC!A8 -> Heatpump: | B115: =ELEC!B8 -> 450 | C115: =ELEC!C8 -> 0 | D115: =ELEC!D8 -> 0
A116: =ELEC!A9 -> Add'l Heatpump: | B116: =ELEC!B9 -> 6 | C116: =ELEC!C9 -> 0 | D116: =ELEC!D9 -> 0
...

Sheet SUMMARY - REMODEL
A1: JOB COST SUMMARY
A3: CUSTOMER NAME: | B3: ='NEW POOL'!B3 -> Bishop
A5: PLANS & ENGINEERING TOTAL | D5: ='COST - REMODEL'!D9 -> 0
A7: LAYOUT TOTAL | D7: ='COST - REMODEL'!D16 -> 550
A9: PERMIT TOTAL | D9: ='COST - REMODEL'!D23 -> 0
A11: DEMO TOTAL | D11: ='COST - REMODEL'!D32 -> 3927
A13: EXCAVATION TOTAL: | D13: ='COST - REMODEL'!D54 -> 0
A15: PLUMBING TOTAL: | D15: ='COST - REMODEL'!D75 -> 0
A17: GAS TOTAL: | D17: ='COST - REMODEL'!D81 -> 0
A19: STEEL TOTAL: | D19: ='COST - REMODEL'!D108 -> 0
A21: ELECTRICAL TOTAL: | D21: ='COST - REMODEL'!D124 -> 0
A23: TILE LABOR TOTAL: | D23: ='COST - REMODEL'!D175 -> 1560
A25: TILE MATERIAL TOTAL: | D25: ='COST - REMODEL'!D177 -> 560
A27: COPING / DECKING LABOR TOTAL: | D27: ='COST - REMODEL'!D206 -> 0
A29: COPING / DECKING MATERIAL TOTAL: | D29: ='COST - REMODEL'!D208 -> 0
A31: STONE / ROCKWORK LABOR TOTAL: | D31: ='COST - REMODEL'!D227 -> 0
A33: STONE / ROCKWORK MATERIAL TOTAL: | D33: ='COST - REMODEL'!D229 -> 0
A35: DRAINAGE: | D35: ='COST - REMODEL'!D210 -> 0
A37: EQUIPMENT ORDERED TOTAL: | D37: ='COST - REMODEL'!D257 -> 1450.8344
A39: EQUIPMENT SET TOTAL: | D39: ='COST - REMODEL'!D266 -> 0
A41: CLEAN-UP TOTAL: | D41: ='COST - REMODEL'!D273 -> 350
A43: INTERIOR FINISH TOTAL: | D43: ='COST - REMODEL'!D286 -> 6271
A45: WATER TRUCK TOTAL: | D45: ='COST - REMODEL'!D292 -> 980
A47: START-UP / ORIENTATION TOTAL: | D47: ='COST - NEW'!D330 -> 1000
A49: =CUSTOM!A3 -> Parged Concrete | D49: ='COST - NEW'!D333 -> 0
A51: =CUSTOM!A5 -> Oversized coping | D51: ='COST - NEW'!D334 -> 824
A53: =CUSTOM!A7 -> handrail | D53: ='COST - NEW'!D335 -> 1028
A55: =CUSTOM!A9 -> No Custom Feature | D55: ='COST - NEW'!D336 -> 0
A57: =CUSTOM!A11 -> No Custom Feature | D57: ='COST - NEW'!D337 -> 0
A59: =CUSTOM!A13 -> No Custom Feature | D59: ='COST - NEW'!D338 -> 0
A61: =CUSTOM!A15 -> No Custom Feature | D61: ='COST - NEW'!D339 -> 0
A63: =CUSTOM!A17 -> No Custom Feature | D63: ='COST - NEW'!D340 -> 0
A65: TOTAL COST: | D65: =SUM(D5:D64) -> 18500.834

Sheet EQUIP
M1: MAY 2022 | P1: COST | Q1: RETAIL | R1: TAX
A2: 2020 SCP PRICING | H2: 0.08 | I2: 0.69 | N2: NP | O2: Remodel | P2: =P111*(1+R2) -> 8239 | Q2: =((S111*(1+R2))) -> 11684.4 | R2: 0.07
A3: UPDATED: | B3: 43922 | M3: Base White Goods: | N3: =SUM(N4:N10) -> 1046.1 | O3: =SUM(O4:O10) -> 216.6 | P3: See Bottom for Detail
M4: Skimmer | N4: 120 | O4: 0 | S4: Remodel Set: | T4: 250
M5: AutoFill | N5: 100 | O5: 0
M6: Layout Paint | N6: =10*1.06 -> 10.6 | O6: =10*1.06 -> 10.6
M7: Permit Box | N7: =25*1.06 -> 26.5 | O7: 0 | P7: Check Valve: | Q7: 65
M8: Valves | N8: =550*1.06 -> 583 | O8: 0
A9: Misc | M9: Gift Basket | N9: 100 | O9: 100
D10: 2015 | E10: 2017 | F10: 2018 | G10: 2019 | M10: Misc | N10: =100*1.06 -> 106 | O10: =100*1.06 -> 106
B11: Skimmer | C11: HAY-25-1559 | D11: 69.92 | E11: =D11*1.05 -> 73.416 | F11: =E11*1.05 -> 77.0868 | G11: =+F11*1.03 -> 79.399404 | H11: =G11*(1+$H$2) -> 85.751356 | I11: =H11/$I$2 -> 124.27733 | M11: Retail | N11: =N3/S13 -> 1494.4286 | O11: =O3/S13 -> 309.42857
M13: PUMPS | O13: Main Drain | P13: Valve | Q13: Remodel | R13: Rem Retail | S13: 0.7
M14: No Auxiliary Pump | N14: 0 | O14: 0 | Q14: =SUM(N14:P14) -> 0 | R14: 0 | S14: =SUM(N14:Q14) -> 0 | U14: No Auxiliary Pump Selected
M15: Jandy 1.65HP Variable Pump | N15: 1153.6 | O15: 290 | P15: 90 | Q15: =SUM(N15:P15)*1.1 -> 1686.96 | R15: =((N15+P15)/$S$13)*1.2 -> 2131.8857 | S15: =CEILING(Q15/$S$13,10)-100 -> 2310 | T15: =S15-S16 -> -230
M16: Jandy 1.85HP Variable Pump | N16: 1236 | O16: 290 | P16: =P15 -> 90 | Q16: =SUM(N16:P16)*1.1 -> 1777.6 | R16: =((N16+P16)/$S$13)*1.2 -> 2273.1429 | S16: =CEILING(Q16/$S$13,10) -> 2540 | T16: INCLUDED
M17: Jandy 2.7HP Variable Pump | N17: 1596.5 | O17: 290 | P17: =P16 -> 90 | Q17: =SUM(N17:P17)*1.1 -> 2174.15 | R17: =((N17+P17)/$S$13)*1.2 -> 2891.1429 | S17: =CEILING(Q17/$S$13,10) -> 3110 | T17: =S17-S16 -> 570
B18: Paramount Venturi Skimmer | D18: 90 | E18: =D18*1.05 -> 94.5 | F18: 125 | G18: =+F18*1.03 -> 128.75 | H18: =G18*(1+$H$2) -> 139.05 | I18: =H18/$I$2 -> 201.52174 | M18: Jandy 1.0HP Single Speed Pump | N18: 824 | O18: =O17 -> 290 | P18: =P16 -> 90 | Q18: =SUM(N18:P18)*1.1 -> 1324.4 | R18: =((N18+P18)/$S$13)*1.2 -> 1566.8571 | S18: =CEILING(Q18/$S$13,10) -> 1900
M19: Jandy 2.0HP Single Speed Pump | N19: 927 | O19: =O18 -> 290 | P19: =P16 -> 90 | Q19: =SUM(N19:P19)*1.1 -> 1437.7 | R19: =((N19+P19)/$S$13)*1.2 -> 1743.4286 | S19: =CEILING(Q19/$S$13,10) -> 2060
B21: Vac Lock for Vac Line | C21: HAY-20-518 | D21: 20.13 | E21: =D21*1.05 -> 21.1365 | F21: =E21*1.04 -> 21.98196 | G21: =+F21*1.03 -> 22.641419 | H21: =G21*(1+$H$2) -> 24.452732 | I21: =H21/$I$2 -> 35.438742 | M21: FILTERS | O21: NP Upgrade | P21: Valve Remodel | Q21: Rem Cost | R21: Rem Retail | S21: 0.7
M22: No Filter | N22: 0 | O22: 0 | Q22: 0 | S22: =N22/$S$21 -> 0
M23: 200 SQFT Cartridge Filter | N23: 772.5 | O23: =S23-S24 -> -515 | P23: =P15 -> 90 | Q23: =((N23+P23))*1.1 -> 948.75 | R23: =Q23/$S$21 -> 1355.3571 | S23: =N23/$S$21 -> 1103.5714
B24: Polaris 360 - Standard | C24: POL-20-520 | D24: 439.87 | E24: =D24*1.05 -> 461.8635 | F24: =E24*1.04 -> 480.33804 | G24: =+F24*1.03 -> 494.74818 | H24: =G24*(1+$H$2) -> 534.32804 | I24: =H24/$I$2 -> 774.38846 | M24: 340 SQFT Cartridge Filter | N24: 1133 | O24: INCLUDED | P24: =P23 -> 90 | Q24: =((N24+P24))*1.1 -> 1345.3 | R24: =Q24/$S$21 -> 1921.8571 | S24: =N24/$S$21 -> 1618.5714 | U24: http://www.jandy.com/en/products/filters/cv
B25: Polaris 360 - Black | C25: POL-20-531 | D25: 535.8 | E25: =D25*1.05 -> 562.59 | F25: =E25*1.04 -> 585.0936 | G25: =+F25*1.03 -> 602.64641 | H25: =G25*(1+$H$2) -> 650.85812 | I25: =H25/$I$2 -> 943.27264 | M25: 460 SQFT Cartridge Filter | N25: 1174.2 | O25: =CEILING((N25-$N$24)*1.7,20) -> 80 | P25: =P24 -> 90 | Q25: =((N25+P25))*1.1 -> 1390.62 | R25: =Q25/$S$21 -> 1986.6 | S25: =N25/$S$21 -> 1677.4286 | U25: http://www.jandy.com/en/products/filters/cv
B26: Polaris 280 w/ Booster | E26: =547.7+251.35 -> 799.05 | F26: =580+250 -> 830 | G26: =+F26*1.03 -> 854.9 | H26: =G26*(1+$H$2) -> 923.292 | I26: =H26/$I$2 -> 1338.1043 | M26: 580 SQFT Cartridge Filter | N26: 1493.5 | O26: =CEILING((N26-$N$24)*1.7,20) -> 620 | P26: =P25 -> 90 | Q26: =((N26+P26))*1.1 -> 1741.85 | R26: =Q26/$S$21 -> 2488.3571 | S26: =N26/$S$21 -> 2133.5714 | U26: http://www.jandy.com/en/products/filters/cv
B27: Pool rx | D27: 69.41 | E27: =D27*1.05 -> 72.8805 | F27: =E27*1.04 -> 75.79572 | G27: =+F27*1.03 -> 78.069592 | H27: =G27*(1+$H$2) -> 84.315159 | I27: =H27/$I$2 -> 122.19588 | M27: 4.9 SQFT Sand Filter | N27: 780.64 | O27: INCLUDED | P27: =P26 -> 90 | Q27: =((N27+P27))*1.1 -> 957.704 | R27: =Q27/$S$21 -> 1368.1486 | S27: =N27/$S$21 -> 1115.2 | U27: http://www.jandy.com/en/products/filters/js
B28: Vac Breaker | C28: WRD-56-4204 | D28: 55 | E28: =D28*1.05 -> 57.75 | F28: =E28*1.04 -> 60.06 | G28: =+F28*1.03 -> 61.8618 | H28: =G28*(1+$H$2) -> 66.810744 | I28: =H28/$I$2 -> 96.827165 | M28: 60 SQFT DE Filter | N28: 857.06 | O28: INCLUDED | P28: =P27 -> 90 | Q28: =((N28+P28))*1.1 -> 1041.766 | R28: =Q28/$S$21 -> 1488.2371 | S28: =N28/$S$21 -> 1224.3714 | U28: http://www.jandy.com/en/products/filters/dev
B29: Chlorine Floater | C29: RAI-45-804 | D29: 7.63 | E29: =D29*1.05 -> 8.0115 | F29: =E29*1.04 -> 8.33196 | G29: =+F29*1.03 -> 8.5819188 | H29: =G29*(1+$H$2) -> 9.2684723 | I29: =H29/$I$2 -> 13.432569
B30: In-Line Chlorinator | C30: RAI-45-806 | D30: 58.27 | E30: =D30*1.05 -> 61.1835 | F30: 72.59 | G30: =+F30*1.03 -> 74.7677 | H30: =G30*(1+$H$2) -> 80.749116 | I30: =H30/$I$2 -> 117.0277 | M30: CLEANERS | S30: =S13 -> 0.7
B31: Nature 2 Fusion Cartridge | C31: FOU-45-133 | D31: 84.24 | E31: =D31*1.05 -> 88.452 | F31: =E31*1.04 -> 91.99008 | G31: =+F31*1.03 -> 94.749782 | H31: =G31*(1+$H$2) -> 102.32976 | I31: =H31/$I$2 -> 148.30401 | M31: No Cleaner | N31: 0
B32: 2.0 HP Blower | C32: POL-85-8013 | D32: 171.72 | E32: =D32*1.05 -> 180.306 | F32: =E32*1.04 -> 187.51824 | G32: =+F32*1.03 -> 193.14379 | H32: =G32*(1+$H$2) -> 208.59529 | I32: =H32/$I$2 -> 302.31201 | M32: Polaris Epic IQ | N32: 1077.25 | S32: =CEILING(N32/$S$30,10) -> 1540
B33: TR36P | E33: 445 | F33: 460 | G33: =+F33*1.03 -> 473.8 | H33: =G33*(1+$H$2) -> 511.704 | I33: =H33/$I$2 -> 741.6 | M33: Polaris Alpha IQ | N33: 1397.13 | S33: =CEILING(N33/$S$30,10) -> 2000
B34: Polaris 9650 | E34: 1257 | F34: 1426.5 | G34: =+F34*1.03 -> 1469.295 | H34: =G34*(1+$H$2) -> 1586.8386 | I34: =H34/$I$2 -> 2299.7661
A35: Pumps | G35: =+F35*1.03 -> 0 | H35: =G35*(1+$H$2) -> 0 | M35: HEATERS | Q35: Rem Cost | R35: Rem Retail | S35: =S30 -> 0.7
G36: =+F36*1.03 -> 0 | H36: =G36*(1+$H$2) -> 0 | M36: No Heater | S36: 0
A37: TLD-10-2006 | B37: SHPF1.5-2 STEALTH | C37: PUMP 1.5HP 2SP HH FR 230V | D37: 645.05 | E37: =D37*1.082 -> 697.9441 | F37: 715 | G37: =+F37*1.03 -> 736.45 | H37: =G37*(1+$H$2) -> 795.366 | I37: =H37/$I$2 -> 1152.7043 | J37: =F37-#REF! -> #REF! | M37: Jandy JTR 3000 Heater/Chiller | N37: 5175.75 | P37: =ELEC!D7+ELEC!D8 -> 0 | Q37: =N37*1.05 -> 5434.5375 | R37: =Q37/S35 -> 7763.625 | S37: =N37/S35 -> 7393.9286
M38: Jandy 400K BTU - VersaFlo | N38: 3297 | P38: =ELEC!D8+ELEC!D9 -> 0 | Q38: =N38*1.05 -> 3461.85 | R38: =Q38/S35 -> 4945.5 | S38: =N38/S35 -> 4710
N39: 0 | Q39: =N39*1.1 -> 0 | R39: =Q39/S35 -> 0 | S39: =CEILING(N39/S35,5) -> 0 | U39: =IF('NEW POOL'!E121="",0,1) -> 0
A40: TLS-10-2000 | B40: SHPF.75 STEALTH | C40: PUMP 3/4HP 115/230V | D40: 479.06 | E40: =D40*1.082 -> 518.34292 | F40: 525 | G40: =+F40*1.03 -> 540.75 | H40: =G40*(1+$H$2) -> 584.01 | I40: =H40/$I$2 -> 846.3913 | J40: =F40-#REF! -> #REF!
M41: LIGHTS | P41: Remodel Install | R41: Remodel | S41: =S30 -> 0.7
A42: TLD-10-2001 | B42: SHPF1.0 STEALTH | C42: PUMP 1HP HH FR 208-230/115V | D42: 517.36 | E42: =D42*1.082 -> 559.78352 | F42: 570 | G42: =+F42*1.03 -> 587.1 | H42: =G42*(1+$H$2) -> 634.068 | I42: =H42/$I$2 -> 918.93913 | J42: =F42-#REF! -> #REF! | M42: No Additional Lights | R42: 0
A43: TLD-10-2002 | B43: SHPF1.5 STEALTH | C43: PUMP 1.5HP HH FR 208-230/115V | D43: 566.19 | E43: =D43*1.082 -> 612.61758 | F43: 625 | G43: =+F43*1.03 -> 643.75 | H43: =G43*(1+$H$2) -> 695.25 | I43: =H43/$I$2 -> 1007.6087 | J43: =F43-#REF! -> #REF! | M43: 6 Watt - Jandy Nicheless LED Spa light | N43: 528 | P43: 95 | R43: =((N43+P43)/$S$41)*1.05 -> 934.5 | S43: =CEILING(N43/$S$41,5) -> 755
A44: TLD-10-2003 | B44: SHPF2.0 STEALTH | C44: PUMP 2HP HH FR 208-230V | D44: 666.14 | E44: =D44*1.082 -> 720.76348 | F44: 735 | G44: =+F44*1.03 -> 757.05 | H44: =G44*(1+$H$2) -> 817.614 | I44: =H44/$I$2 -> 1184.9478 | J44: =F44-#REF! -> #REF! | M44: Infinite Water Color | N44: 715 | P44: 95 | R44: =((N44+P44)/$S$41)*1.05 -> 1215 | S44: =CEILING(N44/$S$41,5) -> 1025
A45: TLD-10-2004 | B45: SHPF3.0 STEALTH | C45: PUMP 3HP HH FR 208-230V | D45: 786 | E45: =D45*1.082 -> 850.452 | F45: 870 | G45: =+F45*1.03 -> 896.1 | H45: =G45*(1+$H$2) -> 967.788 | I45: =H45/$I$2 -> 1402.5913 | M45: 24 Watt - Jandy Nicheless LED | N45: 601 | P45: =P43 -> 95 | R45: =((N45+P45)/$S$41)*1.05 -> 1044 | S45: =CEILING(N45/$S$41,5) -> 860
M46: Transformer | N46: =110*1.06 -> 116.6 | S46: =N46/S41 -> 166.57143
B47: No Auxilary Pump | H47: 0
A48: TLD-10-2024 | B48: Jandy PlusHP Variable Speed | E48: 597 | F48: 600 | G48: =+F48*1.03 -> 618 | H48: 1270 | I48: =H48/$I$2 -> 1840.5797 | M48: SANITATION | P48: Remodel Install | Q48: Remodel Cost | R48: Remod Retail | S48: =S41 -> 0.7
A49: TLD-10-2050 | B49: Jandy WFTR80 | C49: PUMP 80GPM MH UR 230/115V WATER FEATURE | D49: 383 | E49: =D49*1.082 -> 414.406 | F49: 415 | G49: =+F49*1.03 -> 427.45 | H49: 530 | I49: =H49/$I$2 -> 768.11594 | J49: =H49-#REF! -> #REF! | M49: No Sanitation | N49: 0 | R49: =((N49+P49)/$S$48)*1.05 -> 0 | S49: =CEILING(N49/$S$41,5) -> 0
A50: TLD-10-2051 | B50: Jandy WFTR120 | C50: PUMP 120GPM MH UR 230/115V WATER FEATURE | D50: 458 | E50: =D50*1.082 -> 495.556 | F50: 505 | G50: =+F50*1.03 -> 520.15 | H50: 640 | I50: =H50/$I$2 -> 927.53623 | J50: =H50-#REF! -> #REF! | M50: Chlorine Floater | N50: =12*1.06 -> 12.72 | P50: 0 | Q50: =N50 -> 12.72 | R50: =((N50+P50)/$S$48)*1.05 -> 19.08 | S50: =CEILING(N50/$S$41,5) -> 20
B51: SWF 125 | D51: 460 | E51: =D51*1.082 -> 497.72 | F51: 510 | G51: =+F51*1.03 -> 525.3 | H51: =G51*(1+$H$2) -> 567.324 | I51: =H51/$I$2 -> 822.2087 | J51: =H51-#REF! -> #REF! | M51: In-Line Chlorine Feeder | N51: 200 | P51: 65 | Q51: =N51+P51 -> 265 | R51: =((N51+P51)/$S$48)*1.05 -> 397.5 | S51: =CEILING(N51/$S$41,5) -> 290
A52: TLD-10-2126 | B52: PlusHP | C52: Variable Speed | E52: 955 | F52: 1013.16 | G52: =F52*1.05 -> 1063.818 | H52: =G52*(1+$H$2) -> 1148.9234 | I52: =H52/$I$2 -> 1665.1064 | M52: Mineral Sanitizer | N52: 100 | P52: =P51 -> 65 | Q52: =N52+P52 -> 165 | R52: =((N52+P52)/$S$48)*1.05 -> 247.5 | S52: =CEILING(N52/$S$41,5) -> 145
M53: Chlorinator / Mineral Jandy Fusion Inground | N53: =300*1.06 -> 318 | P53: =P52 -> 65 | Q53: =N53+P53 -> 383 | R53: =((N53+P53)/$S$48)*1.05 -> 574.5 | S53: =CEILING(N53/$S$41,5) -> 455
A54: TLD-10-2070 | B54: JEP1.5 | C54: 1.5 HP Variable Speed Pump | D54: 929.97 | E54: 985 | F54: 1050 | G54: =+F54*1.03 -> 1081.5 | H54: =G54*(1+$H$2) -> 1168.02 | I54: =H54/$I$2 -> 1692.7826 | M54: Ozone25 System with Degas Vessel | N54: 1100 | O54: =PLUM!B41 -> 200 | P54: 95 | Q54: =N54+P54 -> 1195 | R54: =((N54+P54)/$S$48)*1.05 -> 1792.5 | S54: =CEILING((N54+O54)/$S$41,5) -> 1860
M55: Del Ozone with UV AOP unit with Degas | N55: 2000 | O55: =PLUM!B42 -> 210 | P55: 110 | Q55: =N55+P55 -> 2110 | R55: =((N55+P55)/$S$48)*1.05 -> 3165 | S55: =CEILING((N55+O55)/$S$41,5) -> 3160
M56: Salt System - Jandy Tru-Clear | N56: 1150 | P56: =P55 -> 110 | Q56: =N56+P56 -> 1260 | R56: =((N56+P56)/$S$48)*1.05 -> 1890 | S56: =CEILING(N56/$S$41,5) -> 1645
A57: TLD-10-2071 | B57: JEP2.0 | C57: 2.0 HP Variable Speed Pump | D57: 950.78 | E57: 1110 | F57: 1210 | G57: 1120 | H57: =G57*(1+$H$2) -> 1209.6 | I57: =H57/$I$2 -> 1753.0435 | M57: Salt/mineral System - Fusion Soft | N57: 1000 | P57: =P56 -> 110 | Q57: =N57+P57 -> 1110 | R57: =((N57+P57)/$S$48)*1.05 -> 1665 | S57: =CEILING(N57/$S$41,5) -> 1430
M58: Salt/Automation Credit | N58: =300*1.06 -> 318 | S58: =CEILING(-N58/$S$41,5) -> -450
A59: TLD-10-2084 | B59: VS-FHP1.0 | C59: Flo-Pro Variable Speed Pump | D59: 965.16 | E59: 765 | F59: 780 | G59: =+F59*1.03 -> 803.4 | H59: =G59*(1+$H$2) -> 867.672 | I59: =H59/$I$2 -> 1257.4957
G60: =+F60*1.03 -> 0 | H60: =G60*(1+$H$2) -> 0 | M60: AUTOMATION | P60: Install | S60: 0.75
A61: Filters | G61: =+F61*1.03 -> 0 | H61: =G61*(1+$H$2) -> 0 | M61: 6614 APL BASE PANEL | N61: 1600
M62: Additional JVA | N62: 200 | P62: 75 | R62: =SUM(N62:Q62)/S60 -> 366.66667 | S62: =CEILING((R62),5) -> 370
A63: TLD-05-105 | B63: CS100 CS Series | C63: 150 SF Cartridge Filter | D63: 255 | E63: 360 | F63: 370 | G63: =+F63*1.03 -> 381.1 | H63: 520 | I63: =H63/$I$2 -> 753.62319 | M63: No Automation | N63: 0 | O63: 0
M64: Jandy TCX Controler (1 JVA, Lights and Heater Control) | N64: 650 | P64: 35 | R64: =SUM(N64:Q64)/S60 -> 913.33333 | S64: =R64/$S$60 -> 1217.7778 | U64: 1 JVA, Heat, Pump, Lights NO INFINITE WATER COLOR
A65: TLD-05-108 | B65: CS250 CS Series | C65: 250 SF Cartridge Filter | D65: 486.06 | E65: 525 | F65: 550 | G65: =+F65*1.03 -> 566.5 | H65: 650 | I65: =H65/$I$2 -> 942.02899 | M65: iAqualink Only P-4 (H.O. To Provide WiFi) | N65: 650 | O65: 325 | P65: 0 | R65: =($N$61+N65+O65+P65+Q65) -> 2575 | S65: =R65/$S$60 -> 3433.3333 | U65: Zodiac iAqualink P-4 (No Handheld)
A66: TLD-05-114 | B66: CL340 CL SERIES | C66: FILTER CARTRIDGE 340 SQFT | D66: 663.51 | E66: 700 | F66: 735 | G66: =+F66*1.03 -> 757.05 | H66: 755 | I66: =H66/$I$2 -> 1094.2029 | M66: iAqualink Only PS-4 (H.O. To Provide WiFi) Only use with Infinite Light System | N66: 1100 | O66: 325 | P66: =P65 -> 0 | R66: =($N$61+N66+O66+P66+Q66) -> 3025 | S66: =R66/$S$60 -> 4033.3333 | U66: Zodiac iAqualink P-8 (No Handheld)
A67: TLD-05-115 | B67: CL460 CL SERIES | C67: FILTER CARTRIDGE 460 SQFT | D67: 744.21 | E67: 790 | F67: 830 | G67: =+F67*1.03 -> 854.9 | H67: 850 | I67: =H67/$I$2 -> 1231.8841 | M67: iAqualink Only PS-6 (H.O. To Provide WiFi) | N67: 1797 | O67: 325 | P67: =P66 -> 0 | R67: =($N$61+N67+O67+P67+Q67) -> 3722 | S67: =R67/$S$60 -> 4962.6667 | U67: Zodiac iAqualink PS-6 (No Handheld)
A68: TLD-05-113 | B68: CL580 CL SERIES | C68: FILTER CARTRIDGE 580 SQFT | D68: 919.06 | E68: 980 | F68: 1025 | G68: =+F68*1.03 -> 1055.75 | H68: 1200 | I68: =H68/$I$2 -> 1739.1304 | M68: iAqualink Only PS-8 (H.O. To Provide WiFi) | N68: 2600 | O68: 325 | P68: =P67 -> 0 | R68: =($N$61+N68+O68+P68+Q68) -> 4525 | S68: =R68/$S$60 -> 6033.3333 | U68: Zodiac iAqualink PS-8 (No Handheld)
G69: =+F69*1.03 -> 0 | H69: =G69*(1+$H$2) -> 0 | M69: IQ Pump 01 | N69: 121 | P69: 35 | R69: =SUM(N69:Q69)/S60 -> 208 | S69: =R69/$S$60 -> 277.33333
A70: JDY-27-1700 | B70: 1201C | C70: WATERFALL 1' BACK FEED EXT LIP | D70: 219 | E70: 138.2 | F70: 140 | G70: =+F70*1.03 -> 144.2 | H70: 160 | I70: =H70/$I$2 -> 231.88406 | N70: 0 | O70: 325 | P70: =P69 -> 35 | R70: =($N$61+N70+O70+P70+Q70) -> 1960 | S70: =R70/$S$60 -> 2613.3333
A71: JDY-27-1708 | B71: 12018C | C71: WATERFALL 18" BACK FEED EXT LIP | D71: 254 | E71: 149.25 | F71: 155 | G71: =+F71*1.03 -> 159.65 | H71: 165 | I71: =H71/$I$2 -> 239.13043 | N71: 0 | O71: 325 | P71: =P70 -> 35 | R71: =($N$61+N71+O71+P71+Q71) -> 1960 | S71: =R71/$S$60 -> 2613.3333
A72: JDY-27-1701 | B72: 1202C | C72: WATERFALL 2' BACK FEED EXT LIP | D72: 272 | E72: 156.72 | F72: 160 | G72: =+F72*1.03 -> 164.8 | H72: 170 | I72: =H72/$I$2 -> 246.37681 | N72: 0 | O72: 325 | P72: =P71 -> 35 | R72: =($N$61+N72+O72+P72+Q72) -> 1960 | S72: =R72/$S$60 -> 2613.3333
A73: JDY-27-1702 | B73: 1203C | C73: WATERFALL 3' BACK FEED EXT LIP | D73: 346 | E73: 209.28 | F73: 215 | G73: =+F73*1.03 -> 221.45 | H73: 250 | I73: =H73/$I$2 -> 362.31884
A74: JDY-27-1703 | B74: 1204C | C74: WATERFALL 4' BACK FEED EXT LIP | D74: 433 | E74: 296.12 | F74: 305 | G74: =+F74*1.03 -> 314.15 | H74: 340 | I74: =H74/$I$2 -> 492.75362
A75: JDY-27-1704 | B75: 1205C | C75: WATERFALL 5' BACK FEED EXT LIP | D75: 533 | E75: 392.18 | F75: 405 | G75: =+F75*1.03 -> 417.15 | H75: 580 | I75: =H75/$I$2 -> 840.57971 | M75: WATER FEATURES | N75: Sheer | O75: Valve | P75: Install | S75: 0.7
G76: =+F76*1.03 -> 0 | H76: =G76*(1+$H$2) -> 0 | M76: No Sheer Descent | N76: 0 | O76: 0 | P76: 0 | R76: =SUM(N76:Q76) -> 0 | S76: 0 | U76: No Sheer Descent
A77: Heaters | G77: =+F77*1.03 -> 0 | H77: =G77*(1+$H$2) -> 0 | M77: 12" Sheer Descent | N77: 185 | O77: 85 | P77: 250 | R77: =SUM(N77:Q77) -> 520 | S77: =CEILING(R77/$S$75,20) -> 760 | U77: Cascading Water Feature
G78: =+F78*1.03 -> 0 | H78: =G78*(1+$H$2) -> 0 | M78: 18" Sheer Descent | N78: 200 | O78: =O77 -> 85 | P78: =P77 -> 250 | R78: =SUM(N78:Q78) -> 535 | S78: =CEILING(R78/$S$75,20) -> 780 | U78: Cascading Water Feature
B79: LXI250N | C79: HEATER 250BTU LX NG LN | D79: 1673.46 | E79: =D79*1.082 -> 1810.6837 | F79: 1885 | G79: =+F79*1.03 -> 1941.55 | H79: =G79*(1+$H$2) -> 2096.874 | I79: =H79/$I$2 -> 3038.9478 | M79: 2' Sheer Descent | N79: 233 | O79: =O78 -> 85 | P79: =P78 -> 250 | R79: =SUM(N79:Q79) -> 568 | S79: =CEILING(R79/$S$75,20) -> 820 | U79: Cascading Water Feature
C80: 400K JXI N/G HEATER - NO BYPASS | D80: 2051.12 | E80: =D80*1.082 -> 2219.3118 | F80: =E80*1.04 -> 2308.0843 | G80: =+F80*1.03 -> 2377.3268 | H80: =G80*(1+$H$2) -> 2567.513 | I80: =H80/$I$2 -> 3721.0333 | M80: 3' Sheer Descent | N80: 272 | O80: =O79 -> 85 | P80: =P79 -> 250 | R80: =SUM(N80:Q80) -> 607 | S80: =CEILING(R80/$S$75,20) -> 880 | U80: Cascading Water Feature
C81: 400K JXI N/G HEATER - WITH BYPASS | D81: 2051.12 | E81: =E80+155 -> 2374.3118 | F81: 2475 | G81: 2475 | H81: 2360 | I81: =H81/$I$2 -> 3420.2899 | M81: 4' Sheer Descent | N81: 355 | O81: =O80 -> 85 | P81: =P80 -> 250 | R81: =SUM(N81:Q81) -> 690 | S81: =CEILING(R81/$S$75,20) -> 1000 | U81: Cascading Water Feature
M82: 5' Sheer Descent Requires 2nd Pump) | N82: 442 | O82: =O81 -> 85 | P82: =P81 -> 250 | R82: =SUM(N82:Q82) -> 777 | S82: =CEILING(R82/$S$75,20) -> 1120 | U82: Cascading Water Feature
A83: Cleaners | M83: 6' Sheer Descent( Requires 2nd Pump) | N83: 570 | O83: =O82 -> 85 | P83: =P82 -> 250 | R83: =SUM(N83:Q83) -> 905 | S83: =CEILING(R83/$S$75,20) -> 1300 | U83: Cascading Water Feature
C84: MX6 Suction Cleaner | H84: 550 | M84: No Deck Jet or Laminar Jet | N84: 0
C85: Polaris 9650 Robotic Cleaner | G85: =+F85*1.03 -> 0 | H85: 1586 | M85: Deck Jet | N85: 150 | O85: =O83 -> 85 | P85: 50 | Q85: 0 | R85: =SUM(N85:Q85) -> 285 | S85: =CEILING(R85/$S$75,20) -> 420
C86: Premier Clean In-Floor System | G86: =+F86*1.03 -> 0 | H86: 1950 | M86: Laminar Jet | N86: 1050 | O86: =O85 -> 85 | P86: 75 | Q86: =$N$102 -> 15 | R86: =SUM(N86:Q86) -> 1225 | S86: =CEILING(R86/$S$75,20) -> 1760
A87: Salt Systems | G87: =+F87*1.03 -> 0 | H87: =G87*(1+$H$2) -> 0 | M87: No Wok Pot
G88: =+F88*1.03 -> 0 | H88: =G88*(1+$H$2) -> 0 | M88: 30" Precast Wok - Water Only | N88: 983 | O88: =O86 -> 85 | P88: =P83 -> 250 | Q88: =$N$102 -> 15 | R88: =SUM(N88:Q88) -> 1333 | S88: =CEILING(R88/$S$75,20) -> 1920
A89: JDY-45-1400 | B89: APURE1400 AQUAPURE | C89: CHLORINE GENERATOR 14 BLADE | D89: 533.56 | E89: =D89*1.05 -> 560.238 | F89: =E89*1.08 -> 605.05704 | G89: =+F89*1.03 -> 623.20875 | H89: =G89*(1+$H$2) -> 673.06545 | I89: =H89/$I$2 -> 975.45718 | M89: 32" Precast Wok - Water Only | N89: 1083 | O89: =O88 -> 85 | P89: =P88 -> 250 | Q89: =$N$102 -> 15 | R89: =SUM(N89:Q89) -> 1433 | S89: =CEILING(R89/$S$75,20) -> 2060
A90: JDY-45-1500 | B90: APUREM POWER PACK | C90: POWER PACK FOR AQUAPURE | D90: 533.56 | E90: =D90*1.05 -> 560.238 | F90: =E90*1.08 -> 605.05704 | G90: =+F90*1.03 -> 623.20875 | H90: =G90*(1+$H$2) -> 673.06545 | I90: =H90/$I$2 -> 975.45718 | M90: 36" Precast Wok - Water Only | N90: 1228 | O90: =O89 -> 85 | P90: =P89 -> 250 | Q90: =$N$102 -> 15 | R90: =SUM(N90:Q90) -> 1578 | S90: =CEILING(R90/$S$75,20) -> 2260 | U90: Add $500 for Copper
A91: JDY-45-0705 | B91: PLC700 PURELINK | C91: CELL KIT 7 BLADE | D91: 393 | E91: =D91*1.05 -> 412.65 | F91: =E91*1.08 -> 445.662 | G91: =+F91*1.03 -> 459.03186 | H91: =G91*(1+$H$2) -> 495.75441 | I91: =H91/$I$2 -> 718.48465 | M91: 30" Precast Wok - Fire & Water | N91: 3190 | O91: =O90 -> 85 | P91: =P90 -> 250 | Q91: =$N$102 -> 15 | R91: =SUM(N91:Q91) -> 3540 | S91: =CEILING(R91/$S$75,20) -> 5060 | U91: Match throw add additional $588, auto add $2134, Add $500 for Copper
A92: JDY-45-1405 | B92: PLC1400 PURELINK | C92: CELL KIT 14 BLADE | D92: 591.21 | E92: =D92*1.05 -> 620.7705 | F92: =E92*1.08 -> 670.43214 | G92: =+F92*1.03 -> 690.5451 | H92: =G92*(1+$H$2) -> 745.78871 | I92: =H92/$I$2 -> 1080.8532 | M92: 36" Precast Wok - Fire & Water | N92: 3862 | O92: =O91 -> 85 | P92: =P91 -> 250 | Q92: =$N$102 -> 15 | R92: =SUM(N92:Q92) -> 4212 | S92: =CEILING(R92/$S$75,20) -> 6020 | U92: Match throw add additional $588, auto add $2134, Add $500 for Copper
A93: CLW-45-1033 | B93: NATURE 2 FUSION SOFT 700 | C93: UP TO 25K GALLONS | D93: 402.14 | E93: =D93*1.05 -> 422.247 | F93: =E93*1.08 -> 456.02676 | G93: =+F93*1.03 -> 469.70756 | H93: =G93*(1+$H$2) -> 507.28417 | I93: =H93/$I$2 -> 735.19445 | N93: 0 | O93: =O92 -> 85 | P93: =P92 -> 250 | Q93: =$N$102 -> 15 | R93: =SUM(N93:Q93) -> 350 | S93: =CEILING(R93/$S$75,20) -> 500 | U93: Match throw add additional $588, auto add $2134, Add $500 for Copper
A94: CLW-45-1034 | B94: NATURE 2 FUSION SOFT 1400 | C94: UP TO 40K GALLONS | D94: 521.25 | E94: =D94*1.05 -> 547.3125 | F94: =E94*1.08 -> 591.0975 | G94: =+F94*1.03 -> 608.83043 | H94: 410 | I94: =H94/$I$2 -> 594.2029 | M94: 30" Precast Wok - Fire Only | N94: 875 | O94: =O93 -> 85 | P94: =P93 -> 250 | Q94: =$N$102 -> 15 | R94: =SUM(N94:Q94) -> 1225 | S94: =CEILING(R94/$S$75,20) -> 1760 | U94: Match throw add additional $588, auto add $2134, Add $500 for Copper
A95: CLW-451-1050 | B95: FUSION M POWER PACK | C95: IF NO AUTOMATION | D95: 549.08 | E95: =D95*1.05 -> 576.534 | F95: =E95*1.08 -> 622.65672 | G95: =+F95*1.03 -> 641.33642 | H95: =G95*(1+$H$2) -> 692.64334 | I95: =H95/$I$2 -> 1003.8309 | M95: 36" Precast Wok - Fire Only | N95: 1110 | O95: =O94 -> 85 | P95: =P94 -> 250 | Q95: =$N$102 -> 15 | R95: =SUM(N95:Q95) -> 1460 | S95: =CEILING(R95/$S$75,20) -> 2100 | U95: Match throw add additional $588, auto add $2134, Add $500 for Copper
G96: =+F96*1.03 -> 0 | H96: =G96*(1+$H$2) -> 0 | N96: 0 | O96: =O95 -> 85 | P96: =P95 -> 250 | Q96: =$N$102 -> 15 | R96: =SUM(N96:Q96) -> 350 | S96: =CEILING(R96/$S$75,20) -> 500 | U96: Match throw add additional $588, auto add $2134, Add $500 for Copper
M97: No LED Bubbler
M98: LED Bubbler, Includes Bubbler and Light. Need light run and water feature run | N98: 780 | O98: =O96 -> 85 | P98: 75 | Q98: =$N$102 -> 15 | R98: =SUM(N98:Q98) -> 955 | S98: =CEILING(R98/$S$75,20) -> 1380
A99: Automation | G99: =+F99*1.03 -> 0 | H99: =G99*(1+$H$2) -> 0
G100: =+F100*1.03 -> 0 | H100: =G100*(1+$H$2) -> 0 | M100: Delivery - First Wok | N100: 240
A101: JDY-30-3014 | B101: PDA-P4 | C101: PDA POOL ONLY P4 | D101: 479.03 | E101: =D101*1.082 -> 518.31046 | F101: 581 | G101: =+F101*1.03 -> 598.43 | H101: =G101*(1+$H$2) -> 646.3044 | I101: =H101/$I$2 -> 936.67304 | M101: Delivery - Each Additional | N101: 100
A102: JDY-30-3018 | B102: PDA-P8 | C102: PDA POOL ONLY P8 | D102: 912.79 | E102: =D102*1.082 -> 987.63878 | F102: 1019.71 | G102: =+F102*1.03 -> 1050.3013 | H102: =G102*(1+$H$2) -> 1134.3254 | I102: =H102/$I$2 -> 1643.9499 | M102: Materials | N102: 15
...

Sheet CLEAN
A1: 44562
A3: CLEAN-UP
A4: Base: | B4: 700 | C4: 1 | D4: =B4*C4 -> 700
A5: Add'l Over 500: | B5: 0.5 | C5: =IF('NEW POOL'!B8>500,'NEW POOL'!B8-500,0) -> 76 | D5: =B5*C5 -> 38
A6: Spa: | B6: 100 | C6: =EXC!C27 -> 0 | D6: =B6*C6 -> 0
A7: RBB: | B7: 2.5 | C7: ='NEW POOL'!B38 -> 0 | D7: =B7*C7 -> 0
A8: Travel: | B8: 7 | C8: ='NEW POOL'!E10 -> 0 | D8: =B8*C8 -> 0
D10: =SUM(D4:D9) -> 738
A12: Remodel: | B12: 350
A13: Remodel - w/ Deck: | B13: 600

Sheet FIBER
A1: MARCH 2022
H2: A | I2: B | J2: C | K2: D | L2: E | M2: F | N2: G | P2: 1 | Q2: 2 | R2: 3 | T2: 4 | U2: 5 | V2: 6 | W2: 7 | X2: 8
C3: 2020 | D3: 2021 | E3: 2024 | F3: QTY | G3: Total | H3: Perimeter | I3: Surface | J3: Width | K3: Length | L3: Shallow | M3: Deep | N3: Gallons | P3: Name | Q3: Shell | R3: Freight | S3: Surcharge | T3: Shell Total | U3: Crane | V3: Install | W3: Gravel | X3: Total
A4: SMALL POOLS | B4: Fiberglass - Small | C4: 0 | D4: =C4 -> 0 | E4: 0 | F4: =IF('NEW POOL'!$A$21=B4,1,0) -> 1 | G4: =E4*F4 -> 0 | H4: 0 | I4: 0 | J4: 0 | K4: 0 | L4: 0 | M4: 0 | P4: =B4 -> Fiberglass - Small | Q4: =C4 -> 0 | R4: 0 | T4: =SUM(Q4:S4) -> 0 | U4: 0 | V4: 0 | W4: - | X4: =SUM(T4:W4) -> 0 | Z4: =VLOOKUP('NEW POOL'!A$21,FIBER!B$4:M$9,5,FALSE) -> 1
B5: Caeser | C5: 10242 | D5: =13603+1225 -> 14828 | E5: 11325 | F5: =IF('NEW POOL'!$A$21=B5,1,0) -> 0 | G5: =E5*F5 -> 0 | H5: 48 | I5: 135 | J5: 10 | K5: 16 | L5: 4 | M5: 4 | N5: 2450 | O5: =F5*N5 -> 0 | P5: =B5 -> Caeser | Q5: =E5 -> 11325 | R5: =$C$62 -> 950 | S5: =C65 -> 0 | T5: =SUM(Q5:S5) -> 12275 | U5: =$C$67 -> 550 | V5: =$C$71 -> 9000 | W5: =$C$75 -> 1900 | X5: =SUM(T5:W5) -> 23725 | Z5: =VLOOKUP('NEW POOL'!A$21,FIBER!B$4:M$9,6,FALSE) -> 0
B6: Chateau & Gayla 12 | C6: 13857 | D6: =16168+1456 -> 17624 | E6: 14825 | F6: =IF('NEW POOL'!$A$21=B6,1,0) -> 0 | G6: =E6*F6 -> 0 | H6: 70 | I6: 264 | J6: 11.833 | K6: 25.417 | L6: 4.5 | M6: 4.5 | N6: 8100 | O6: =F6*N6 -> 0 | P6: =B6 -> Chateau & Gayla 12 | Q6: =E6 -> 14825 | R6: =$C$62 -> 950 | S6: =S5 -> 0 | T6: =SUM(Q6:S6) -> 15775 | U6: =$C$67 -> 550 | V6: =$C$71 -> 9000 | W6: =$C$75 -> 1900 | X6: =SUM(T6:W6) -> 27225 | Z6: =VLOOKUP('NEW POOL'!A$21,FIBER!B$4:M$9,7,FALSE) -> 0
B7: Gayla 12/Freeport | C7: 8727 | D7: =16168+1456 -> 17624 | E7: 14375 | F7: =IF('NEW POOL'!$A$21=B7,1,0) -> 0 | G7: =E7*F7 -> 0 | H7: 64 | I7: 214 | J7: 12 | K7: 26 | L7: 4 | M7: 5 | N7: 5300 | O7: =F7*N7 -> 0 | P7: =B7 -> Gayla 12/Freeport | Q7: =E7 -> 14375 | R7: =$C$62 -> 950 | S7: =S5 -> 0 | T7: =SUM(Q7:S7) -> 15325 | U7: =$C$67 -> 550 | V7: =$C$71 -> 9000 | W7: =$C$75 -> 1900 | X7: =SUM(T7:W7) -> 26775 | Z7: =VLOOKUP('NEW POOL'!A$21,FIBER!B$4:M$9,8,FALSE) -> 0
B8: Lotus 12/Bermuda | C8: 11631 | D8: =9490+854 -> 10344 | E8: 15375 | F8: =IF('NEW POOL'!$A$21=B8,1,0) -> 0 | G8: =E8*F8 -> 0 | H8: 73 | I8: 209 | J8: 12 | K8: 26 | L8: 3 | M8: 4.583 | N8: 4400 | O8: =F8*N8 -> 0 | P8: =B8 -> Lotus 12/Bermuda | Q8: =E8 -> 15375 | R8: =$C$62 -> 950 | S8: =S5 -> 0 | T8: =SUM(Q8:S8) -> 16325 | U8: =$C$67 -> 550 | V8: =$C$71 -> 9000 | W8: =$C$75 -> 1900 | X8: =SUM(T8:W8) -> 27775 | Z8: =VLOOKUP('NEW POOL'!A$21,FIBER!B$4:M$9,9,FALSE) -> 0
B9: Santorini & Bliss 12 | C9: 12409 | D9: =11699+1053 -> 12752 | E9: 12825 | F9: =IF('NEW POOL'!$A$21=B9,1,0) -> 0 | G9: =E9*F9 -> 0 | H9: 59 | I9: 177 | J9: 11 | K9: 22 | L9: 3.5 | M9: 5 | N9: 5200 | O9: =F9*N9 -> 0 | P9: =B9 -> Santorini & Bliss 12 | Q9: =E9 -> 12825 | R9: =$C$62 -> 950 | S9: =S5 -> 0 | T9: =SUM(Q9:S9) -> 13775 | U9: =$C$67 -> 550 | V9: =$C$71 -> 9000 | W9: =$C$75 -> 1900 | X9: =SUM(T9:W9) -> 25225 | Z9: =VLOOKUP('NEW POOL'!A$21,FIBER!B$4:M$9,10,FALSE) -> 0
G10: =SUM(G4:G9) -> 0 | O10: =SUM(O4:O9) -> 0
A11: MEDIUM POOLS | B11: Fiberglass - Medium | C11: 0 | D11: =C11 -> 0 | E11: 0 | F11: =IF('NEW POOL'!$A$22=FIBER!P11,1,0) -> 1 | G11: =E11*F11 -> 0 | H11: =H4 -> 0 | I11: =I4 -> 0 | J11: =J4 -> 0 | K11: =K4 -> 0 | L11: =L4 -> 0 | M11: =M4 -> 0 | O11: =F11*N11 -> 0 | P11: =B11 -> Fiberglass - Medium | Q11: =C11 -> 0 | R11: 0 | T11: =SUM(Q11:S11) -> 0 | U11: 0 | V11: 0 | W11: 0 | X11: =SUM(T11:W11) -> 0 | Z11: =VLOOKUP('NEW POOL'!A$22,FIBER!B$11:M$18,5,FALSE) -> 1
B12: Belvedere | C12: 13838 | D12: =16945+1526 -> 18471 | E12: 22801 | F12: =IF('NEW POOL'!$A$22=FIBER!P12,1,0) -> 0 | G12: =E12*F12 -> 0 | H12: 84 | I12: 377 | J12: 14 | K12: 30 | L12: 3.5 | M12: 6 | N12: 11200 | O12: =F12*N12 -> 0 | P12: =B12 -> Belvedere | Q12: =E12 -> 22801 | R12: =$C$63 -> 1100 | S12: =S5 -> 0 | T12: =SUM(Q12:S12) -> 23901 | U12: =$C$68 -> 1700 | V12: =$C$72 -> 9000 | W12: =$C$76 -> 2650 | X12: =SUM(T12:W12) -> 37251 | Z12: =VLOOKUP('NEW POOL'!A$22,FIBER!B$11:M$18,6,FALSE) -> 0
B13: Martinique Grand | C13: 14917 | D13: =20918+1883 -> 22801 | E13: 23825 | F13: =IF('NEW POOL'!$A$22=FIBER!P13,1,0) -> 0 | G13: =E13*F13 -> 0 | H13: 92 | I13: 300 | J13: 14 | K13: 30 | L13: 4 | M13: 6 | N13: 9000 | O13: =F13*N13 -> 0 | P13: =B13 -> Martinique Grand | Q13: =E13 -> 23825 | R13: =$C$63 -> 1100 | S13: =S12 -> 0 | T13: =SUM(Q13:S13) -> 24925 | U13: =$C$68 -> 1700 | V13: =$C$72 -> 9000 | W13: =$C$76 -> 2650 | X13: =SUM(T13:W13) -> 38275 | Z13: =VLOOKUP('NEW POOL'!A$22,FIBER!B$11:M$18,7,FALSE) -> 0
B14: Noveau 14 | C14: 14482 | D14: =18222+1640 -> 19862 | E14: 23625 | F14: =IF('NEW POOL'!$A$22=FIBER!P14,1,0) -> 0 | G14: =E14*F14 -> 0 | H14: 83 | I14: 347 | J14: 14 | K14: 30 | L14: 3.5 | M14: 6 | N14: 8800 | O14: =F14*N14 -> 0 | P14: =B14 -> Noveau 14 | Q14: =E14 -> 23625 | R14: =$C$63 -> 1100 | S14: =S13 -> 0 | T14: =SUM(Q14:S14) -> 24725 | U14: =$C$68 -> 1700 | V14: =$C$72 -> 9000 | W14: =$C$76 -> 2650 | X14: =SUM(T14:W14) -> 38075 | Z14: =VLOOKUP('NEW POOL'!A$22,FIBER!B$11:M$18,8,FALSE) -> 0
B15: Lotus 14 | C15: 15012 | D15: =20918+1883 -> 22801 | E15: 20650 | F15: =IF('NEW POOL'!$A$22=FIBER!P15,1,0) -> 0 | G15: =E15*F15 -> 0 | H15: 74 | I15: 310 | J15: 14 | K15: 30 | L15: 3.5 | M15: 6 | N15: 10000 | O15: =F15*N15 -> 0 | P15: =B15 -> Lotus 14 | Q15: =E15 -> 20650 | R15: =$C$63 -> 1100 | S15: =S14 -> 0 | T15: =SUM(Q15:S15) -> 21750 | U15: =$C$68 -> 1700 | V15: =$C$72 -> 9000 | W15: =$C$76 -> 2650 | X15: =SUM(T15:W15) -> 35100 | Z15: =VLOOKUP('NEW POOL'!A$22,FIBER!B$11:M$18,9,FALSE) -> 0
B16: Renaissance 14 | C16: 15347 | D16: =14350+1292 -> 15642 | E16: 23625 | F16: =IF('NEW POOL'!$A$22=FIBER!P16,1,0) -> 0 | G16: =E16*F16 -> 0 | H16: 81 | I16: 678 | J16: 14 | K16: 30 | L16: 3.5 | M16: 6 | N16: 7600 | O16: =F16*N16 -> 0 | P16: =B16 -> Renaissance 14 | Q16: =E16 -> 23625 | R16: =$C$63 -> 1100 | S16: =S13 -> 0 | T16: =SUM(Q16:S16) -> 24725 | U16: =$C$68 -> 1700 | V16: =$C$72 -> 9000 | W16: =$C$76 -> 2650 | X16: =SUM(T16:W16) -> 38075
B17: Sovereign & Gayla 14 | C17: 18475 | D17: 18475 | E17: 21275 | F17: =IF('NEW POOL'!$A$22=FIBER!P17,1,0) -> 0 | G17: =E17*F17 -> 0 | H17: 90 | I17: 416 | J17: 14 | K17: 33 | L17: 3.583 | M17: 5.333 | N17: 11700 | O17: =F17*N17 -> 0 | P17: =B17 -> Sovereign & Gayla 14 | Q17: =E17 -> 21275 | R17: =$C$63 -> 1100 | S17: =S14 -> 0 | T17: =SUM(Q17:S17) -> 22375 | U17: =$C$68 -> 1700 | V17: =$C$72 -> 9000 | W17: =$C$76 -> 2650 | X17: =SUM(T17:W17) -> 35725
B18: Belvedere/Olympia 14 | C18: 15347 | D18: =14350+1292 -> 15642 | E18: 24100 | F18: =IF('NEW POOL'!$A$22=FIBER!P18,1,0) -> 0 | G18: =E18*F18 -> 0 | H18: 85 | I18: 377 | J18: 14 | K18: 30 | L18: 3.6 | M18: 6 | N18: 11200 | O18: =F18*N18 -> 0 | P18: =B18 -> Belvedere/Olympia 14 | Q18: =E18 -> 24100 | R18: =$C$63 -> 1100 | S18: =S15 -> 0 | T18: =SUM(Q18:S18) -> 25200 | U18: =$C$68 -> 1700 | V18: =$C$72 -> 9000 | W18: =$C$76 -> 2650 | X18: =SUM(T18:W18) -> 38550 | Z18: =VLOOKUP('NEW POOL'!A$22,FIBER!B$11:M$18,10,FALSE) -> 0
G19: =SUM(G11:G18) -> 0 | O19: =SUM(O11:O18) -> 0
A20: LARGE POOLS | B20: Fiberglass - Large | C20: 0 | D20: 0 | E20: 0 | F20: =IF('NEW POOL'!$A$23=FIBER!P20,1,0) -> 1 | G20: =E20*F20 -> 0 | H20: =H11 -> 0 | I20: =I11 -> 0 | J20: =J11 -> 0 | K20: =K11 -> 0 | L20: =L11 -> 0 | M20: =M11 -> 0 | P20: =B20 -> Fiberglass - Large | Q20: =C20 -> 0 | R20: =R11 -> 0 | T20: =Q20+R20 -> 0 | U20: =U11 -> 0 | V20: =V11 -> 0 | W20: =W11 -> 0 | X20: =X11 -> 0 | Z20: =VLOOKUP('NEW POOL'!A$23,FIBER!B$20:M$30,5,FALSE) -> 1
B21: Genesis | C21: 28150 | D21: 28150 | E21: 28150 | F21: =IF('NEW POOL'!$A$23=FIBER!P21,1,0) -> 0 | G21: =E21*F21 -> 0 | H21: 104 | I21: 555 | J21: 16 | K21: 38 | L21: 3.5 | M21: 5.833 | N21: 17500 | O21: =F21*N21 -> 0 | P21: =B21 -> Genesis | Q21: =E21 -> 28150 | R21: =$C$64 -> 1200 | S21: =S18 -> 0 | T21: =SUM(Q21:S21) -> 29350 | U21: =$C$69 -> 2300 | V21: =$C$73 -> 9000 | W21: =$C$77 -> 3110 | X21: =SUM(T21:W21) -> 43760 | Z21: =VLOOKUP('NEW POOL'!A$23,FIBER!B$20:M$30,6,FALSE) -> 0
B22: Monaco | C22: 31100 | D22: 31100 | E22: 31100 | F22: =IF('NEW POOL'!$A$23=FIBER!P22,1,0) -> 0 | G22: =E22*F22 -> 0 | H22: 101 | I22: 518 | J22: 16 | K22: 37.833 | L22: 3.5 | M22: 7 | N22: 18500 | O22: =F22*N22 -> 0 | P22: =B22 -> Monaco | Q22: =E22 -> 31100 | R22: =$C$64 -> 1200 | S22: =S21 -> 0 | T22: =SUM(Q22:S22) -> 32300 | U22: =$C$69 -> 2300 | V22: =$C$73 -> 9000 | W22: =$C$77 -> 3110 | X22: =SUM(T22:W22) -> 46710 | Z22: =VLOOKUP('NEW POOL'!A$23,FIBER!B$20:M$30,7,FALSE) -> 0
B23: Elysium Grand | C23: 20551 | D23: =20740+1867 -> 22607 | E23: 25600 | F23: =IF('NEW POOL'!$A$23=FIBER!P23,1,0) -> 0 | G23: =E23*F23 -> 0 | H23: 114 | I23: 381 | J23: 16 | K23: 35 | L23: 4.25 | M23: 6.5 | N23: 11500 | O23: =F23*N23 -> 0 | P23: =B23 -> Elysium Grand | Q23: =E23 -> 25600 | R23: =$C$64 -> 1200 | S23: =S22 -> 0 | T23: =SUM(Q23:S23) -> 26800 | U23: =$C$69 -> 2300 | V23: =$C$73 -> 9000 | W23: =$C$77 -> 3110 | X23: =SUM(T23:W23) -> 41210 | Z23: =VLOOKUP('NEW POOL'!A$23,FIBER!B$20:M$30,8,FALSE) -> 0
B24: Grand Palace | C24: 18301 | D24: =24700+2223 -> 26923 | E24: 30000 | F24: =IF('NEW POOL'!$A$23=FIBER!P24,1,0) -> 0 | G24: =E24*F24 -> 0 | H24: 137 | I24: 548 | J24: 15.833 | K24: 40 | L24: 3.5 | M24: 7 | N24: 15600 | O24: =F24*N24 -> 0 | P24: =B24 -> Grand Palace | Q24: =E24 -> 30000 | R24: =$C$64 -> 1200 | S24: =S23 -> 0 | T24: =SUM(Q24:S24) -> 31200 | U24: =$C$69 -> 2300 | V24: =$C$73 -> 9000 | W24: =$C$77 -> 3110 | X24: =SUM(T24:W24) -> 45610 | Z24: =VLOOKUP('NEW POOL'!A$23,FIBER!B$20:M$30,9,FALSE) -> 0
B25: Imperial | C25: 21883 | D25: =25271+2275 -> 27546 | E25: 21700 | F25: =IF('NEW POOL'!$A$23=FIBER!P25,1,0) -> 0 | G25: =E25*F25 -> 0 | H25: 94 | I25: 480 | J25: 16 | K25: 33 | L25: 3.583 | M25: 5.417 | N25: 15000 | O25: =F25*N25 -> 0 | P25: =B25 -> Imperial | Q25: =E25 -> 21700 | R25: =$C$64 -> 1200 | S25: =S24 -> 0 | T25: =SUM(Q25:S25) -> 22900 | U25: =$C$69 -> 2300 | V25: =$C$73 -> 9000 | W25: =$C$77 -> 3110 | X25: =SUM(T25:W25) -> 37310 | Z25: =VLOOKUP('NEW POOL'!A$23,FIBER!B$20:M$30,10,FALSE) -> 0
B26: Gayla 16 | C26: 19777 | D26: =21032+1893 -> 22925 | E26: 24000 | F26: =IF('NEW POOL'!$A$23=FIBER!P26,1,0) -> 0 | G26: =E26*F26 -> 0 | H26: 96 | I26: 468 | J26: 16 | K26: 40 | L26: 3.5 | M26: 6.5 | N26: 17000 | O26: =F26*N26 -> 0 | P26: =B26 -> Gayla 16 | Q26: =E26 -> 24000 | R26: =$C$64 -> 1200 | S26: =S25 -> 0 | T26: =SUM(Q26:S26) -> 25200 | U26: =$C$69 -> 2300 | V26: =$C$73 -> 9000 | W26: =$C$77 -> 3110 | X26: =SUM(T26:W26) -> 39610
B27: Oasis 16 | C27: 15135 | D27: =22995+2069 -> 25064 | E27: 23300 | F27: =IF('NEW POOL'!$A$23=FIBER!P27,1,0) -> 0 | G27: =E27*F27 -> 0 | H27: 87 | I27: 395 | J27: 16 | K27: 35 | L27: 4.5 | M27: 6.5 | N27: 11600 | O27: =F27*N27 -> 0 | P27: =B27 -> Oasis 16 | Q27: =E27 -> 23300 | R27: =$C$64 -> 1200 | S27: =S26 -> 0 | T27: =SUM(Q27:S27) -> 24500 | U27: =$C$69 -> 2300 | V27: =$C$73 -> 9000 | W27: =$C$77 -> 3110 | X27: =SUM(T27:W27) -> 38910
B28: Gayla XDL | E28: 27725 | F28: =IF('NEW POOL'!$A$23=FIBER!P28,1,0) -> 0 | G28: =E28*F28 -> 0 | H28: 83 | I28: 375 | J28: 15 | K28: 34 | L28: 3.5 | M28: 6 | N28: 12000 | O28: =F28*N28 -> 0 | P28: =B28 -> Gayla XDL | Q28: =E28 -> 27725 | R28: =$C$64 -> 1200 | S28: =S27 -> 0 | T28: =SUM(Q28:S28) -> 28925 | U28: =$C$69 -> 2300 | V28: =$C$73 -> 9000 | W28: =$C$77 -> 3110 | X28: =SUM(T28:W28) -> 43335
B29: Versailles | E29: 30500 | F29: =IF('NEW POOL'!$A$23=FIBER!P29,1,0) -> 0 | G29: =E29*F29 -> 0 | H29: 108 | I29: 585 | J29: 16 | K29: 40 | L29: 3.667 | M29: 8 | N29: 21000 | O29: =F29*N29 -> 0 | P29: =B29 -> Versailles | Q29: =E29 -> 30500 | R29: =$C$64 -> 1200 | S29: =S28 -> 0 | T29: =SUM(Q29:S29) -> 31700 | U29: =$C$69 -> 2300 | V29: =$C$73 -> 9000 | W29: =$C$77 -> 3110 | X29: =SUM(T29:W29) -> 46110
B30: Villa Reale | C30: 22008 | D30: =23591+2124 -> 25715 | E30: 29600 | F30: =IF('NEW POOL'!$A$23=FIBER!P30,1,0) -> 0 | G30: =E30*F30 -> 0 | H30: 107 | I30: 563 | J30: 15.833 | K30: 40 | L30: 3.5 | M30: 7 | N30: 15400 | O30: =F30*N30 -> 0 | P30: =B30 -> Villa Reale | Q30: =E30 -> 29600 | R30: =$C$64 -> 1200 | S30: =S27 -> 0 | T30: =SUM(Q30:S30) -> 30800 | U30: =$C$69 -> 2300 | V30: =$C$73 -> 9000 | W30: =$C$77 -> 3110 | X30: =SUM(T30:W30) -> 45210
G31: =SUM(G20:G30) -> 0 | O31: =SUM(O20:O30) -> 0
B32: Standard Finish | C32: 0 | D32: =C32 -> 0 | E32: =D32 -> 0 | F32: =IF('NEW POOL'!A24=FIBER!B32,1,0) -> 1 | G32: =C32*F32 -> 0
B33: Crystite G2 | C33: 1000 | D33: 1000 | E33: 1000 | F33: =IF('NEW POOL'!A24=FIBER!B33,1,0) -> 0 | G33: =C33*F33 -> 0 | N33: Gallons: | O33: =O10+O19+O31 -> 0
B34: Crystite G3 | C34: 1500 | D34: 1500 | E34: 1500 | F34: =IF('NEW POOL'!A24=FIBER!B34,1,0) -> 0 | G34: =C34*F34 -> 0
A36: SPAS | B36: No Spa | C36: 0 | E36: 0 | F36: =IF('NEW POOL'!A25=FIBER!B36,1,0) -> 1 | G36: =C36*F36 -> 0
B37: Meridian | E37: 4794 | F37: =IF('NEW POOL'!A$25=FIBER!B37,1,0) -> 0 | G37: =D37*F37 -> 0
B38: Mystic | C38: 3379 | D38: =3814+350 -> 4164 | E38: 4575 | F38: =IF('NEW POOL'!A$25=FIBER!B38,1,0) -> 0 | G38: =D38*F38 -> 0
B39: Regal | C39: 0 | D39: 0 | E39: 5000 | F39: =IF('NEW POOL'!A$25=FIBER!B39,1,0) -> 0 | G39: =D39*F39 -> 0
B40: Royal | C40: 3226 | D40: =3641+330 -> 3971 | E40: 5000 | F40: =IF('NEW POOL'!A$25=FIBER!B40,1,0) -> 0 | G40: =D40*F40 -> 0
B41: Shasta | C41: 2610 | D41: =2947+266 -> 3213 | E41: 4150 | F41: =IF('NEW POOL'!A$25=FIBER!B41,1,0) -> 0 | G41: =D41*F41 -> 0
B42: Spillover | C42: 500 | D42: =C42*1.05 -> 525 | E42: 75 | F42: ='NEW POOL'!B26 -> 0 | G42: =D42*F42 -> 0 | P42: No Spillover
F43: Total: | G43: =SUM(G36:G42) -> 0 | P43: Add Spillover
B45: Standard Finish | C45: 0 | D45: =C45 -> 0 | E45: =D45 -> 0 | F45: =F32 -> 1 | G45: =C45*F45 -> 0
B46: Crystite G2 | C46: 500 | D46: =C46 -> 500 | E46: =D46 -> 500 | F46: =F33*P46 -> 0 | G46: =C46*F46 -> 0 | P46: ='NEW POOL'!B25 -> 0
B47: Crystite G3 | C47: 750 | D47: =C47 -> 750 | E47: =D47 -> 750 | F47: =F34*P47 -> 0 | G47: =C47*F47 -> 0 | P47: =P46 -> 0
A49: TANNING | B49: No Tanning | C49: 0 | D49: =C49 -> 0 | E49: 0 | F49: =IF('NEW POOL'!$A$27=FIBER!B49,1,0) -> 1 | G49: =E49*F49 -> 0
B50: Gemini | E50: 2838 | F50: =IF('NEW POOL'!$A$27=FIBER!B50,1,0) -> 0 | G50: =E50*F50 -> 0
B51: Genesis | E51: 4262 | F51: =IF('NEW POOL'!$A$27=FIBER!B51,1,0) -> 0 | G51: =E51*F51 -> 0
B52: Hermosa | C52: 3396 | D52: =3833+350 -> 4183 | E52: 3514 | F52: =IF('NEW POOL'!$A$27=FIBER!B52,1,0) -> 0 | G52: =E52*F52 -> 0
B53: Picasso | E53: 3264 | F53: =IF('NEW POOL'!$A$27=FIBER!B53,1,0) -> 0 | G53: =E53*F53 -> 0
B54: Rectangle | E54: 5205 | F54: =IF('NEW POOL'!$A$27=FIBER!B54,1,0) -> 0 | G54: =E54*F54 -> 0
B55: Semi-Circle | C55: 3396 | D55: =3833+350 -> 4183 | E55: 4805 | F55: =IF('NEW POOL'!$A$27=FIBER!B55,1,0) -> 0 | G55: =E55*F55 -> 0
F56: Total: | G56: =SUM(G49:G55) -> 0
B58: Standard Finish | C58: 0 | D58: =C58 -> 0 | E58: =D58 -> 0 | F58: =F45 -> 1 | G58: 0
B59: Crystite G2 | C59: 500 | D59: =C59 -> 500 | E59: =D59 -> 500 | F59: =F33*P59 -> 0 | G59: =C59*F59 -> 0 | P59: ='NEW POOL'!B27 -> 0
B60: Crystite G3 | C60: 750 | D60: =C60 -> 750 | E60: =D60 -> 750 | F60: =P60*F34 -> 0 | G60: =C60*F60 -> 0 | P60: =P59 -> 0
B62: Freight - Small | C62: 950 | D62: =C62 -> 950 | E62: =D62 -> 950 | F62: ='NEW POOL'!B21 -> 0 | G62: =E62*F62 -> 0
B63: Freight - Medium | C63: 1100 | D63: =C63 -> 1100 | E63: =D63 -> 1100 | F63: ='NEW POOL'!B22 -> 0 | G63: =E63*F63 -> 0
B64: Freight - Large | C64: 1200 | D64: =C64 -> 1200 | E64: =D64 -> 1200 | F64: ='NEW POOL'!B23 -> 0 | G64: =E64*F64 -> 0
B65: 2023 Surcharge | C65: 0 | D65: =C65 -> 0 | E65: 0 | F65: 0 | G65: =E65*F65 -> 0
B66: No Crane | C66: 150 | D66: =C66 -> 150 | E66: =D66 -> 150 | F66: =IF('NEW POOL'!B28=0,1,0) -> 1 | G66: =E66*F66 -> 150 | P66: No Crane | Q66: No Crane
B67: Crane - Small | C67: 550 | D67: =C67 -> 550 | E67: =D67 -> 550 | F67: =U67 -> 0 | G67: =E67*F67 -> 0 | P67: Crane Required | Q67: =B67 -> Crane - Small | R67: =IF('NEW POOL'!A28="Crane - Small",1,0) -> 0 | T67: =IF(F$66=1,0,1) -> 0 | U67: =R67*T67 -> 0
B68: Crane - Medium | C68: 1700 | D68: =C68 -> 1700 | E68: 2000 | F68: =U68 -> 0 | G68: =E68*F68 -> 0 | Q68: =B68 -> Crane - Medium | R68: =IF('NEW POOL'!A28="Crane - Medium",1,0) -> 0 | T68: =IF(F$66=1,0,1) -> 0 | U68: =R68*T68 -> 0
B69: Crane - Large | C69: 2300 | D69: =C69 -> 2300 | E69: 2600 | F69: =U69 -> 0 | G69: =E69*F69 -> 0 | Q69: =B69 -> Crane - Large | R69: =IF('NEW POOL'!A28="Crane - Large",1,0) -> 0 | T69: =IF(F$66=1,0,1) -> 0 | U69: =R69*T69 -> 0
B70: Crane - Spa | C70: 150 | D70: =C70 -> 150 | E70: =D70 -> 150 | F70: ='NEW POOL'!B25 -> 0 | G70: =E70*F70 -> 0
B71: Install - Small | C71: 9000 | D71: =C71 -> 9000 | E71: 9000 | F71: =F62 -> 0 | G71: =E71*F71 -> 0
B72: Install - Medium | C72: 9000 | D72: =C72 -> 9000 | E72: 9000 | F72: =F63 -> 0 | G72: =E72*F72 -> 0
B73: Install - Large | C73: 9000 | D73: =C73 -> 9000 | E73: =D73 -> 9000 | F73: =F64 -> 0 | G73: =E73*F73 -> 0
B74: Install - Spa | C74: 2600 | D74: =C74 -> 2600 | E74: 2600 | F74: =SUM(F38:F41) -> 0 | G74: =E74*F74 -> 0
B75: Gravel - Small | C75: 1900 | D75: =C75 -> 1900 | E75: 1900 | F75: =F71 -> 0 | G75: =E75*F75 -> 0
B76: Gravel - Medium | C76: 2650 | D76: =C76 -> 2650 | E76: =D76 -> 2650 | F76: =F72 -> 0 | G76: =E76*F76 -> 0 | R76: PVC | T76: STONE | U76: WATER | V76: LABOR | W76: FREIGHT
B77: Gravel - Large | C77: 3110 | D77: =C77 -> 3110 | E77: =D77 -> 3110 | F77: =F73 -> 0 | G77: =E77*F77 -> 0 | Q77: Small | R77: 1306 | T77: 2058 | U77: 396 | V77: 7000 | W77: 450
B78: Water - Small | C78: 980 | D78: =C78 -> 980 | E78: =D78 -> 980 | F78: =F62 -> 0 | G78: =E78*F78 -> 0 | Q78: Small | R78: 1190 | T78: 1467 | U78: 375 | V78: 7000 | W78: 600
B79: Water - Medium | C79: 1470 | D79: =C79 -> 1470 | E79: =D79 -> 1470 | F79: =F63 -> 0 | G79: =E79*F79 -> 0
B80: Water - Large | C80: 1470 | D80: =C80 -> 1470 | E80: =D80 -> 1470 | F80: =F64 -> 0 | G80: =E80*F80 -> 0
B81: Slurry Beam | C81: 8 | D81: =C81 -> 8 | E81: =D81 -> 8 | G81: =E81*F81 -> 0 | I81: =IF(('NEW POOL'!B85+'NEW POOL'!B87+'NEW POOL'!B90)>1,0,1) -> 1 | Q81: Small | R81: 1177 | T81: 2154 | U81: 405 | V81: 7000 | W81: 620 | X81: Spa +$600
B82: Equipment Pad | C82: 250 | D82: =C82 -> 250 | E82: =D82 -> 250 | Q82: Small | R82: 738 | T82: 1324 | U82: 375 | V82: 7000 | W82: 600
Q86: Large | R86: 900 | T86: 2922 | U86: 705 | V86: 7000 | W86: 0

Sheet MISC
A1: MARCH 2022
A3: START-UP
A5: Start-Up & 30 Days: | B5: 700 | C5: 1 | D5: =B5*C5 -> 700
A6: Add Automation: | B6: 300 | C6: ='NEW POOL'!B131 -> 1 | D6: =B6*C6 -> 300
A7: Premium Start-Up: | B7: 800 | C7: ='NEW POOL'!B179 -> 0 | D7: =B7*C7 -> 0
A9: Total: | D9: =SUM(D5:D8) -> 1000
A11: DRAINAGE
F12: Base | G12: LNFT | H12: Add'l | I12: Base | J12: Add'l | K12: Total | M12: Drainage
A13: ='NEW POOL'!A104 -> Downspout Total LF from all | C13: =G13 -> 0 | D13: =K13 -> 0 | F13: =IF('NEW POOL'!B104>0,1,0) -> 0 | G13: ='NEW POOL'!B104 -> 0 | H13: =IF(G13<11,0,G13-$O$13) -> 0 | I13: =F13*$M$13 -> 0 | J13: =H13*$M$14 -> 0 | K13: =I13+J13 -> 0 | M13: 150 | N13: Base | O13: 10 | P13: LNFT Included
A14: ='NEW POOL'!A105 -> Deck Drain Total LF | C14: =G14 -> 0 | D14: =K14 -> 0 | F14: =IF('NEW POOL'!B105>0,1,0) -> 0 | G14: ='NEW POOL'!B105 -> 0 | H14: =IF(G14<11,0,G14-$O$13) -> 0 | I14: =F14*$M$13 -> 0 | J14: =H14*$M$14 -> 0 | K14: =I14+J14 -> 0 | M14: 12.5
A15: ='NEW POOL'!A106 -> French Drain Total LF | C15: =G15 -> 0 | D15: =K15 -> 0 | F15: =IF('NEW POOL'!B106>0,1,0) -> 0 | G15: ='NEW POOL'!B106 -> 0 | H15: =IF(G15<11,0,G15-$O$13) -> 0 | I15: =F15*$M$13 -> 0 | J15: =H15*$M$14 -> 0 | K15: =I15+J15 -> 0
A16: ='NEW POOL'!A107 -> Box Drain Total LF | C16: =G16 -> 0 | D16: =K16 -> 0 | F16: =IF('NEW POOL'!B107>0,1,0) -> 0 | G16: ='NEW POOL'!B107 -> 0 | H16: =IF(G16<11,0,G16-$O$13) -> 0 | I16: =F16*$M$13 -> 0 | J16: =H16*$M$14 -> 0 | K16: =I16+J16 -> 0
A18: Total: | D18: =SUM(D13:D15) -> 0
A20: WATER TRUCK
A22: Base - 7,000 Gallons | B22: 490 | C22: 1 | D22: =B22*C22 -> 490
A23: Add'l Truck | B23: =B22 -> 490 | C23: ='NEW POOL'!B177 -> 1 | D23: =B23*C23 -> 490
